Workbook

Sheet Arbitrage
A1: Date | B1: Sportsbook1(F) | C1: Sportsbook2(U) | D1: Prop(F/U) | E1: Line1(F) | F1: Line2(U) | G1: FreeRollPick(F/U) | H1: EvenProfitMargin | I1: FreeRollProfitMargin | J1: TotalAmountWagering | K1: EvenAmount1(F) | L1: EvenAmount2(U) | M1: EvenProfit | N1: FreeRollAmount1(F) | O1: FreeRollAmount2(U) | P1: FreeRollProfit | Q1: E/F? (EvenProfit/FreeRoll) | R1: Event(F/U)? | S1: PROFIT REALIZED | U1: TOTAL PROFIT | X1: DATE | Y1: PROFIT | AA1: ACCOUNTS | AB1: START | AC1: END
A2: 45236 | B2: Fanduel | C2: Betano | D2: Justin Herbert Rushing Attempts (U/O 3.5) | E2: -114 | F2: 125 | G2: F | H2: =IF(E2<0,100*(E2+F2)/(10000-200*E2-E2*F2),IF(E2>0,(E2*F2-10000)/(100*(E2+F2+200)),0)) -> 0.023379384 | I2: =IF(E2<0,IF(G2="F",-100*(E2+F2)/(E2*(F2+100)),IF(G2="U",-(F2+E2)/(E2-100),0)),IF(E2>0,IF(G2="F",(E2*F2-10000)/(100*F2+10000),IF(G2="U",(E2*F2-10000)/(100*E2+10000),0)),0)) -> 0.04288499 | J2: 1125 | K2: =IF(E2<0,(H2*J2*-E2*(1+F2/100))/(E2+F2),(100*H2*J2*(100+F2))/(E2*F2-10000)) -> 613.31031 | L2: =IF(E2<0,((100-E2)*H2*J2)/(E2+F2),100*((100+E2)*H2*J2)/(E2*F2-10000)) -> 511.68969 | M2: =H2*J2 -> 26.301807 | N2: =IF(G2="F",(F2*J2)/(100+F2),IF(G2="U",IF(E2<0,(-E2*J2)/(100-E2),IF(E2>0,(100*J2)/(E2+100),0)),0)) -> 625 | O2: =IF(AND(G2="F",E2<>""),(100*J2)/(100+F2),IF(G2="U",IF(E2<0,(100*J2)/(100-E2),IF(E2>0,(E2*J2)/(E2+100),0)),0)) -> 500 | P2: =I2*J2 -> 48.245614 | Q2: F | R2: F | S2: =IF((Q2="F"),IF(R2=G2,P2,0),IF(Q2="E",M2,0)) -> 48.245614 | U2: =SUM(S:S) -> 2130.9386 | W2: WEEK 1 | X2: 45236 | Y2: {=SUM(_xlfn._xlws.FILTER(S:S,A:A=X2,0))} -> 48.245614 | AA2: SCOTIA | AB2: 15800 | AC2: 4289.91
A3: 45236 | B3: Fanduel | C3: Betano | D3: Vancouver Cancucks/Edmonton Oilers | E3: 100 | F3: 102 | G3: U | H3: =IF(E3<0,100*(E3+F3)/(10000-200*E3-E3*F3),IF(E3>0,(E3*F3-10000)/(100*(E3+F3+200)),0)) -> 0.0049751244 | I3: =IF(E3<0,IF(G3="F",-100*(E3+F3)/(E3*(F3+100)),IF(G3="U",-(F3+E3)/(E3-100),0)),IF(E3>0,IF(G3="F",(E3*F3-10000)/(100*F3+10000),IF(G3="U",(E3*F3-10000)/(100*E3+10000),0)),0)) -> 0.01 | J3: 2000 | K3: =IF(E3<0,(H3*J3*-E3*(1+F3/100))/(E3+F3),(100*H3*J3*(100+F3))/(E3*F3-10000)) -> 1004.9751 | L3: =IF(E3<0,((100-E3)*H3*J3)/(E3+F3),100*((100+E3)*H3*J3)/(E3*F3-10000)) -> 995.02488 | M3: =H3*J3 -> 9.9502488 | N3: =IF(G3="F",(F3*J3)/(100+F3),IF(G3="U",IF(E3<0,(-E3*J3)/(100-E3),IF(E3>0,(100*J3)/(E3+100),0)),0)) -> 1000 | O3: =IF(AND(G3="F",E3<>""),(100*J3)/(100+F3),IF(G3="U",IF(E3<0,(100*J3)/(100-E3),IF(E3>0,(E3*J3)/(E3+100),0)),0)) -> 1000 | P3: =I3*J3 -> 20 | Q3: F | R3: F | S3: =IF((Q3="F"),IF(R3=G3,P3,0),IF(Q3="E",M3,0)) -> 0 | U3: WAGERED | W3: =SUM(Y2:Y7) -> 141.99561 | X3: 45237 | Y3: {=SUM(_xlfn._xlws.FILTER(S:S,A:A=X3,0))} -> 0 | AA3: Bet365 | AB3: 0 | AC3: 4394.46
A4: 45238 | B4: DraftKings | C4: Bet365 | D4: Lauri Markkanen Threes Made (U/O 3.5) | E4: 100 | F4: 110 | G4: U | H4: =IF(E4<0,100*(E4+F4)/(10000-200*E4-E4*F4),IF(E4>0,(E4*F4-10000)/(100*(E4+F4+200)),0)) -> 0.024390244 | I4: =IF(E4<0,IF(G4="F",-100*(E4+F4)/(E4*(F4+100)),IF(G4="U",-(F4+E4)/(E4-100),0)),IF(E4>0,IF(G4="F",(E4*F4-10000)/(100*F4+10000),IF(G4="U",(E4*F4-10000)/(100*E4+10000),0)),0)) -> 0.05 | J4: 1000 | K4: =IF(E4<0,(H4*J4*-E4*(1+F4/100))/(E4+F4),(100*H4*J4*(100+F4))/(E4*F4-10000)) -> 512.19512 | L4: =IF(E4<0,((100-E4)*H4*J4)/(E4+F4),100*((100+E4)*H4*J4)/(E4*F4-10000)) -> 487.80488 | M4: =H4*J4 -> 24.390244 | N4: =IF(G4="F",(F4*J4)/(100+F4),IF(G4="U",IF(E4<0,(-E4*J4)/(100-E4),IF(E4>0,(100*J4)/(E4+100),0)),0)) -> 500 | O4: =IF(AND(G4="F",E4<>""),(100*J4)/(100+F4),IF(G4="U",IF(E4<0,(100*J4)/(100-E4),IF(E4>0,(E4*J4)/(E4+100),0)),0)) -> 500 | P4: =I4*J4 -> 50 | Q4: F | R4: F | S4: =IF((Q4="F"),IF(R4=G4,P4,0),IF(Q4="E",M4,0)) -> 0 | U4: =SUM(J:J) -> 108801.3 | X4: 45238 | Y4: {=SUM(_xlfn._xlws.FILTER(S:S,A:A=X4,0))} -> 93.75 | AA4: Betano | AB4: 0 | AC4: 1391.95
A5: 45238 | B5: Bet365 | C5: DraftKings | D5: Brandon Ingram Assists (U/O 6.5) | E5: 100 | F5: 110 | G5: U | H5: =IF(E5<0,100*(E5+F5)/(10000-200*E5-E5*F5),IF(E5>0,(E5*F5-10000)/(100*(E5+F5+200)),0)) -> 0.024390244 | I5: =IF(E5<0,IF(G5="F",-100*(E5+F5)/(E5*(F5+100)),IF(G5="U",-(F5+E5)/(E5-100),0)),IF(E5>0,IF(G5="F",(E5*F5-10000)/(100*F5+10000),IF(G5="U",(E5*F5-10000)/(100*E5+10000),0)),0)) -> 0.05 | J5: 1000 | K5: =IF(E5<0,(H5*J5*-E5*(1+F5/100))/(E5+F5),(100*H5*J5*(100+F5))/(E5*F5-10000)) -> 512.19512 | L5: =IF(E5<0,((100-E5)*H5*J5)/(E5+F5),100*((100+E5)*H5*J5)/(E5*F5-10000)) -> 487.80488 | M5: =H5*J5 -> 24.390244 | N5: =IF(G5="F",(F5*J5)/(100+F5),IF(G5="U",IF(E5<0,(-E5*J5)/(100-E5),IF(E5>0,(100*J5)/(E5+100),0)),0)) -> 500 | O5: =IF(AND(G5="F",E5<>""),(100*J5)/(100+F5),IF(G5="U",IF(E5<0,(100*J5)/(100-E5),IF(E5>0,(E5*J5)/(E5+100),0)),0)) -> 500 | P5: =I5*J5 -> 50 | Q5: F | R5: F | S5: =IF((Q5="F"),IF(R5=G5,P5,0),IF(Q5="E",M5,0)) -> 0 | U5: PROFIT MARGIN | X5: 45239 | Y5: {=SUM(_xlfn._xlws.FILTER(S:S,A:A=X5,0))} -> 0 | AA5: Fanduel | AB5: 0 | AC5: 3004.1
A6: 45238 | B6: DraftKings | C6: Bet365 | D6: Chris Paul Threes Made (O/U 0.5) | E6: -160 | F6: 185 | G6: F | H6: =IF(E6<0,100*(E6+F6)/(10000-200*E6-E6*F6),IF(E6>0,(E6*F6-10000)/(100*(E6+F6+200)),0)) -> 0.034916201 | I6: =IF(E6<0,IF(G6="F",-100*(E6+F6)/(E6*(F6+100)),IF(G6="U",-(F6+E6)/(E6-100),0)),IF(E6>0,IF(G6="F",(E6*F6-10000)/(100*F6+10000),IF(G6="U",(E6*F6-10000)/(100*E6+10000),0)),0)) -> 0.054824561 | J6: 1710 | K6: =IF(E6<0,(H6*J6*-E6*(1+F6/100))/(E6+F6),(100*H6*J6*(100+F6))/(E6*F6-10000)) -> 1089.0503 | L6: =IF(E6<0,((100-E6)*H6*J6)/(E6+F6),100*((100+E6)*H6*J6)/(E6*F6-10000)) -> 620.94972 | M6: =H6*J6 -> 59.706704 | N6: =IF(G6="F",(F6*J6)/(100+F6),IF(G6="U",IF(E6<0,(-E6*J6)/(100-E6),IF(E6>0,(100*J6)/(E6+100),0)),0)) -> 1110 | O6: =IF(AND(G6="F",E6<>""),(100*J6)/(100+F6),IF(G6="U",IF(E6<0,(100*J6)/(100-E6),IF(E6>0,(E6*J6)/(E6+100),0)),0)) -> 600 | P6: =I6*J6 -> 93.75 | Q6: F | R6: F | S6: =IF((Q6="F"),IF(R6=G6,P6,0),IF(Q6="E",M6,0)) -> 93.75 | U6: =U2/U4 -> 0.019585598 | X6: 45240 | Y6: {=SUM(_xlfn._xlws.FILTER(S:S,A:A=X6,0))} -> 0 | AA6: PokerStars | AB6: 0 | AC6: 680.6
A7: 45254 | B7: UniBet | C7: BetVictor/Fanduel | D7: Dimitri Van den Bergh v Jim Williams | E7: -127 | F7: 138 | G7: F | H7: =IF(E7<0,100*(E7+F7)/(10000-200*E7-E7*F7),IF(E7>0,(E7*F7-10000)/(100*(E7+F7+200)),0)) -> 0.020783736 | I7: =IF(E7<0,IF(G7="F",-100*(E7+F7)/(E7*(F7+100)),IF(G7="U",-(F7+E7)/(E7-100),0)),IF(E7>0,IF(G7="F",(E7*F7-10000)/(100*F7+10000),IF(G7="U",(E7*F7-10000)/(100*E7+10000),0)),0)) -> 0.03639251 | J7: 1602.27 | K7: =IF(E7<0,(H7*J7*-E7*(1+F7/100))/(E7+F7),(100*H7*J7*(100+F7))/(E7*F7-10000)) -> 915.05523 | L7: =IF(E7<0,((100-E7)*H7*J7)/(E7+F7),100*((100+E7)*H7*J7)/(E7*F7-10000)) -> 687.21477 | M7: =H7*J7 -> 33.301156 | N7: =IF(G7="F",(F7*J7)/(100+F7),IF(G7="U",IF(E7<0,(-E7*J7)/(100-E7),IF(E7>0,(100*J7)/(E7+100),0)),0)) -> 929.04731 | O7: =IF(AND(G7="F",E7<>""),(100*J7)/(100+F7),IF(G7="U",IF(E7<0,(100*J7)/(100-E7),IF(E7>0,(E7*J7)/(E7+100),0)),0)) -> 673.22269 | P7: =I7*J7 -> 58.310627 | Q7: F | R7: F | S7: =IF((Q7="F"),IF(R7=G7,P7,0),IF(Q7="E",M7,0)) -> 58.310627 | U7: AVERAGE WEEKLY INCOME | X7: 45241 | Y7: {=SUM(_xlfn._xlws.FILTER(S:S,A:A=X7,0))} -> 0 | AA7: TheScore | AB7: 0 | AC7: 3426.4
A8: 45251 | B8: Betano | C8: Fanduel | D8: Uruguay vs Bolivia Both Teams to Score (N/Y) | E8: -238 | F8: 270 | G8: U | H8: =IF(E8<0,100*(E8+F8)/(10000-200*E8-E8*F8),IF(E8>0,(E8*F8-10000)/(100*(E8+F8+200)),0)) -> 0.026259642 | I8: =IF(E8<0,IF(G8="F",-100*(E8+F8)/(E8*(F8+100)),IF(G8="U",-(F8+E8)/(E8-100),0)),IF(E8>0,IF(G8="F",(E8*F8-10000)/(100*F8+10000),IF(G8="U",(E8*F8-10000)/(100*E8+10000),0)),0)) -> 0.094674556 | J8: 1000 | K8: =IF(E8<0,(H8*J8*-E8*(1+F8/100))/(E8+F8),(100*H8*J8*(100+F8))/(E8*F8-10000)) -> 722.63253 | L8: =IF(E8<0,((100-E8)*H8*J8)/(E8+F8),100*((100+E8)*H8*J8)/(E8*F8-10000)) -> 277.36747 | M8: =H8*J8 -> 26.259642 | N8: =IF(G8="F",(F8*J8)/(100+F8),IF(G8="U",IF(E8<0,(-E8*J8)/(100-E8),IF(E8>0,(100*J8)/(E8+100),0)),0)) -> 704.14201 | O8: =IF(AND(G8="F",E8<>""),(100*J8)/(100+F8),IF(G8="U",IF(E8<0,(100*J8)/(100-E8),IF(E8>0,(E8*J8)/(E8+100),0)),0)) -> 295.85799 | P8: =I8*J8 -> 94.674556 | Q8: F | R8: F | S8: =IF((Q8="F"),IF(R8=G8,P8,0),IF(Q8="E",M8,0)) -> 0 | U8: =AVERAGE(W3,W9,W16,W23,W30,W37,W44,W51) -> 266.36732 | W8: WEEK 2 | X8: 45242 | Y8: {=SUM(_xlfn._xlws.FILTER(S:S,A:A=X8,0))} -> 0 | AA8: Unibet | AB8: 0 | AC8: 0
A9: 45244 | B9: DraftKings | C9: Betano | D9: Ryan Kalkbrenner Rebounds (U/O 5.5) | E9: -110 | F9: 115 | G9: F | H9: =IF(E9<0,100*(E9+F9)/(10000-200*E9-E9*F9),IF(E9>0,(E9*F9-10000)/(100*(E9+F9+200)),0)) -> 0.011198208 | I9: =IF(E9<0,IF(G9="F",-100*(E9+F9)/(E9*(F9+100)),IF(G9="U",-(F9+E9)/(E9-100),0)),IF(E9>0,IF(G9="F",(E9*F9-10000)/(100*F9+10000),IF(G9="U",(E9*F9-10000)/(100*E9+10000),0)),0)) -> 0.021141649 | J9: 322.5 | K9: =IF(E9<0,(H9*J9*-E9*(1+F9/100))/(E9+F9),(100*H9*J9*(100+F9))/(E9*F9-10000)) -> 170.82027 | L9: =IF(E9<0,((100-E9)*H9*J9)/(E9+F9),100*((100+E9)*H9*J9)/(E9*F9-10000)) -> 151.67973 | M9: =H9*J9 -> 3.6114222 | N9: =IF(G9="F",(F9*J9)/(100+F9),IF(G9="U",IF(E9<0,(-E9*J9)/(100-E9),IF(E9>0,(100*J9)/(E9+100),0)),0)) -> 172.5 | O9: =IF(AND(G9="F",E9<>""),(100*J9)/(100+F9),IF(G9="U",IF(E9<0,(100*J9)/(100-E9),IF(E9>0,(E9*J9)/(E9+100),0)),0)) -> 150 | P9: =I9*J9 -> 6.8181818 | Q9: F | R9: F | S9: =IF((Q9="F"),IF(R9=G9,P9,0),IF(Q9="E",M9,0)) -> 6.8181818 | W9: =SUM(Y8:Y14) -> 137.9682 | X9: 45243 | Y9: {=SUM(_xlfn._xlws.FILTER(S:S,A:A=X9,0))} -> 0 | AA9: Northstar | AB9: 0 | AC9: 1101.18
A10: 45244 | B10: Fanduel | C10: Betano | D10: LeBron James Threes Made (O/U 1.5) | E10: -130 | F10: 140 | G10: F | H10: =IF(E10<0,100*(E10+F10)/(10000-200*E10-E10*F10),IF(E10>0,(E10*F10-10000)/(100*(E10+F10+200)),0)) -> 0.018450185 | I10: =IF(E10<0,IF(G10="F",-100*(E10+F10)/(E10*(F10+100)),IF(G10="U",-(F10+E10)/(E10-100),0)),IF(E10>0,IF(G10="F",(E10*F10-10000)/(100*F10+10000),IF(G10="U",(E10*F10-10000)/(100*E10+10000),0)),0)) -> 0.032051282 | J10: 447.43 | K10: =IF(E10<0,(H10*J10*-E10*(1+F10/100))/(E10+F10),(100*H10*J10*(100+F10))/(E10*F10-10000)) -> 257.56118 | L10: =IF(E10<0,((100-E10)*H10*J10)/(E10+F10),100*((100+E10)*H10*J10)/(E10*F10-10000)) -> 189.86882 | M10: =H10*J10 -> 8.2551661 | N10: =IF(G10="F",(F10*J10)/(100+F10),IF(G10="U",IF(E10<0,(-E10*J10)/(100-E10),IF(E10>0,(100*J10)/(E10+100),0)),0)) -> 261.00083 | O10: =IF(AND(G10="F",E10<>""),(100*J10)/(100+F10),IF(G10="U",IF(E10<0,(100*J10)/(100-E10),IF(E10>0,(E10*J10)/(E10+100),0)),0)) -> 186.42917 | P10: =I10*J10 -> 14.340705 | Q10: F | R10: F | S10: =IF((Q10="F"),IF(R10=G10,P10,0),IF(Q10="E",M10,0)) -> 14.340705 | X10: 45244 | Y10: {=SUM(_xlfn._xlws.FILTER(S:S,A:A=X10,0))} -> 137.9682 | AA10: Proline+ | AB10: 0 | AC10: 0
A11: 45244 | B11: Fanduel | C11: Bet365 | D11: LeBron James Threes Made (O/U 1.5) | E11: -130 | F11: 150 | G11: F | H11: =IF(E11<0,100*(E11+F11)/(10000-200*E11-E11*F11),IF(E11>0,(E11*F11-10000)/(100*(E11+F11+200)),0)) -> 0.036036036 | I11: =IF(E11<0,IF(G11="F",-100*(E11+F11)/(E11*(F11+100)),IF(G11="U",-(F11+E11)/(E11-100),0)),IF(E11>0,IF(G11="F",(E11*F11-10000)/(100*F11+10000),IF(G11="U",(E11*F11-10000)/(100*E11+10000),0)),0)) -> 0.061538462 | J11: 1666.67 | K11: =IF(E11<0,(H11*J11*-E11*(1+F11/100))/(E11+F11),(100*H11*J11*(100+F11))/(E11*F11-10000)) -> 975.97793 | L11: =IF(E11<0,((100-E11)*H11*J11)/(E11+F11),100*((100+E11)*H11*J11)/(E11*F11-10000)) -> 690.69207 | M11: =H11*J11 -> 60.06018 | N11: =IF(G11="F",(F11*J11)/(100+F11),IF(G11="U",IF(E11<0,(-E11*J11)/(100-E11),IF(E11>0,(100*J11)/(E11+100),0)),0)) -> 1000.002 | O11: =IF(AND(G11="F",E11<>""),(100*J11)/(100+F11),IF(G11="U",IF(E11<0,(100*J11)/(100-E11),IF(E11>0,(E11*J11)/(E11+100),0)),0)) -> 666.668 | P11: =I11*J11 -> 102.56431 | Q11: F | R11: F | S11: =IF((Q11="F"),IF(R11=G11,P11,0),IF(Q11="E",M11,0)) -> 102.56431 | X11: 45245 | Y11: {=SUM(_xlfn._xlws.FILTER(S:S,A:A=X11,0))} -> 0 | AA11: BetRivers | AB11: 0 | AC11: 1600.59
A12: 45244 | B12: Fanduel | C12: TheScore | D12: LeBron James Threes Made (O/U 1.5) | E12: -130 | F12: 135 | G12: F | H12: =IF(E12<0,100*(E12+F12)/(10000-200*E12-E12*F12),IF(E12>0,(E12*F12-10000)/(100*(E12+F12+200)),0)) -> 0.0093370682 | I12: =IF(E12<0,IF(G12="F",-100*(E12+F12)/(E12*(F12+100)),IF(G12="U",-(F12+E12)/(E12-100),0)),IF(E12>0,IF(G12="F",(E12*F12-10000)/(100*F12+10000),IF(G12="U",(E12*F12-10000)/(100*E12+10000),0)),0)) -> 0.016366612 | J12: 870.37 | K12: =IF(E12<0,(H12*J12*-E12*(1+F12/100))/(E12+F12),(100*H12*J12*(100+F12))/(E12*F12-10000)) -> 496.54162 | L12: =IF(E12<0,((100-E12)*H12*J12)/(E12+F12),100*((100+E12)*H12*J12)/(E12*F12-10000)) -> 373.82838 | M12: =H12*J12 -> 8.126704 | N12: =IF(G12="F",(F12*J12)/(100+F12),IF(G12="U",IF(E12<0,(-E12*J12)/(100-E12),IF(E12>0,(100*J12)/(E12+100),0)),0)) -> 499.99979 | O12: =IF(AND(G12="F",E12<>""),(100*J12)/(100+F12),IF(G12="U",IF(E12<0,(100*J12)/(100-E12),IF(E12>0,(E12*J12)/(E12+100),0)),0)) -> 370.37021 | P12: =I12*J12 -> 14.245008 | Q12: F | R12: F | S12: =IF((Q12="F"),IF(R12=G12,P12,0),IF(Q12="E",M12,0)) -> 14.245008 | X12: 45246 | Y12: {=SUM(_xlfn._xlws.FILTER(S:S,A:A=X12,0))} -> 0 | AA12: DraftKings | AB12: 0 | AC12: 3203.19
A13: 45254 | B13: Unibet | C13: Fanduel | D13: Damon Heta v Jules van Dongen | E13: -225 | F13: 250 | G13: U | H13: =IF(E13<0,100*(E13+F13)/(10000-200*E13-E13*F13),IF(E13>0,(E13*F13-10000)/(100*(E13+F13+200)),0)) -> 0.02247191 | I13: =IF(E13<0,IF(G13="F",-100*(E13+F13)/(E13*(F13+100)),IF(G13="U",-(F13+E13)/(E13-100),0)),IF(E13>0,IF(G13="F",(E13*F13-10000)/(100*F13+10000),IF(G13="U",(E13*F13-10000)/(100*E13+10000),0)),0)) -> 0.076923077 | J13: 102.48 | K13: =IF(E13<0,(H13*J13*-E13*(1+F13/100))/(E13+F13),(100*H13*J13*(100+F13))/(E13*F13-10000)) -> 72.542022 | L13: =IF(E13<0,((100-E13)*H13*J13)/(E13+F13),100*((100+E13)*H13*J13)/(E13*F13-10000)) -> 29.937978 | M13: =H13*J13 -> 2.3029213 | N13: =IF(G13="F",(F13*J13)/(100+F13),IF(G13="U",IF(E13<0,(-E13*J13)/(100-E13),IF(E13>0,(100*J13)/(E13+100),0)),0)) -> 70.947692 | O13: =IF(AND(G13="F",E13<>""),(100*J13)/(100+F13),IF(G13="U",IF(E13<0,(100*J13)/(100-E13),IF(E13>0,(E13*J13)/(E13+100),0)),0)) -> 31.532308 | P13: =I13*J13 -> 7.8830769 | Q13: F | R13: F | S13: =IF((Q13="F"),IF(R13=G13,P13,0),IF(Q13="E",M13,0)) -> 0 | X13: 45247 | Y13: {=SUM(_xlfn._xlws.FILTER(S:S,A:A=X13,0))} -> 0 | AA13: TonyBet | AB13: 0 | AC13: 0
A14: 45252 | B14: PokerStars | C14: Unibet | D14: Projekt Warsaw v Calcit Kamnik | E14: -700 | F14: 1800 | G14: F | H14: =IF(E14<0,100*(E14+F14)/(10000-200*E14-E14*F14),IF(E14>0,(E14*F14-10000)/(100*(E14+F14+200)),0)) -> 0.078014184 | I14: =IF(E14<0,IF(G14="F",-100*(E14+F14)/(E14*(F14+100)),IF(G14="U",-(F14+E14)/(E14-100),0)),IF(E14>0,IF(G14="F",(E14*F14-10000)/(100*F14+10000),IF(G14="U",(E14*F14-10000)/(100*E14+10000),0)),0)) -> 0.082706767 | J14: 440.43 | K14: =IF(E14<0,(H14*J14*-E14*(1+F14/100))/(E14+F14),(100*H14*J14*(100+F14))/(E14*F14-10000)) -> 415.44106 | L14: =IF(E14<0,((100-E14)*H14*J14)/(E14+F14),100*((100+E14)*H14*J14)/(E14*F14-10000)) -> 24.988936 | M14: =H14*J14 -> 34.359787 | N14: =IF(G14="F",(F14*J14)/(100+F14),IF(G14="U",IF(E14<0,(-E14*J14)/(100-E14),IF(E14>0,(100*J14)/(E14+100),0)),0)) -> 417.24947 | O14: =IF(AND(G14="F",E14<>""),(100*J14)/(100+F14),IF(G14="U",IF(E14<0,(100*J14)/(100-E14),IF(E14>0,(E14*J14)/(E14+100),0)),0)) -> 23.180526 | P14: =I14*J14 -> 36.426541 | Q14: E | R14: F | S14: =IF((Q14="F"),IF(R14=G14,P14,0),IF(Q14="E",M14,0)) -> 34.359787 | X14: 45248 | Y14: {=SUM(_xlfn._xlws.FILTER(S:S,A:A=X14,0))} -> 0 | AA14: BetVictor | AB14: 0 | AC14: 1846.33
A15: 45252 | B15: PokerStars | C15: Unibet | D15: Projekt Warsaw v Calcit Kamnik (Boosted) | E15: -700 | F15: 2800 | G15: F | H15: =IF(E15<0,100*(E15+F15)/(10000-200*E15-E15*F15),IF(E15>0,(E15*F15-10000)/(100*(E15+F15+200)),0)) -> 0.099526066 | I15: =IF(E15<0,IF(G15="F",-100*(E15+F15)/(E15*(F15+100)),IF(G15="U",-(F15+E15)/(E15-100),0)),IF(E15>0,IF(G15="F",(E15*F15-10000)/(100*F15+10000),IF(G15="U",(E15*F15-10000)/(100*E15+10000),0)),0)) -> 0.10344828 | J15: 470.85 | K15: =IF(E15<0,(H15*J15*-E15*(1+F15/100))/(E15+F15),(100*H15*J15*(100+F15))/(E15*F15-10000)) -> 452.99787 | L15: =IF(E15<0,((100-E15)*H15*J15)/(E15+F15),100*((100+E15)*H15*J15)/(E15*F15-10000)) -> 17.852133 | M15: =H15*J15 -> 46.861848 | N15: =IF(G15="F",(F15*J15)/(100+F15),IF(G15="U",IF(E15<0,(-E15*J15)/(100-E15),IF(E15>0,(100*J15)/(E15+100),0)),0)) -> 454.61379 | O15: =IF(AND(G15="F",E15<>""),(100*J15)/(100+F15),IF(G15="U",IF(E15<0,(100*J15)/(100-E15),IF(E15>0,(E15*J15)/(E15+100),0)),0)) -> 16.236207 | P15: =I15*J15 -> 48.708621 | Q15: E | R15: F | S15: =IF((Q15="F"),IF(R15=G15,P15,0),IF(Q15="E",M15,0)) -> 46.861848 | W15: WEEK 3 | X15: 45249 | Y15: {=SUM(_xlfn._xlws.FILTER(S:S,A:A=X15,0))} -> 0 | AA15: SportsInteraction | AB15: 0 | AC15: 0
A16: 45252 | B16: PokerStars | C16: Unibet | D16: Projekt Warsaw v Calcit Kamnik | E16: -700 | F16: 1400 | G16: F | H16: =IF(E16<0,100*(E16+F16)/(10000-200*E16-E16*F16),IF(E16>0,(E16*F16-10000)/(100*(E16+F16+200)),0)) -> 0.061946903 | I16: =IF(E16<0,IF(G16="F",-100*(E16+F16)/(E16*(F16+100)),IF(G16="U",-(F16+E16)/(E16-100),0)),IF(E16>0,IF(G16="F",(E16*F16-10000)/(100*F16+10000),IF(G16="U",(E16*F16-10000)/(100*E16+10000),0)),0)) -> 0.066666667 | J16: 201.69 | K16: =IF(E16<0,(H16*J16*-E16*(1+F16/100))/(E16+F16),(100*H16*J16*(100+F16))/(E16*F16-10000)) -> 187.41106 | L16: =IF(E16<0,((100-E16)*H16*J16)/(E16+F16),100*((100+E16)*H16*J16)/(E16*F16-10000)) -> 14.278938 | M16: =H16*J16 -> 12.494071 | N16: =IF(G16="F",(F16*J16)/(100+F16),IF(G16="U",IF(E16<0,(-E16*J16)/(100-E16),IF(E16>0,(100*J16)/(E16+100),0)),0)) -> 188.244 | O16: =IF(AND(G16="F",E16<>""),(100*J16)/(100+F16),IF(G16="U",IF(E16<0,(100*J16)/(100-E16),IF(E16>0,(E16*J16)/(E16+100),0)),0)) -> 13.446 | P16: =I16*J16 -> 13.446 | Q16: E | R16: F | S16: =IF((Q16="F"),IF(R16=G16,P16,0),IF(Q16="E",M16,0)) -> 12.494071 | W16: =SUM(Y15:Y21) -> 234.56103 | X16: 45250 | Y16: {=SUM(_xlfn._xlws.FILTER(S:S,A:A=X16,0))} -> 0 | AA16: BetMGM | AB16: 0 | AC16: 3829.73
A17: 45256 | B17: Unibet | C17: Betano | D17: Exeter Chiefs v Newcastle Falcons | E17: -225 | F17: 235 | G17: F | H17: =IF(E17<0,100*(E17+F17)/(10000-200*E17-E17*F17),IF(E17>0,(E17*F17-10000)/(100*(E17+F17+200)),0)) -> 0.0092699884 | I17: =IF(E17<0,IF(G17="F",-100*(E17+F17)/(E17*(F17+100)),IF(G17="U",-(F17+E17)/(E17-100),0)),IF(E17>0,IF(G17="F",(E17*F17-10000)/(100*F17+10000),IF(G17="U",(E17*F17-10000)/(100*E17+10000),0)),0)) -> 0.013266998 | J17: 500 | K17: =IF(E17<0,(H17*J17*-E17*(1+F17/100))/(E17+F17),(100*H17*J17*(100+F17))/(E17*F17-10000)) -> 349.36269 | L17: =IF(E17<0,((100-E17)*H17*J17)/(E17+F17),100*((100+E17)*H17*J17)/(E17*F17-10000)) -> 150.63731 | M17: =H17*J17 -> 4.6349942 | N17: =IF(G17="F",(F17*J17)/(100+F17),IF(G17="U",IF(E17<0,(-E17*J17)/(100-E17),IF(E17>0,(100*J17)/(E17+100),0)),0)) -> 350.74627 | O17: =IF(AND(G17="F",E17<>""),(100*J17)/(100+F17),IF(G17="U",IF(E17<0,(100*J17)/(100-E17),IF(E17>0,(E17*J17)/(E17+100),0)),0)) -> 149.25373 | P17: =I17*J17 -> 6.6334992 | Q17: E | R17: F | S17: =IF((Q17="F"),IF(R17=G17,P17,0),IF(Q17="E",M17,0)) -> 4.6349942 | X17: 45251 | Y17: {=SUM(_xlfn._xlws.FILTER(S:S,A:A=X17,0))} -> 0 | AA17: 888Sports | AB17: 0 | AC17: 0
A18: 45252 | B18: Fanduel | C18: Betano | D18: Chris Paul Assists (U/O 9.5) | E18: -102 | F18: 110 | G18: F | H18: =IF(E18<0,100*(E18+F18)/(10000-200*E18-E18*F18),IF(E18>0,(E18*F18-10000)/(100*(E18+F18+200)),0)) -> 0.019221528 | I18: =IF(E18<0,IF(G18="F",-100*(E18+F18)/(E18*(F18+100)),IF(G18="U",-(F18+E18)/(E18-100),0)),IF(E18>0,IF(G18="F",(E18*F18-10000)/(100*F18+10000),IF(G18="U",(E18*F18-10000)/(100*E18+10000),0)),0)) -> 0.037348273 | J18: 412.08 | K18: =IF(E18<0,(H18*J18*-E18*(1+F18/100))/(E18+F18),(100*H18*J18*(100+F18))/(E18*F18-10000)) -> 212.07962 | L18: =IF(E18<0,((100-E18)*H18*J18)/(E18+F18),100*((100+E18)*H18*J18)/(E18*F18-10000)) -> 200.00038 | M18: =H18*J18 -> 7.9208073 | N18: =IF(G18="F",(F18*J18)/(100+F18),IF(G18="U",IF(E18<0,(-E18*J18)/(100-E18),IF(E18>0,(100*J18)/(E18+100),0)),0)) -> 215.85143 | O18: =IF(AND(G18="F",E18<>""),(100*J18)/(100+F18),IF(G18="U",IF(E18<0,(100*J18)/(100-E18),IF(E18>0,(E18*J18)/(E18+100),0)),0)) -> 196.22857 | P18: =I18*J18 -> 15.390476 | Q18: E | R18: F | S18: =IF((Q18="F"),IF(R18=G18,P18,0),IF(Q18="E",M18,0)) -> 7.9208073 | X18: 45252 | Y18: {=SUM(_xlfn._xlws.FILTER(S:S,A:A=X18,0))} -> 149.52236 | AA18: Pointsbet | AB18: 0 | AC18: 190.88
A19: 45252 | B19: Fanduel | C19: Betano | D19: Fenerbahce v CS Sepsi CIS 1st Q Total (O/U 38.5) | E19: 100 | F19: 107 | G19: F | H19: =IF(E19<0,100*(E19+F19)/(10000-200*E19-E19*F19),IF(E19>0,(E19*F19-10000)/(100*(E19+F19+200)),0)) -> 0.017199017 | I19: =IF(E19<0,IF(G19="F",-100*(E19+F19)/(E19*(F19+100)),IF(G19="U",-(F19+E19)/(E19-100),0)),IF(E19>0,IF(G19="F",(E19*F19-10000)/(100*F19+10000),IF(G19="U",(E19*F19-10000)/(100*E19+10000),0)),0)) -> 0.033816425 | J19: 414 | K19: =IF(E19<0,(H19*J19*-E19*(1+F19/100))/(E19+F19),(100*H19*J19*(100+F19))/(E19*F19-10000)) -> 210.5602 | L19: =IF(E19<0,((100-E19)*H19*J19)/(E19+F19),100*((100+E19)*H19*J19)/(E19*F19-10000)) -> 203.4398 | M19: =H19*J19 -> 7.1203931 | N19: =IF(G19="F",(F19*J19)/(100+F19),IF(G19="U",IF(E19<0,(-E19*J19)/(100-E19),IF(E19>0,(100*J19)/(E19+100),0)),0)) -> 214 | O19: =IF(AND(G19="F",E19<>""),(100*J19)/(100+F19),IF(G19="U",IF(E19<0,(100*J19)/(100-E19),IF(E19>0,(E19*J19)/(E19+100),0)),0)) -> 200 | P19: =I19*J19 -> 14 | Q19: F | R19: F | S19: =IF((Q19="F"),IF(R19=G19,P19,0),IF(Q19="E",M19,0)) -> 14 | X19: 45253 | Y19: {=SUM(_xlfn._xlws.FILTER(S:S,A:A=X19,0))} -> 0 | AA19: Pinnacle | AB19: 0 | AC19: 0
A20: 45252 | B20: Fanduel | C20: Betano | D20: Grant Williams Rebounds (U/O 3.5) | E20: -114 | F20: 118 | G20: F | H20: =IF(E20<0,100*(E20+F20)/(10000-200*E20-E20*F20),IF(E20>0,(E20*F20-10000)/(100*(E20+F20+200)),0)) -> 0.0086482747 | I20: =IF(E20<0,IF(G20="F",-100*(E20+F20)/(E20*(F20+100)),IF(G20="U",-(F20+E20)/(E20-100),0)),IF(E20>0,IF(G20="F",(E20*F20-10000)/(100*F20+10000),IF(G20="U",(E20*F20-10000)/(100*E20+10000),0)),0)) -> 0.016095284 | J20: 432.26 | K20: =IF(E20<0,(H20*J20*-E20*(1+F20/100))/(E20+F20),(100*H20*J20*(100+F20))/(E20*F20-10000)) -> 232.26078 | L20: =IF(E20<0,((100-E20)*H20*J20)/(E20+F20),100*((100+E20)*H20*J20)/(E20*F20-10000)) -> 199.99922 | M20: =H20*J20 -> 3.7383032 | N20: =IF(G20="F",(F20*J20)/(100+F20),IF(G20="U",IF(E20<0,(-E20*J20)/(100-E20),IF(E20>0,(100*J20)/(E20+100),0)),0)) -> 233.9756 | O20: =IF(AND(G20="F",E20<>""),(100*J20)/(100+F20),IF(G20="U",IF(E20<0,(100*J20)/(100-E20),IF(E20>0,(E20*J20)/(E20+100),0)),0)) -> 198.2844 | P20: =I20*J20 -> 6.9573475 | Q20: E | R20: F | S20: =IF((Q20="F"),IF(R20=G20,P20,0),IF(Q20="E",M20,0)) -> 3.7383032 | X20: 45254 | Y20: {=SUM(_xlfn._xlws.FILTER(S:S,A:A=X20,0))} -> 58.310627 | AA20: Partypoker | AB20: 0 | AC20: 113.22
A21: 45252 | B21: Bet365 | C21: Betano | D21: Kelly Olynyk Rebounds (O/U 5.5) | E21: 100 | F21: 112 | G21: F | H21: =IF(E21<0,100*(E21+F21)/(10000-200*E21-E21*F21),IF(E21>0,(E21*F21-10000)/(100*(E21+F21+200)),0)) -> 0.029126214 | I21: =IF(E21<0,IF(G21="F",-100*(E21+F21)/(E21*(F21+100)),IF(G21="U",-(F21+E21)/(E21-100),0)),IF(E21>0,IF(G21="F",(E21*F21-10000)/(100*F21+10000),IF(G21="U",(E21*F21-10000)/(100*E21+10000),0)),0)) -> 0.056603774 | J21: 424 | K21: =IF(E21<0,(H21*J21*-E21*(1+F21/100))/(E21+F21),(100*H21*J21*(100+F21))/(E21*F21-10000)) -> 218.17476 | L21: =IF(E21<0,((100-E21)*H21*J21)/(E21+F21),100*((100+E21)*H21*J21)/(E21*F21-10000)) -> 205.82524 | M21: =H21*J21 -> 12.349515 | N21: =IF(G21="F",(F21*J21)/(100+F21),IF(G21="U",IF(E21<0,(-E21*J21)/(100-E21),IF(E21>0,(100*J21)/(E21+100),0)),0)) -> 224 | O21: =IF(AND(G21="F",E21<>""),(100*J21)/(100+F21),IF(G21="U",IF(E21<0,(100*J21)/(100-E21),IF(E21>0,(E21*J21)/(E21+100),0)),0)) -> 200 | P21: =I21*J21 -> 24 | Q21: F | R21: F | S21: =IF((Q21="F"),IF(R21=G21,P21,0),IF(Q21="E",M21,0)) -> 24 | X21: 45255 | Y21: {=SUM(_xlfn._xlws.FILTER(S:S,A:A=X21,0))} -> 26.728049 | AA21: CASH | AB21: 0 | AC21: 500
A22: 45252 | B22: Fanduel | C22: Betano | D22: Moses Moody Rebounds (O/U 2.5) | E22: -122 | F22: 125 | G22: F | H22: =IF(E22<0,100*(E22+F22)/(10000-200*E22-E22*F22),IF(E22>0,(E22*F22-10000)/(100*(E22+F22+200)),0)) -> 0.0060422961 | I22: =IF(E22<0,IF(G22="F",-100*(E22+F22)/(E22*(F22+100)),IF(G22="U",-(F22+E22)/(E22-100),0)),IF(E22>0,IF(G22="F",(E22*F22-10000)/(100*F22+10000),IF(G22="U",(E22*F22-10000)/(100*E22+10000),0)),0)) -> 0.010928962 | J22: 562.5 | K22: =IF(E22<0,(H22*J22*-E22*(1+F22/100))/(E22+F22),(100*H22*J22*(100+F22))/(E22*F22-10000)) -> 310.98943 | L22: =IF(E22<0,((100-E22)*H22*J22)/(E22+F22),100*((100+E22)*H22*J22)/(E22*F22-10000)) -> 251.51057 | M22: =H22*J22 -> 3.3987915 | N22: =IF(G22="F",(F22*J22)/(100+F22),IF(G22="U",IF(E22<0,(-E22*J22)/(100-E22),IF(E22>0,(100*J22)/(E22+100),0)),0)) -> 312.5 | O22: =IF(AND(G22="F",E22<>""),(100*J22)/(100+F22),IF(G22="U",IF(E22<0,(100*J22)/(100-E22),IF(E22>0,(E22*J22)/(E22+100),0)),0)) -> 250 | P22: =I22*J22 -> 6.147541 | Q22: F | R22: F | S22: =IF((Q22="F"),IF(R22=G22,P22,0),IF(Q22="E",M22,0)) -> 6.147541 | W22: WEEK 4 | X22: 45256 | Y22: {=SUM(_xlfn._xlws.FILTER(S:S,A:A=X22,0))} -> 48.625924 | AA22: In transit | AB22: 0 | AC22: 0
A23: 45255 | B23: DraftKings | C23: Fanduel | D23: Kyle Mccord Passing TDs (U/O 1.5) | E23: -115 | F23: 120 | G23: F | H23: =IF(E23<0,100*(E23+F23)/(10000-200*E23-E23*F23),IF(E23>0,(E23*F23-10000)/(100*(E23+F23+200)),0)) -> 0.010683761 | I23: =IF(E23<0,IF(G23="F",-100*(E23+F23)/(E23*(F23+100)),IF(G23="U",-(F23+E23)/(E23-100),0)),IF(E23>0,IF(G23="F",(E23*F23-10000)/(100*F23+10000),IF(G23="U",(E23*F23-10000)/(100*E23+10000),0)),0)) -> 0.019762846 | J23: 660 | K23: =IF(E23<0,(H23*J23*-E23*(1+F23/100))/(E23+F23),(100*H23*J23*(100+F23))/(E23*F23-10000)) -> 356.79487 | L23: =IF(E23<0,((100-E23)*H23*J23)/(E23+F23),100*((100+E23)*H23*J23)/(E23*F23-10000)) -> 303.20513 | M23: =H23*J23 -> 7.0512821 | N23: =IF(G23="F",(F23*J23)/(100+F23),IF(G23="U",IF(E23<0,(-E23*J23)/(100-E23),IF(E23>0,(100*J23)/(E23+100),0)),0)) -> 360 | O23: =IF(AND(G23="F",E23<>""),(100*J23)/(100+F23),IF(G23="U",IF(E23<0,(100*J23)/(100-E23),IF(E23>0,(E23*J23)/(E23+100),0)),0)) -> 300 | P23: =I23*J23 -> 13.043478 | Q23: F | R23: U | S23: =IF((Q23="F"),IF(R23=G23,P23,0),IF(Q23="E",M23,0)) -> 0 | W23: =SUM(Y22:Y28) -> 312.9251 | X23: 45257 | Y23: {=SUM(_xlfn._xlws.FILTER(S:S,A:A=X23,0))} -> 0 | AC23: =SUM(AC2:AC22) -> 29572.54
A24: 45255 | B24: Fanduel | C24: Unibet | D24: Michael Penix Jr. Passing TDs (U/O 3.5) | E24: -205 | F24: 240 | G24: F | H24: =IF(E24<0,100*(E24+F24)/(10000-200*E24-E24*F24),IF(E24>0,(E24*F24-10000)/(100*(E24+F24+200)),0)) -> 0.03493014 | I24: =IF(E24<0,IF(G24="F",-100*(E24+F24)/(E24*(F24+100)),IF(G24="U",-(F24+E24)/(E24-100),0)),IF(E24>0,IF(G24="F",(E24*F24-10000)/(100*F24+10000),IF(G24="U",(E24*F24-10000)/(100*E24+10000),0)),0)) -> 0.050215208 | J24: 532.27 | K24: =IF(E24<0,(H24*J24*-E24*(1+F24/100))/(E24+F24),(100*H24*J24*(100+F24))/(E24*F24-10000)) -> 370.25169 | L24: =IF(E24<0,((100-E24)*H24*J24)/(E24+F24),100*((100+E24)*H24*J24)/(E24*F24-10000)) -> 162.01831 | M24: =H24*J24 -> 18.592265 | N24: =IF(G24="F",(F24*J24)/(100+F24),IF(G24="U",IF(E24<0,(-E24*J24)/(100-E24),IF(E24>0,(100*J24)/(E24+100),0)),0)) -> 375.72 | O24: =IF(AND(G24="F",E24<>""),(100*J24)/(100+F24),IF(G24="U",IF(E24<0,(100*J24)/(100-E24),IF(E24>0,(E24*J24)/(E24+100),0)),0)) -> 156.55 | P24: =I24*J24 -> 26.728049 | Q24: F | R24: F | S24: =IF((Q24="F"),IF(R24=G24,P24,0),IF(Q24="E",M24,0)) -> 26.728049 | X24: 45258 | Y24: {=SUM(_xlfn._xlws.FILTER(S:S,A:A=X24,0))} -> 0
A25: 45256 | B25: Unibet | C25: Fanduel | D25: Exeter Chiefs v Newcastle Falcons | E25: -225 | F25: 245 | G25: F | H25: =IF(E25<0,100*(E25+F25)/(10000-200*E25-E25*F25),IF(E25>0,(E25*F25-10000)/(100*(E25+F25+200)),0)) -> 0.01816118 | I25: =IF(E25<0,IF(G25="F",-100*(E25+F25)/(E25*(F25+100)),IF(G25="U",-(F25+E25)/(E25-100),0)),IF(E25>0,IF(G25="F",(E25*F25-10000)/(100*F25+10000),IF(G25="U",(E25*F25-10000)/(100*E25+10000),0)),0)) -> 0.025764895 | J25: 61.64 | K25: =IF(E25<0,(H25*J25*-E25*(1+F25/100))/(E25+F25),(100*H25*J25*(100+F25))/(E25*F25-10000)) -> 43.448854 | L25: =IF(E25<0,((100-E25)*H25*J25)/(E25+F25),100*((100+E25)*H25*J25)/(E25*F25-10000)) -> 18.191146 | M25: =H25*J25 -> 1.1194552 | N25: =IF(G25="F",(F25*J25)/(100+F25),IF(G25="U",IF(E25<0,(-E25*J25)/(100-E25),IF(E25>0,(100*J25)/(E25+100),0)),0)) -> 43.773333 | O25: =IF(AND(G25="F",E25<>""),(100*J25)/(100+F25),IF(G25="U",IF(E25<0,(100*J25)/(100-E25),IF(E25>0,(E25*J25)/(E25+100),0)),0)) -> 17.866667 | P25: =I25*J25 -> 1.5881481 | Q25: E | R25: F | S25: =IF((Q25="F"),IF(R25=G25,P25,0),IF(Q25="E",M25,0)) -> 1.1194552 | X25: 45259 | Y25: {=SUM(_xlfn._xlws.FILTER(S:S,A:A=X25,0))} -> 48.019449 | AA25: CHECKS
A26: 45256 | B26: Fanduel | C26: Bet365 | D26: Zay Flowers Total Receptions (O/U 4.5) | E26: -130 | F26: 140 | G26: F | H26: =IF(E26<0,100*(E26+F26)/(10000-200*E26-E26*F26),IF(E26>0,(E26*F26-10000)/(100*(E26+F26+200)),0)) -> 0.018450185 | I26: =IF(E26<0,IF(G26="F",-100*(E26+F26)/(E26*(F26+100)),IF(G26="U",-(F26+E26)/(E26-100),0)),IF(E26>0,IF(G26="F",(E26*F26-10000)/(100*F26+10000),IF(G26="U",(E26*F26-10000)/(100*E26+10000),0)),0)) -> 0.032051282 | J26: 720 | K26: =IF(E26<0,(H26*J26*-E26*(1+F26/100))/(E26+F26),(100*H26*J26*(100+F26))/(E26*F26-10000)) -> 414.46494 | L26: =IF(E26<0,((100-E26)*H26*J26)/(E26+F26),100*((100+E26)*H26*J26)/(E26*F26-10000)) -> 305.53506 | M26: =H26*J26 -> 13.284133 | N26: =IF(G26="F",(F26*J26)/(100+F26),IF(G26="U",IF(E26<0,(-E26*J26)/(100-E26),IF(E26>0,(100*J26)/(E26+100),0)),0)) -> 420 | O26: =IF(AND(G26="F",E26<>""),(100*J26)/(100+F26),IF(G26="U",IF(E26<0,(100*J26)/(100-E26),IF(E26>0,(E26*J26)/(E26+100),0)),0)) -> 300 | P26: =I26*J26 -> 23.076923 | Q26: F | R26: F | S26: =IF((Q26="F"),IF(R26=G26,P26,0),IF(Q26="E",M26,0)) -> 23.076923 | X26: 45260 | Y26: {=SUM(_xlfn._xlws.FILTER(S:S,A:A=X26,0))} -> 53.616133 | AA26: Dec 9 2023 | AB26: 21273.48
A27: 45256 | B27: Fanduel | C27: Bet365 | D27: Zay Flowers Total Receptions (O/U 4.5) | E27: -130 | F27: 140 | G27: F | H27: =IF(E27<0,100*(E27+F27)/(10000-200*E27-E27*F27),IF(E27>0,(E27*F27-10000)/(100*(E27+F27+200)),0)) -> 0.018450185 | I27: =IF(E27<0,IF(G27="F",-100*(E27+F27)/(E27*(F27+100)),IF(G27="U",-(F27+E27)/(E27-100),0)),IF(E27>0,IF(G27="F",(E27*F27-10000)/(100*F27+10000),IF(G27="U",(E27*F27-10000)/(100*E27+10000),0)),0)) -> 0.032051282 | J27: 617.59 | K27: =IF(E27<0,(H27*J27*-E27*(1+F27/100))/(E27+F27),(100*H27*J27*(100+F27))/(E27*F27-10000)) -> 355.51306 | L27: =IF(E27<0,((100-E27)*H27*J27)/(E27+F27),100*((100+E27)*H27*J27)/(E27*F27-10000)) -> 262.07694 | M27: =H27*J27 -> 11.394649 | N27: =IF(G27="F",(F27*J27)/(100+F27),IF(G27="U",IF(E27<0,(-E27*J27)/(100-E27),IF(E27>0,(100*J27)/(E27+100),0)),0)) -> 360.26083 | O27: =IF(AND(G27="F",E27<>""),(100*J27)/(100+F27),IF(G27="U",IF(E27<0,(100*J27)/(100-E27),IF(E27>0,(E27*J27)/(E27+100),0)),0)) -> 257.32917 | P27: =I27*J27 -> 19.794551 | Q27: F | R27: F | S27: =IF((Q27="F"),IF(R27=G27,P27,0),IF(Q27="E",M27,0)) -> 19.794551 | X27: 45261 | Y27: {=SUM(_xlfn._xlws.FILTER(S:S,A:A=X27,0))} -> 0 | AA27: Dec 21 2023 | AB27: 21950.72
A28: 45258 | B28: Fanduel | C28: Bet365 | D28: Domantas Sabonis Points (O/U 19.5) | E28: -105 | F28: 110 | G28: F | H28: =IF(E28<0,100*(E28+F28)/(10000-200*E28-E28*F28),IF(E28>0,(E28*F28-10000)/(100*(E28+F28+200)),0)) -> 0.011750881 | I28: =IF(E28<0,IF(G28="F",-100*(E28+F28)/(E28*(F28+100)),IF(G28="U",-(F28+E28)/(E28-100),0)),IF(E28>0,IF(G28="F",(E28*F28-10000)/(100*F28+10000),IF(G28="U",(E28*F28-10000)/(100*E28+10000),0)),0)) -> 0.022675737 | J28: 1050 | K28: =IF(E28<0,(H28*J28*-E28*(1+F28/100))/(E28+F28),(100*H28*J28*(100+F28))/(E28*F28-10000)) -> 544.12456 | L28: =IF(E28<0,((100-E28)*H28*J28)/(E28+F28),100*((100+E28)*H28*J28)/(E28*F28-10000)) -> 505.87544 | M28: =H28*J28 -> 12.338425 | N28: =IF(G28="F",(F28*J28)/(100+F28),IF(G28="U",IF(E28<0,(-E28*J28)/(100-E28),IF(E28>0,(100*J28)/(E28+100),0)),0)) -> 550 | O28: =IF(AND(G28="F",E28<>""),(100*J28)/(100+F28),IF(G28="U",IF(E28<0,(100*J28)/(100-E28),IF(E28>0,(E28*J28)/(E28+100),0)),0)) -> 500 | P28: =I28*J28 -> 23.809524 | Q28: F | R28: U | S28: =IF((Q28="F"),IF(R28=G28,P28,0),IF(Q28="E",M28,0)) -> 0 | X28: 45262 | Y28: {=SUM(_xlfn._xlws.FILTER(S:S,A:A=X28,0))} -> 162.66359 | AA28: Jan 15 2023 | AB28: 29572.54
A29: 45259 | B29: Bet365 | C29: Unibet | D29: Alex Ovechkin PowerPlay Points (U/O 0.5) | E29: -175 | F29: 185 | G29: F | H29: =IF(E29<0,100*(E29+F29)/(10000-200*E29-E29*F29),IF(E29>0,(E29*F29-10000)/(100*(E29+F29+200)),0)) -> 0.012924071 | I29: =IF(E29<0,IF(G29="F",-100*(E29+F29)/(E29*(F29+100)),IF(G29="U",-(F29+E29)/(E29-100),0)),IF(E29>0,IF(G29="F",(E29*F29-10000)/(100*F29+10000),IF(G29="U",(E29*F29-10000)/(100*E29+10000),0)),0)) -> 0.020050125 | J29: 68.8 | K29: =IF(E29<0,(H29*J29*-E29*(1+F29/100))/(E29+F29),(100*H29*J29*(100+F29))/(E29*F29-10000)) -> 44.347658 | L29: =IF(E29<0,((100-E29)*H29*J29)/(E29+F29),100*((100+E29)*H29*J29)/(E29*F29-10000)) -> 24.452342 | M29: =H29*J29 -> 0.88917609 | N29: =IF(G29="F",(F29*J29)/(100+F29),IF(G29="U",IF(E29<0,(-E29*J29)/(100-E29),IF(E29>0,(100*J29)/(E29+100),0)),0)) -> 44.659649 | O29: =IF(AND(G29="F",E29<>""),(100*J29)/(100+F29),IF(G29="U",IF(E29<0,(100*J29)/(100-E29),IF(E29>0,(E29*J29)/(E29+100),0)),0)) -> 24.140351 | P29: =I29*J29 -> 1.3794486 | Q29: F | R29: F | S29: =IF((Q29="F"),IF(R29=G29,P29,0),IF(Q29="E",M29,0)) -> 1.3794486 | W29: WEEK 5 | X29: 45263 | Y29: {=SUM(_xlfn._xlws.FILTER(S:S,A:A=X29,0))} -> 93.623167
A30: 45263 | B30: Fanduel | C30: Bet365 | D30: Russell Wilson Passing TDs (U/O 1.5) | E30: -122 | F30: 130 | G30: F | H30: =IF(E30<0,100*(E30+F30)/(10000-200*E30-E30*F30),IF(E30>0,(E30*F30-10000)/(100*(E30+F30+200)),0)) -> 0.01591723 | I30: =IF(E30<0,IF(G30="F",-100*(E30+F30)/(E30*(F30+100)),IF(G30="U",-(F30+E30)/(E30-100),0)),IF(E30>0,IF(G30="F",(E30*F30-10000)/(100*F30+10000),IF(G30="U",(E30*F30-10000)/(100*E30+10000),0)),0)) -> 0.028510335 | J30: 1391.5 | K30: =IF(E30<0,(H30*J30*-E30*(1+F30/100))/(E30+F30),(100*H30*J30*(100+F30))/(E30*F30-10000)) -> 776.87008 | L30: =IF(E30<0,((100-E30)*H30*J30)/(E30+F30),100*((100+E30)*H30*J30)/(E30*F30-10000)) -> 614.62992 | M30: =H30*J30 -> 22.148826 | N30: =IF(G30="F",(F30*J30)/(100+F30),IF(G30="U",IF(E30<0,(-E30*J30)/(100-E30),IF(E30>0,(100*J30)/(E30+100),0)),0)) -> 786.5 | O30: =IF(AND(G30="F",E30<>""),(100*J30)/(100+F30),IF(G30="U",IF(E30<0,(100*J30)/(100-E30),IF(E30>0,(E30*J30)/(E30+100),0)),0)) -> 605 | P30: =I30*J30 -> 39.672131 | Q30: F | R30: F | S30: =IF((Q30="F"),IF(R30=G30,P30,0),IF(Q30="E",M30,0)) -> 39.672131 | W30: =SUM(Y29:Y35) -> 786.07359 | X30: 45264 | Y30: {=SUM(_xlfn._xlws.FILTER(S:S,A:A=X30,0))} -> 0
A31: 45259 | B31: Betano | C31: DraftKings | D31: USC v Eastern Washington | E31: -1250 | F31: 2500 | G31: F | H31: =IF(E31<0,100*(E31+F31)/(10000-200*E31-E31*F31),IF(E31>0,(E31*F31-10000)/(100*(E31+F31+200)),0)) -> 0.036927622 | I31: =IF(E31<0,IF(G31="F",-100*(E31+F31)/(E31*(F31+100)),IF(G31="U",-(F31+E31)/(E31-100),0)),IF(E31>0,IF(G31="F",(E31*F31-10000)/(100*F31+10000),IF(G31="U",(E31*F31-10000)/(100*E31+10000),0)),0)) -> 0.038461538 | J31: 1212.64 | K31: =IF(E31<0,(H31*J31*-E31*(1+F31/100))/(E31+F31),(100*H31*J31*(100+F31))/(E31*F31-10000)) -> 1164.2777 | L31: =IF(E31<0,((100-E31)*H31*J31)/(E31+F31),100*((100+E31)*H31*J31)/(E31*F31-10000)) -> 48.362304 | M31: =H31*J31 -> 44.779911 | N31: =IF(G31="F",(F31*J31)/(100+F31),IF(G31="U",IF(E31<0,(-E31*J31)/(100-E31),IF(E31>0,(100*J31)/(E31+100),0)),0)) -> 1166 | O31: =IF(AND(G31="F",E31<>""),(100*J31)/(100+F31),IF(G31="U",IF(E31<0,(100*J31)/(100-E31),IF(E31>0,(E31*J31)/(E31+100),0)),0)) -> 46.64 | P31: =I31*J31 -> 46.64 | Q31: F | R31: F | S31: =IF((Q31="F"),IF(R31=G31,P31,0),IF(Q31="E",M31,0)) -> 46.64 | X31: 45265 | Y31: {=SUM(_xlfn._xlws.FILTER(S:S,A:A=X31,0))} -> 98.491175
A32: 45263 | B32: Betano | C32: DraftKings | D32: Aston Villa/Bournemouth Total Cards (O/U 4.5) | E32: -110 | F32: 115 | G32: F | H32: =IF(E32<0,100*(E32+F32)/(10000-200*E32-E32*F32),IF(E32>0,(E32*F32-10000)/(100*(E32+F32+200)),0)) -> 0.011198208 | I32: =IF(E32<0,IF(G32="F",-100*(E32+F32)/(E32*(F32+100)),IF(G32="U",-(F32+E32)/(E32-100),0)),IF(E32>0,IF(G32="F",(E32*F32-10000)/(100*F32+10000),IF(G32="U",(E32*F32-10000)/(100*E32+10000),0)),0)) -> 0.021141649 | J32: 934.79 | K32: =IF(E32<0,(H32*J32*-E32*(1+F32/100))/(E32+F32),(100*H32*J32*(100+F32))/(E32*F32-10000)) -> 495.13513 | L32: =IF(E32<0,((100-E32)*H32*J32)/(E32+F32),100*((100+E32)*H32*J32)/(E32*F32-10000)) -> 439.65487 | M32: =H32*J32 -> 10.467973 | N32: =IF(G32="F",(F32*J32)/(100+F32),IF(G32="U",IF(E32<0,(-E32*J32)/(100-E32),IF(E32>0,(100*J32)/(E32+100),0)),0)) -> 500.00395 | O32: =IF(AND(G32="F",E32<>""),(100*J32)/(100+F32),IF(G32="U",IF(E32<0,(100*J32)/(100-E32),IF(E32>0,(E32*J32)/(E32+100),0)),0)) -> 434.78605 | P32: =I32*J32 -> 19.763002 | Q32: F | R32: F | S32: =IF((Q32="F"),IF(R32=G32,P32,0),IF(Q32="E",M32,0)) -> 19.763002 | X32: 45266 | Y32: {=SUM(_xlfn._xlws.FILTER(S:S,A:A=X32,0))} -> 238.07328
A33: 45260 | B33: Bet365 | C33: BetRivers | D33: Alex Ovechkin PowerPlay Points (U/O 0.5) | E33: -160 | F33: 185 | G33: F | H33: =IF(E33<0,100*(E33+F33)/(10000-200*E33-E33*F33),IF(E33>0,(E33*F33-10000)/(100*(E33+F33+200)),0)) -> 0.034916201 | I33: =IF(E33<0,IF(G33="F",-100*(E33+F33)/(E33*(F33+100)),IF(G33="U",-(F33+E33)/(E33-100),0)),IF(E33>0,IF(G33="F",(E33*F33-10000)/(100*F33+10000),IF(G33="U",(E33*F33-10000)/(100*E33+10000),0)),0)) -> 0.054824561 | J33: 1143.47 | K33: =IF(E33<0,(H33*J33*-E33*(1+F33/100))/(E33+F33),(100*H33*J33*(100+F33))/(E33*F33-10000)) -> 728.24346 | L33: =IF(E33<0,((100-E33)*H33*J33)/(E33+F33),100*((100+E33)*H33*J33)/(E33*F33-10000)) -> 415.22654 | M33: =H33*J33 -> 39.925628 | N33: =IF(G33="F",(F33*J33)/(100+F33),IF(G33="U",IF(E33<0,(-E33*J33)/(100-E33),IF(E33>0,(100*J33)/(E33+100),0)),0)) -> 742.25246 | O33: =IF(AND(G33="F",E33<>""),(100*J33)/(100+F33),IF(G33="U",IF(E33<0,(100*J33)/(100-E33),IF(E33>0,(E33*J33)/(E33+100),0)),0)) -> 401.21754 | P33: =I33*J33 -> 62.690241 | Q33: F | R33: U | S33: =IF((Q33="F"),IF(R33=G33,P33,0),IF(Q33="E",M33,0)) -> 0 | X33: 45267 | Y33: {=SUM(_xlfn._xlws.FILTER(S:S,A:A=X33,0))} -> 291.92171
A34: 45260 | B34: Bet365 | C34: BetRivers | D34: Connor McDavid PowerPlay Points (O/U 0.5) | E34: 100 | F34: 110 | G34: F | H34: =IF(E34<0,100*(E34+F34)/(10000-200*E34-E34*F34),IF(E34>0,(E34*F34-10000)/(100*(E34+F34+200)),0)) -> 0.024390244 | I34: =IF(E34<0,IF(G34="F",-100*(E34+F34)/(E34*(F34+100)),IF(G34="U",-(F34+E34)/(E34-100),0)),IF(E34>0,IF(G34="F",(E34*F34-10000)/(100*F34+10000),IF(G34="U",(E34*F34-10000)/(100*E34+10000),0)),0)) -> 0.047619048 | J34: 616.6 | K34: =IF(E34<0,(H34*J34*-E34*(1+F34/100))/(E34+F34),(100*H34*J34*(100+F34))/(E34*F34-10000)) -> 315.81951 | L34: =IF(E34<0,((100-E34)*H34*J34)/(E34+F34),100*((100+E34)*H34*J34)/(E34*F34-10000)) -> 300.78049 | M34: =H34*J34 -> 15.039024 | N34: =IF(G34="F",(F34*J34)/(100+F34),IF(G34="U",IF(E34<0,(-E34*J34)/(100-E34),IF(E34>0,(100*J34)/(E34+100),0)),0)) -> 322.98095 | O34: =IF(AND(G34="F",E34<>""),(100*J34)/(100+F34),IF(G34="U",IF(E34<0,(100*J34)/(100-E34),IF(E34>0,(E34*J34)/(E34+100),0)),0)) -> 293.61905 | P34: =I34*J34 -> 29.361905 | Q34: E | R34: F | S34: =IF((Q34="F"),IF(R34=G34,P34,0),IF(Q34="E",M34,0)) -> 15.039024 | X34: 45268 | Y34: {=SUM(_xlfn._xlws.FILTER(S:S,A:A=X34,0))} -> 25.274725
A35: 45260 | B35: Unibet | C35: Bet365 | D35: Troy Terry Shots on Goal (U/O 2.5) | E35: -139 | F35: 150 | G35: F | H35: =IF(E35<0,100*(E35+F35)/(10000-200*E35-E35*F35),IF(E35>0,(E35*F35-10000)/(100*(E35+F35+200)),0)) -> 0.018755328 | I35: =IF(E35<0,IF(G35="F",-100*(E35+F35)/(E35*(F35+100)),IF(G35="U",-(F35+E35)/(E35-100),0)),IF(E35>0,IF(G35="F",(E35*F35-10000)/(100*F35+10000),IF(G35="U",(E35*F35-10000)/(100*E35+10000),0)),0)) -> 0.031654676 | J35: 207.35 | K35: =IF(E35<0,(H35*J35*-E35*(1+F35/100))/(E35+F35),(100*H35*J35*(100+F35))/(E35*F35-10000)) -> 122.85443 | L35: =IF(E35<0,((100-E35)*H35*J35)/(E35+F35),100*((100+E35)*H35*J35)/(E35*F35-10000)) -> 84.495567 | M35: =H35*J35 -> 3.8889173 | N35: =IF(G35="F",(F35*J35)/(100+F35),IF(G35="U",IF(E35<0,(-E35*J35)/(100-E35),IF(E35>0,(100*J35)/(E35+100),0)),0)) -> 124.41 | O35: =IF(AND(G35="F",E35<>""),(100*J35)/(100+F35),IF(G35="U",IF(E35<0,(100*J35)/(100-E35),IF(E35>0,(E35*J35)/(E35+100),0)),0)) -> 82.94 | P35: =I35*J35 -> 6.5635971 | Q35: F | R35: U | S35: =IF((Q35="F"),IF(R35=G35,P35,0),IF(Q35="E",M35,0)) -> 0 | X35: 45269 | Y35: {=SUM(_xlfn._xlws.FILTER(S:S,A:A=X35,0))} -> 38.68954
A36: 45260 | B36: Betano | C36: Fanduel | D36: Mike Conley Assists (U/O 7.5) | E36: -143 | F36: 152 | G36: F | H36: =IF(E36<0,100*(E36+F36)/(10000-200*E36-E36*F36),IF(E36>0,(E36*F36-10000)/(100*(E36+F36+200)),0)) -> 0.014916468 | I36: =IF(E36<0,IF(G36="F",-100*(E36+F36)/(E36*(F36+100)),IF(G36="U",-(F36+E36)/(E36-100),0)),IF(E36>0,IF(G36="F",(E36*F36-10000)/(100*F36+10000),IF(G36="U",(E36*F36-10000)/(100*E36+10000),0)),0)) -> 0.024975025 | J36: 927.23 | K36: =IF(E36<0,(H36*J36*-E36*(1+F36/100))/(E36+F36),(100*H36*J36*(100+F36))/(E36*F36-10000)) -> 553.7931 | L36: =IF(E36<0,((100-E36)*H36*J36)/(E36+F36),100*((100+E36)*H36*J36)/(E36*F36-10000)) -> 373.4369 | M36: =H36*J36 -> 13.830996 | N36: =IF(G36="F",(F36*J36)/(100+F36),IF(G36="U",IF(E36<0,(-E36*J36)/(100-E36),IF(E36>0,(100*J36)/(E36+100),0)),0)) -> 559.28159 | O36: =IF(AND(G36="F",E36<>""),(100*J36)/(100+F36),IF(G36="U",IF(E36<0,(100*J36)/(100-E36),IF(E36>0,(E36*J36)/(E36+100),0)),0)) -> 367.94841 | P36: =I36*J36 -> 23.157592 | Q36: F | R36: F | S36: =IF((Q36="F"),IF(R36=G36,P36,0),IF(Q36="E",M36,0)) -> 23.157592 | W36: WEEK 6 | X36: 45270 | Y36: {=SUM(_xlfn._xlws.FILTER(S:S,A:A=X36,0))} -> 101.54202
A37: 45260 | B37: Sports Interaction | C37: Fanduel | D37: Khris Middleton Assists (O/U 3.5) | E37: -105 | F37: 108 | G37: F | H37: =IF(E37<0,100*(E37+F37)/(10000-200*E37-E37*F37),IF(E37>0,(E37*F37-10000)/(100*(E37+F37+200)),0)) -> 0.0070854983 | I37: =IF(E37<0,IF(G37="F",-100*(E37+F37)/(E37*(F37+100)),IF(G37="U",-(F37+E37)/(E37-100),0)),IF(E37>0,IF(G37="F",(E37*F37-10000)/(100*F37+10000),IF(G37="U",(E37*F37-10000)/(100*E37+10000),0)),0)) -> 0.013736264 | J37: 577.78 | K37: =IF(E37<0,(H37*J37*-E37*(1+F37/100))/(E37+F37),(100*H37*J37*(100+F37))/(E37*F37-10000)) -> 298.03295 | L37: =IF(E37<0,((100-E37)*H37*J37)/(E37+F37),100*((100+E37)*H37*J37)/(E37*F37-10000)) -> 279.74705 | M37: =H37*J37 -> 4.0938592 | N37: =IF(G37="F",(F37*J37)/(100+F37),IF(G37="U",IF(E37<0,(-E37*J37)/(100-E37),IF(E37>0,(100*J37)/(E37+100),0)),0)) -> 300.00115 | O37: =IF(AND(G37="F",E37<>""),(100*J37)/(100+F37),IF(G37="U",IF(E37<0,(100*J37)/(100-E37),IF(E37>0,(E37*J37)/(E37+100),0)),0)) -> 277.77885 | P37: =I37*J37 -> 7.9365385 | Q37: F | R37: U | S37: =IF((Q37="F"),IF(R37=G37,P37,0),IF(Q37="E",M37,0)) -> 0 | W37: =SUM(Y36:Y42) -> 101.54202 | X37: 45271 | Y37: {=SUM(_xlfn._xlws.FILTER(S:S,A:A=X37,0))} -> 0
A38: 45260 | B38: NorthStar | C38: DraftKings | D38: Ryan Nugent-Hopkins PowerPlay Points (U/O 0.5) | E38: -200 | F38: 210 | G38: F | H38: =IF(E38<0,100*(E38+F38)/(10000-200*E38-E38*F38),IF(E38>0,(E38*F38-10000)/(100*(E38+F38+200)),0)) -> 0.010869565 | I38: =IF(E38<0,IF(G38="F",-100*(E38+F38)/(E38*(F38+100)),IF(G38="U",-(F38+E38)/(E38-100),0)),IF(E38>0,IF(G38="F",(E38*F38-10000)/(100*F38+10000),IF(G38="U",(E38*F38-10000)/(100*E38+10000),0)),0)) -> 0.016129032 | J38: 956.01 | K38: =IF(E38<0,(H38*J38*-E38*(1+F38/100))/(E38+F38),(100*H38*J38*(100+F38))/(E38*F38-10000)) -> 644.26761 | L38: =IF(E38<0,((100-E38)*H38*J38)/(E38+F38),100*((100+E38)*H38*J38)/(E38*F38-10000)) -> 311.74239 | M38: =H38*J38 -> 10.391413 | N38: =IF(G38="F",(F38*J38)/(100+F38),IF(G38="U",IF(E38<0,(-E38*J38)/(100-E38),IF(E38>0,(100*J38)/(E38+100),0)),0)) -> 647.61968 | O38: =IF(AND(G38="F",E38<>""),(100*J38)/(100+F38),IF(G38="U",IF(E38<0,(100*J38)/(100-E38),IF(E38>0,(E38*J38)/(E38+100),0)),0)) -> 308.39032 | P38: =I38*J38 -> 15.419516 | Q38: F | R38: F | S38: =IF((Q38="F"),IF(R38=G38,P38,0),IF(Q38="E",M38,0)) -> 15.419516 | X38: 45272 | Y38: {=SUM(_xlfn._xlws.FILTER(S:S,A:A=X38,0))} -> 0
A39: 45262 | B39: DraftKings | C39: BetRivers | D39: Ashton Jeanty Receiving Yards (O/U 29.5) | E39: -115 | F39: 120 | G39: F | H39: =IF(E39<0,100*(E39+F39)/(10000-200*E39-E39*F39),IF(E39>0,(E39*F39-10000)/(100*(E39+F39+200)),0)) -> 0.010683761 | I39: =IF(E39<0,IF(G39="F",-100*(E39+F39)/(E39*(F39+100)),IF(G39="U",-(F39+E39)/(E39-100),0)),IF(E39>0,IF(G39="F",(E39*F39-10000)/(100*F39+10000),IF(G39="U",(E39*F39-10000)/(100*E39+10000),0)),0)) -> 0.019762846 | J39: 660 | K39: =IF(E39<0,(H39*J39*-E39*(1+F39/100))/(E39+F39),(100*H39*J39*(100+F39))/(E39*F39-10000)) -> 356.79487 | L39: =IF(E39<0,((100-E39)*H39*J39)/(E39+F39),100*((100+E39)*H39*J39)/(E39*F39-10000)) -> 303.20513 | M39: =H39*J39 -> 7.0512821 | N39: =IF(G39="F",(F39*J39)/(100+F39),IF(G39="U",IF(E39<0,(-E39*J39)/(100-E39),IF(E39>0,(100*J39)/(E39+100),0)),0)) -> 360 | O39: =IF(AND(G39="F",E39<>""),(100*J39)/(100+F39),IF(G39="U",IF(E39<0,(100*J39)/(100-E39),IF(E39>0,(E39*J39)/(E39+100),0)),0)) -> 300 | P39: =I39*J39 -> 13.043478 | Q39: F | R39: U | S39: =IF((Q39="F"),IF(R39=G39,P39,0),IF(Q39="E",M39,0)) -> 0 | X39: 45273 | Y39: {=SUM(_xlfn._xlws.FILTER(S:S,A:A=X39,0))} -> 0
A40: 45262 | B40: Bet365 | C40: BetMGM | D40: Toledo v George Mason Moneyline | E40: -145 | F40: 155 | G40: F | H40: =IF(E40<0,100*(E40+F40)/(10000-200*E40-E40*F40),IF(E40>0,(E40*F40-10000)/(100*(E40+F40+200)),0)) -> 0.016266775 | I40: =IF(E40<0,IF(G40="F",-100*(E40+F40)/(E40*(F40+100)),IF(G40="U",-(F40+E40)/(E40-100),0)),IF(E40>0,IF(G40="F",(E40*F40-10000)/(100*F40+10000),IF(G40="U",(E40*F40-10000)/(100*E40+10000),0)),0)) -> 0.027045301 | J40: 1287.51 | K40: =IF(E40<0,(H40*J40*-E40*(1+F40/100))/(E40+F40),(100*H40*J40*(100+F40))/(E40*F40-10000)) -> 774.39093 | L40: =IF(E40<0,((100-E40)*H40*J40)/(E40+F40),100*((100+E40)*H40*J40)/(E40*F40-10000)) -> 513.11907 | M40: =H40*J40 -> 20.943636 | N40: =IF(G40="F",(F40*J40)/(100+F40),IF(G40="U",IF(E40<0,(-E40*J40)/(100-E40),IF(E40>0,(100*J40)/(E40+100),0)),0)) -> 782.60412 | O40: =IF(AND(G40="F",E40<>""),(100*J40)/(100+F40),IF(G40="U",IF(E40<0,(100*J40)/(100-E40),IF(E40>0,(E40*J40)/(E40+100),0)),0)) -> 504.90588 | P40: =I40*J40 -> 34.821095 | Q40: F | R40: U | S40: =IF((Q40="F"),IF(R40=G40,P40,0),IF(Q40="E",M40,0)) -> 0 | X40: 45274 | Y40: {=SUM(_xlfn._xlws.FILTER(S:S,A:A=X40,0))} -> 0
A41: 45262 | B41: NorthStar | C41: Fanduel | D41: Promitheas v AEK Athens | E41: -143 | F41: 150 | G41: F | H41: =IF(E41<0,100*(E41+F41)/(10000-200*E41-E41*F41),IF(E41>0,(E41*F41-10000)/(100*(E41+F41+200)),0)) -> 0.011656953 | I41: =IF(E41<0,IF(G41="F",-100*(E41+F41)/(E41*(F41+100)),IF(G41="U",-(F41+E41)/(E41-100),0)),IF(E41>0,IF(G41="F",(E41*F41-10000)/(100*F41+10000),IF(G41="U",(E41*F41-10000)/(100*E41+10000),0)),0)) -> 0.01958042 | J41: 1000 | K41: =IF(E41<0,(H41*J41*-E41*(1+F41/100))/(E41+F41),(100*H41*J41*(100+F41))/(E41*F41-10000)) -> 595.33722 | L41: =IF(E41<0,((100-E41)*H41*J41)/(E41+F41),100*((100+E41)*H41*J41)/(E41*F41-10000)) -> 404.66278 | M41: =H41*J41 -> 11.656953 | N41: =IF(G41="F",(F41*J41)/(100+F41),IF(G41="U",IF(E41<0,(-E41*J41)/(100-E41),IF(E41>0,(100*J41)/(E41+100),0)),0)) -> 600 | O41: =IF(AND(G41="F",E41<>""),(100*J41)/(100+F41),IF(G41="U",IF(E41<0,(100*J41)/(100-E41),IF(E41>0,(E41*J41)/(E41+100),0)),0)) -> 400 | P41: =I41*J41 -> 19.58042 | Q41: F | R41: F | S41: =IF((Q41="F"),IF(R41=G41,P41,0),IF(Q41="E",M41,0)) -> 19.58042 | X41: 45275 | Y41: {=SUM(_xlfn._xlws.FILTER(S:S,A:A=X41,0))} -> 0
A42: 45262 | B42: BetRivers | C42: Fanduel | D42: Miro Heiskanen Shots on Goal (U/O 2.5) | E42: -122 | F42: 144 | G42: F | H42: =IF(E42<0,100*(E42+F42)/(10000-200*E42-E42*F42),IF(E42>0,(E42*F42-10000)/(100*(E42+F42+200)),0)) -> 0.042333744 | I42: =IF(E42<0,IF(G42="F",-100*(E42+F42)/(E42*(F42+100)),IF(G42="U",-(F42+E42)/(E42-100),0)),IF(E42>0,IF(G42="F",(E42*F42-10000)/(100*F42+10000),IF(G42="U",(E42*F42-10000)/(100*E42+10000),0)),0)) -> 0.073904864 | J42: 1556.32 | K42: =IF(E42<0,(H42*J42*-E42*(1+F42/100))/(E42+F42),(100*H42*J42*(100+F42))/(E42*F42-10000)) -> 891.48195 | L42: =IF(E42<0,((100-E42)*H42*J42)/(E42+F42),100*((100+E42)*H42*J42)/(E42*F42-10000)) -> 664.83805 | M42: =H42*J42 -> 65.884852 | N42: =IF(G42="F",(F42*J42)/(100+F42),IF(G42="U",IF(E42<0,(-E42*J42)/(100-E42),IF(E42>0,(100*J42)/(E42+100),0)),0)) -> 918.48393 | O42: =IF(AND(G42="F",E42<>""),(100*J42)/(100+F42),IF(G42="U",IF(E42<0,(100*J42)/(100-E42),IF(E42>0,(E42*J42)/(E42+100),0)),0)) -> 637.83607 | P42: =I42*J42 -> 115.01962 | Q42: F | R42: F | S42: =IF((Q42="F"),IF(R42=G42,P42,0),IF(Q42="E",M42,0)) -> 115.01962 | X42: 45276 | Y42: {=SUM(_xlfn._xlws.FILTER(S:S,A:A=X42,0))} -> 0
A43: 45262 | B43: NorthStar | C43: Fanduel | D43: Miro Heiskanen Shots on Goal (U/O 2.5) | E43: -122 | F43: 144 | G43: F | H43: =IF(E43<0,100*(E43+F43)/(10000-200*E43-E43*F43),IF(E43>0,(E43*F43-10000)/(100*(E43+F43+200)),0)) -> 0.042333744 | I43: =IF(E43<0,IF(G43="F",-100*(E43+F43)/(E43*(F43+100)),IF(G43="U",-(F43+E43)/(E43-100),0)),IF(E43>0,IF(G43="F",(E43*F43-10000)/(100*F43+10000),IF(G43="U",(E43*F43-10000)/(100*E43+10000),0)),0)) -> 0.073904864 | J43: 138.1 | K43: =IF(E43<0,(H43*J43*-E43*(1+F43/100))/(E43+F43),(100*H43*J43*(100+F43))/(E43*F43-10000)) -> 79.105619 | L43: =IF(E43<0,((100-E43)*H43*J43)/(E43+F43),100*((100+E43)*H43*J43)/(E43*F43-10000)) -> 58.994381 | M43: =H43*J43 -> 5.84629 | N43: =IF(G43="F",(F43*J43)/(100+F43),IF(G43="U",IF(E43<0,(-E43*J43)/(100-E43),IF(E43>0,(100*J43)/(E43+100),0)),0)) -> 81.501639 | O43: =IF(AND(G43="F",E43<>""),(100*J43)/(100+F43),IF(G43="U",IF(E43<0,(100*J43)/(100-E43),IF(E43>0,(E43*J43)/(E43+100),0)),0)) -> 56.598361 | P43: =I43*J43 -> 10.206262 | Q43: F | R43: F | S43: =IF((Q43="F"),IF(R43=G43,P43,0),IF(Q43="E",M43,0)) -> 10.206262 | W43: WEEK 7 | X43: 45277 | Y43: {=SUM(_xlfn._xlws.FILTER(S:S,A:A=X43,0))} -> 205.38485
A44: 45262 | B44: NorthStar | C44: DraftKings | D44: Miro Heiskanen Shots on Goal (U/O 2.5) | E44: -112 | F44: 140 | G44: F | H44: =IF(E44<0,100*(E44+F44)/(10000-200*E44-E44*F44),IF(E44>0,(E44*F44-10000)/(100*(E44+F44+200)),0)) -> 0.058236273 | I44: =IF(E44<0,IF(G44="F",-100*(E44+F44)/(E44*(F44+100)),IF(G44="U",-(F44+E44)/(E44-100),0)),IF(E44>0,IF(G44="F",(E44*F44-10000)/(100*F44+10000),IF(G44="U",(E44*F44-10000)/(100*E44+10000),0)),0)) -> 0.10416667 | J44: 171.43 | K44: =IF(E44<0,(H44*J44*-E44*(1+F44/100))/(E44+F44),(100*H44*J44*(100+F44))/(E44*F44-10000)) -> 95.841065 | L44: =IF(E44<0,((100-E44)*H44*J44)/(E44+F44),100*((100+E44)*H44*J44)/(E44*F44-10000)) -> 75.588935 | M44: =H44*J44 -> 9.9834443 | N44: =IF(G44="F",(F44*J44)/(100+F44),IF(G44="U",IF(E44<0,(-E44*J44)/(100-E44),IF(E44>0,(100*J44)/(E44+100),0)),0)) -> 100.00083 | O44: =IF(AND(G44="F",E44<>""),(100*J44)/(100+F44),IF(G44="U",IF(E44<0,(100*J44)/(100-E44),IF(E44>0,(E44*J44)/(E44+100),0)),0)) -> 71.429167 | P44: =I44*J44 -> 17.857292 | Q44: F | R44: F | S44: =IF((Q44="F"),IF(R44=G44,P44,0),IF(Q44="E",M44,0)) -> 17.857292 | W44: =SUM(Y43:Y49) -> 362.99661 | X44: 45278 | Y44: {=SUM(_xlfn._xlws.FILTER(S:S,A:A=X44,0))} -> 93.934367
A45: 45262 | B45: Fanduel | C45: BetRivers | D45: Jimmy Butler Rebounds (O/U 5.5) | E45: -134 | F45: 150 | G45: F | H45: =IF(E45<0,100*(E45+F45)/(10000-200*E45-E45*F45),IF(E45>0,(E45*F45-10000)/(100*(E45+F45+200)),0)) -> 0.028119508 | I45: =IF(E45<0,IF(G45="F",-100*(E45+F45)/(E45*(F45+100)),IF(G45="U",-(F45+E45)/(E45-100),0)),IF(E45>0,IF(G45="F",(E45*F45-10000)/(100*F45+10000),IF(G45="U",(E45*F45-10000)/(100*E45+10000),0)),0)) -> 0.047761194 | J45: 733.1 | K45: =IF(E45<0,(H45*J45*-E45*(1+F45/100))/(E45+F45),(100*H45*J45*(100+F45))/(E45*F45-10000)) -> 431.61424 | L45: =IF(E45<0,((100-E45)*H45*J45)/(E45+F45),100*((100+E45)*H45*J45)/(E45*F45-10000)) -> 301.48576 | M45: =H45*J45 -> 20.614411 | N45: =IF(G45="F",(F45*J45)/(100+F45),IF(G45="U",IF(E45<0,(-E45*J45)/(100-E45),IF(E45>0,(100*J45)/(E45+100),0)),0)) -> 439.86 | O45: =IF(AND(G45="F",E45<>""),(100*J45)/(100+F45),IF(G45="U",IF(E45<0,(100*J45)/(100-E45),IF(E45>0,(E45*J45)/(E45+100),0)),0)) -> 293.24 | P45: =I45*J45 -> 35.013731 | Q45: F | R45: U | S45: =IF((Q45="F"),IF(R45=G45,P45,0),IF(Q45="E",M45,0)) -> 0 | X45: 45279 | Y45: {=SUM(_xlfn._xlws.FILTER(S:S,A:A=X45,0))} -> 19.210824
A46: 45263 | B46: BetRivers | C46: Betano | D46: Samaje Perine Total Receptions (U/O 2.5) | E46: -117 | F46: 125 | G46: F | H46: =IF(E46<0,100*(E46+F46)/(10000-200*E46-E46*F46),IF(E46>0,(E46*F46-10000)/(100*(E46+F46+200)),0)) -> 0.016657991 | I46: =IF(E46<0,IF(G46="F",-100*(E46+F46)/(E46*(F46+100)),IF(G46="U",-(F46+E46)/(E46-100),0)),IF(E46>0,IF(G46="F",(E46*F46-10000)/(100*F46+10000),IF(G46="U",(E46*F46-10000)/(100*E46+10000),0)),0)) -> 0.030389364 | J46: 1125 | K46: =IF(E46<0,(H46*J46*-E46*(1+F46/100))/(E46+F46),(100*H46*J46*(100+F46))/(E46*F46-10000)) -> 616.671 | L46: =IF(E46<0,((100-E46)*H46*J46)/(E46+F46),100*((100+E46)*H46*J46)/(E46*F46-10000)) -> 508.329 | M46: =H46*J46 -> 18.740239 | N46: =IF(G46="F",(F46*J46)/(100+F46),IF(G46="U",IF(E46<0,(-E46*J46)/(100-E46),IF(E46>0,(100*J46)/(E46+100),0)),0)) -> 625 | O46: =IF(AND(G46="F",E46<>""),(100*J46)/(100+F46),IF(G46="U",IF(E46<0,(100*J46)/(100-E46),IF(E46>0,(E46*J46)/(E46+100),0)),0)) -> 500 | P46: =I46*J46 -> 34.188034 | Q46: F | R46: F | S46: =IF((Q46="F"),IF(R46=G46,P46,0),IF(Q46="E",M46,0)) -> 34.188034 | X46: 45280 | Y46: {=SUM(_xlfn._xlws.FILTER(S:S,A:A=X46,0))} -> 21.739302
A47: 45264 | B47: Bet365 | C47: Fanduel | D47: Jayson Tatum Rebounds (U/O 9.5) | E47: 100 | F47: 105 | G47: F | H47: =IF(E47<0,100*(E47+F47)/(10000-200*E47-E47*F47),IF(E47>0,(E47*F47-10000)/(100*(E47+F47+200)),0)) -> 0.012345679 | I47: =IF(E47<0,IF(G47="F",-100*(E47+F47)/(E47*(F47+100)),IF(G47="U",-(F47+E47)/(E47-100),0)),IF(E47>0,IF(G47="F",(E47*F47-10000)/(100*F47+10000),IF(G47="U",(E47*F47-10000)/(100*E47+10000),0)),0)) -> 0.024390244 | J47: 585.71 | K47: =IF(E47<0,(H47*J47*-E47*(1+F47/100))/(E47+F47),(100*H47*J47*(100+F47))/(E47*F47-10000)) -> 296.47049 | L47: =IF(E47<0,((100-E47)*H47*J47)/(E47+F47),100*((100+E47)*H47*J47)/(E47*F47-10000)) -> 289.23951 | M47: =H47*J47 -> 7.2309877 | N47: =IF(G47="F",(F47*J47)/(100+F47),IF(G47="U",IF(E47<0,(-E47*J47)/(100-E47),IF(E47>0,(100*J47)/(E47+100),0)),0)) -> 299.9978 | O47: =IF(AND(G47="F",E47<>""),(100*J47)/(100+F47),IF(G47="U",IF(E47<0,(100*J47)/(100-E47),IF(E47>0,(E47*J47)/(E47+100),0)),0)) -> 285.7122 | P47: =I47*J47 -> 14.28561 | Q47: F | R47: U | S47: =IF((Q47="F"),IF(R47=G47,P47,0),IF(Q47="E",M47,0)) -> 0 | X47: 45281 | Y47: {=SUM(_xlfn._xlws.FILTER(S:S,A:A=X47,0))} -> 0
A48: 45264 | B48: Betano | C48: Fanduel | D48: Jayson Tatum Rebounds (U/O 9.5) | E48: 102 | F48: 105 | G48: F | H48: =IF(E48<0,100*(E48+F48)/(10000-200*E48-E48*F48),IF(E48>0,(E48*F48-10000)/(100*(E48+F48+200)),0)) -> 0.017444717 | I48: =IF(E48<0,IF(G48="F",-100*(E48+F48)/(E48*(F48+100)),IF(G48="U",-(F48+E48)/(E48-100),0)),IF(E48>0,IF(G48="F",(E48*F48-10000)/(100*F48+10000),IF(G48="U",(E48*F48-10000)/(100*E48+10000),0)),0)) -> 0.034634146 | J48: 820 | K48: =IF(E48<0,(H48*J48*-E48*(1+F48/100))/(E48+F48),(100*H48*J48*(100+F48))/(E48*F48-10000)) -> 413.02211 | L48: =IF(E48<0,((100-E48)*H48*J48)/(E48+F48),100*((100+E48)*H48*J48)/(E48*F48-10000)) -> 406.97789 | M48: =H48*J48 -> 14.304668 | N48: =IF(G48="F",(F48*J48)/(100+F48),IF(G48="U",IF(E48<0,(-E48*J48)/(100-E48),IF(E48>0,(100*J48)/(E48+100),0)),0)) -> 420 | O48: =IF(AND(G48="F",E48<>""),(100*J48)/(100+F48),IF(G48="U",IF(E48<0,(100*J48)/(100-E48),IF(E48>0,(E48*J48)/(E48+100),0)),0)) -> 400 | P48: =I48*J48 -> 28.4 | Q48: F | R48: U | S48: =IF((Q48="F"),IF(R48=G48,P48,0),IF(Q48="E",M48,0)) -> 0 | X48: 45282 | Y48: {=SUM(_xlfn._xlws.FILTER(S:S,A:A=X48,0))} -> 22.727273
A49: 45264 | B49: Betano | C49: NorthStar | D49: Jayson Tatum Rebounds (U/O 9.5) | E49: 102 | F49: 114 | G49: F | H49: =IF(E49<0,100*(E49+F49)/(10000-200*E49-E49*F49),IF(E49>0,(E49*F49-10000)/(100*(E49+F49+200)),0)) -> 0.039134615 | I49: =IF(E49<0,IF(G49="F",-100*(E49+F49)/(E49*(F49+100)),IF(G49="U",-(F49+E49)/(E49-100),0)),IF(E49>0,IF(G49="F",(E49*F49-10000)/(100*F49+10000),IF(G49="U",(E49*F49-10000)/(100*E49+10000),0)),0)) -> 0.076074766 | J49: 107 | K49: =IF(E49<0,(H49*J49*-E49*(1+F49/100))/(E49+F49),(100*H49*J49*(100+F49))/(E49*F49-10000)) -> 55.043269 | L49: =IF(E49<0,((100-E49)*H49*J49)/(E49+F49),100*((100+E49)*H49*J49)/(E49*F49-10000)) -> 51.956731 | M49: =H49*J49 -> 4.1874038 | N49: =IF(G49="F",(F49*J49)/(100+F49),IF(G49="U",IF(E49<0,(-E49*J49)/(100-E49),IF(E49>0,(100*J49)/(E49+100),0)),0)) -> 57 | O49: =IF(AND(G49="F",E49<>""),(100*J49)/(100+F49),IF(G49="U",IF(E49<0,(100*J49)/(100-E49),IF(E49>0,(E49*J49)/(E49+100),0)),0)) -> 50 | P49: =I49*J49 -> 8.14 | Q49: F | R49: U | S49: =IF((Q49="F"),IF(R49=G49,P49,0),IF(Q49="E",M49,0)) -> 0 | X49: 45283 | Y49: {=SUM(_xlfn._xlws.FILTER(S:S,A:A=X49,0))} -> 0
A50: 45265 | B50: TonyBet | C50: TheScore | D50: Vancouver Cancucks/NJ Devils Goals (O/U 6.5) | E50: -110 | F50: 120 | G50: F | H50: =IF(E50<0,100*(E50+F50)/(10000-200*E50-E50*F50),IF(E50>0,(E50*F50-10000)/(100*(E50+F50+200)),0)) -> 0.022123894 | I50: =IF(E50<0,IF(G50="F",-100*(E50+F50)/(E50*(F50+100)),IF(G50="U",-(F50+E50)/(E50-100),0)),IF(E50>0,IF(G50="F",(E50*F50-10000)/(100*F50+10000),IF(G50="U",(E50*F50-10000)/(100*E50+10000),0)),0)) -> 0.041322314 | J50: 641.67 | K50: =IF(E50<0,(H50*J50*-E50*(1+F50/100))/(E50+F50),(100*H50*J50*(100+F50))/(E50*F50-10000)) -> 343.54898 | L50: =IF(E50<0,((100-E50)*H50*J50)/(E50+F50),100*((100+E50)*H50*J50)/(E50*F50-10000)) -> 298.12102 | M50: =H50*J50 -> 14.196239 | N50: =IF(G50="F",(F50*J50)/(100+F50),IF(G50="U",IF(E50<0,(-E50*J50)/(100-E50),IF(E50>0,(100*J50)/(E50+100),0)),0)) -> 350.00182 | O50: =IF(AND(G50="F",E50<>""),(100*J50)/(100+F50),IF(G50="U",IF(E50<0,(100*J50)/(100-E50),IF(E50>0,(E50*J50)/(E50+100),0)),0)) -> 291.66818 | P50: =I50*J50 -> 26.515289 | Q50: F | R50: F | S50: =IF((Q50="F"),IF(R50=G50,P50,0),IF(Q50="E",M50,0)) -> 26.515289 | W50: WEEK 8 | X50: 45284 | Y50: {=SUM(_xlfn._xlws.FILTER(S:S,A:A=X50,0))} -> 22.107174
A51: 45265 | B51: BetRivers | C51: TheScore | D51: Vancouver Cancucks/NJ Devils Goals (O/U 6.5) | E51: -107 | F51: 120 | G51: F | H51: =IF(E51<0,100*(E51+F51)/(10000-200*E51-E51*F51),IF(E51>0,(E51*F51-10000)/(100*(E51+F51+200)),0)) -> 0.029385172 | I51: =IF(E51<0,IF(G51="F",-100*(E51+F51)/(E51*(F51+100)),IF(G51="U",-(F51+E51)/(E51-100),0)),IF(E51>0,IF(G51="F",(E51*F51-10000)/(100*F51+10000),IF(G51="U",(E51*F51-10000)/(100*E51+10000),0)),0)) -> 0.055225149 | J51: 392.76 | K51: =IF(E51<0,(H51*J51*-E51*(1+F51/100))/(E51+F51),(100*H51*J51*(100+F51))/(E51*F51-10000)) -> 208.98667 | L51: =IF(E51<0,((100-E51)*H51*J51)/(E51+F51),100*((100+E51)*H51*J51)/(E51*F51-10000)) -> 183.77333 | M51: =H51*J51 -> 11.54132 | N51: =IF(G51="F",(F51*J51)/(100+F51),IF(G51="U",IF(E51<0,(-E51*J51)/(100-E51),IF(E51>0,(100*J51)/(E51+100),0)),0)) -> 214.23273 | O51: =IF(AND(G51="F",E51<>""),(100*J51)/(100+F51),IF(G51="U",IF(E51<0,(100*J51)/(100-E51),IF(E51>0,(E51*J51)/(E51+100),0)),0)) -> 178.52727 | P51: =I51*J51 -> 21.690229 | Q51: F | R51: F | S51: =IF((Q51="F"),IF(R51=G51,P51,0),IF(Q51="E",M51,0)) -> 21.690229 | W51: =SUM(Y50:Y56) -> 52.876405 | X51: 45285 | Y51: {=SUM(_xlfn._xlws.FILTER(S:S,A:A=X51,0))} -> 0
A52: 45266 | B52: Betano | C52: DraftKings | D52: Philadephia 76ers v Washington Wizards | E52: -250 | F52: 295 | G52: F | H52: =IF(E52<0,100*(E52+F52)/(10000-200*E52-E52*F52),IF(E52>0,(E52*F52-10000)/(100*(E52+F52+200)),0)) -> 0.03364486 | I52: =IF(E52<0,IF(G52="F",-100*(E52+F52)/(E52*(F52+100)),IF(G52="U",-(F52+E52)/(E52-100),0)),IF(E52>0,IF(G52="F",(E52*F52-10000)/(100*F52+10000),IF(G52="U",(E52*F52-10000)/(100*E52+10000),0)),0)) -> 0.04556962 | J52: 1501 | K52: =IF(E52<0,(H52*J52*-E52*(1+F52/100))/(E52+F52),(100*H52*J52*(100+F52))/(E52*F52-10000)) -> 1108.215 | L52: =IF(E52<0,((100-E52)*H52*J52)/(E52+F52),100*((100+E52)*H52*J52)/(E52*F52-10000)) -> 392.78505 | M52: =H52*J52 -> 50.500935 | N52: =IF(G52="F",(F52*J52)/(100+F52),IF(G52="U",IF(E52<0,(-E52*J52)/(100-E52),IF(E52>0,(100*J52)/(E52+100),0)),0)) -> 1121 | O52: =IF(AND(G52="F",E52<>""),(100*J52)/(100+F52),IF(G52="U",IF(E52<0,(100*J52)/(100-E52),IF(E52>0,(E52*J52)/(E52+100),0)),0)) -> 380 | P52: =I52*J52 -> 68.4 | Q52: F | R52: F | S52: =IF((Q52="F"),IF(R52=G52,P52,0),IF(Q52="E",M52,0)) -> 68.4 | X52: 45286 | Y52: {=SUM(_xlfn._xlws.FILTER(S:S,A:A=X52,0))} -> 0
A53: 45264 | B53: Bet365 | C53: Fanduel | D53: CJ McCollum Rebounds (O/U 3.5) | E53: -115 | F53: 120 | G53: F | H53: =IF(E53<0,100*(E53+F53)/(10000-200*E53-E53*F53),IF(E53>0,(E53*F53-10000)/(100*(E53+F53+200)),0)) -> 0.010683761 | I53: =IF(E53<0,IF(G53="F",-100*(E53+F53)/(E53*(F53+100)),IF(G53="U",-(F53+E53)/(E53-100),0)),IF(E53>0,IF(G53="F",(E53*F53-10000)/(100*F53+10000),IF(G53="U",(E53*F53-10000)/(100*E53+10000),0)),0)) -> 0.019762846 | J53: 550 | K53: =IF(E53<0,(H53*J53*-E53*(1+F53/100))/(E53+F53),(100*H53*J53*(100+F53))/(E53*F53-10000)) -> 297.32906 | L53: =IF(E53<0,((100-E53)*H53*J53)/(E53+F53),100*((100+E53)*H53*J53)/(E53*F53-10000)) -> 252.67094 | M53: =H53*J53 -> 5.8760684 | N53: =IF(G53="F",(F53*J53)/(100+F53),IF(G53="U",IF(E53<0,(-E53*J53)/(100-E53),IF(E53>0,(100*J53)/(E53+100),0)),0)) -> 300 | O53: =IF(AND(G53="F",E53<>""),(100*J53)/(100+F53),IF(G53="U",IF(E53<0,(100*J53)/(100-E53),IF(E53>0,(E53*J53)/(E53+100),0)),0)) -> 250 | P53: =I53*J53 -> 10.869565 | Q53: F | R53: U | S53: =IF((Q53="F"),IF(R53=G53,P53,0),IF(Q53="E",M53,0)) -> 0 | X53: 45287 | Y53: {=SUM(_xlfn._xlws.FILTER(S:S,A:A=X53,0))} -> 30.769231
A54: 45265 | B54: BetRivers/NorthStar | C54: Bet888 | D54: Tyler Toffoli PowerPlay Points (U/O 0.5) | E54: -250 | F54: 255 | G54: F | H54: =IF(E54<0,100*(E54+F54)/(10000-200*E54-E54*F54),IF(E54>0,(E54*F54-10000)/(100*(E54+F54+200)),0)) -> 0.004040404 | I54: =IF(E54<0,IF(G54="F",-100*(E54+F54)/(E54*(F54+100)),IF(G54="U",-(F54+E54)/(E54-100),0)),IF(E54>0,IF(G54="F",(E54*F54-10000)/(100*F54+10000),IF(G54="U",(E54*F54-10000)/(100*E54+10000),0)),0)) -> 0.0056338028 | J54: 1060.7 | K54: =IF(E54<0,(H54*J54*-E54*(1+F54/100))/(E54+F54),(100*H54*J54*(100+F54))/(E54*F54-10000)) -> 760.70404 | L54: =IF(E54<0,((100-E54)*H54*J54)/(E54+F54),100*((100+E54)*H54*J54)/(E54*F54-10000)) -> 299.99596 | M54: =H54*J54 -> 4.2856566 | N54: =IF(G54="F",(F54*J54)/(100+F54),IF(G54="U",IF(E54<0,(-E54*J54)/(100-E54),IF(E54>0,(100*J54)/(E54+100),0)),0)) -> 761.91127 | O54: =IF(AND(G54="F",E54<>""),(100*J54)/(100+F54),IF(G54="U",IF(E54<0,(100*J54)/(100-E54),IF(E54>0,(E54*J54)/(E54+100),0)),0)) -> 298.78873 | P54: =I54*J54 -> 5.9757746 | Q54: E | R54: F | S54: =IF((Q54="F"),IF(R54=G54,P54,0),IF(Q54="E",M54,0)) -> 4.2856566 | X54: 45288 | Y54: {=SUM(_xlfn._xlws.FILTER(S:S,A:A=X54,0))} -> 0
A55: 45265 | B55: BetRivers/NorthStar | C55: BetMGM | D55: Jack Hughes PowerPlay Points (U/O 0.5) | E55: -167 | F55: 218 | G55: F | H55: =IF(E55<0,100*(E55+F55)/(10000-200*E55-E55*F55),IF(E55>0,(E55*F55-10000)/(100*(E55+F55+200)),0)) -> 0.06390497 | I55: =IF(E55<0,IF(G55="F",-100*(E55+F55)/(E55*(F55+100)),IF(G55="U",-(F55+E55)/(E55-100),0)),IF(E55>0,IF(G55="F",(E55*F55-10000)/(100*F55+10000),IF(G55="U",(E55*F55-10000)/(100*E55+10000),0)),0)) -> 0.096034346 | J55: 159 | K55: =IF(E55<0,(H55*J55*-E55*(1+F55/100))/(E55+F55),(100*H55*J55*(100+F55))/(E55*F55-10000)) -> 105.80475 | L55: =IF(E55<0,((100-E55)*H55*J55)/(E55+F55),100*((100+E55)*H55*J55)/(E55*F55-10000)) -> 53.195248 | M55: =H55*J55 -> 10.16089 | N55: =IF(G55="F",(F55*J55)/(100+F55),IF(G55="U",IF(E55<0,(-E55*J55)/(100-E55),IF(E55>0,(100*J55)/(E55+100),0)),0)) -> 109 | O55: =IF(AND(G55="F",E55<>""),(100*J55)/(100+F55),IF(G55="U",IF(E55<0,(100*J55)/(100-E55),IF(E55>0,(E55*J55)/(E55+100),0)),0)) -> 50 | P55: =I55*J55 -> 15.269461 | Q55: F | R55: U | S55: =IF((Q55="F"),IF(R55=G55,P55,0),IF(Q55="E",M55,0)) -> 0 | X55: 45289 | Y55: {=SUM(_xlfn._xlws.FILTER(S:S,A:A=X55,0))} -> 0
A56: 45265 | B56: BetRivers/NorthStar | C56: BetMGM | D56: Jack Hughes PowerPlay Points (U/O 0.5) | E56: -167 | F56: 175 | G56: F | H56: =IF(E56<0,100*(E56+F56)/(10000-200*E56-E56*F56),IF(E56>0,(E56*F56-10000)/(100*(E56+F56+200)),0)) -> 0.011015491 | I56: =IF(E56<0,IF(G56="F",-100*(E56+F56)/(E56*(F56+100)),IF(G56="U",-(F56+E56)/(E56-100),0)),IF(E56>0,IF(G56="F",(E56*F56-10000)/(100*F56+10000),IF(G56="U",(E56*F56-10000)/(100*E56+10000),0)),0)) -> 0.017419706 | J56: 371.25 | K56: =IF(E56<0,(H56*J56*-E56*(1+F56/100))/(E56+F56),(100*H56*J56*(100+F56))/(E56*F56-10000)) -> 234.76291 | L56: =IF(E56<0,((100-E56)*H56*J56)/(E56+F56),100*((100+E56)*H56*J56)/(E56*F56-10000)) -> 136.48709 | M56: =H56*J56 -> 4.0895009 | N56: =IF(G56="F",(F56*J56)/(100+F56),IF(G56="U",IF(E56<0,(-E56*J56)/(100-E56),IF(E56>0,(100*J56)/(E56+100),0)),0)) -> 236.25 | O56: =IF(AND(G56="F",E56<>""),(100*J56)/(100+F56),IF(G56="U",IF(E56<0,(100*J56)/(100-E56),IF(E56>0,(E56*J56)/(E56+100),0)),0)) -> 135 | P56: =I56*J56 -> 6.4670659 | Q56: F | R56: U | S56: =IF((Q56="F"),IF(R56=G56,P56,0),IF(Q56="E",M56,0)) -> 0 | X56: 45290 | Y56: {=SUM(_xlfn._xlws.FILTER(S:S,A:A=X56,0))} -> 0
A57: 45265 | B57: Fanduel | C57: Bet365 | D57: Grayson Allen Rebs + Assists (U/O 6.5) | E57: 104 | F57: 105 | G57: F | H57: =IF(E57<0,100*(E57+F57)/(10000-200*E57-E57*F57),IF(E57>0,(E57*F57-10000)/(100*(E57+F57+200)),0)) -> 0.022493888 | I57: =IF(E57<0,IF(G57="F",-100*(E57+F57)/(E57*(F57+100)),IF(G57="U",-(F57+E57)/(E57-100),0)),IF(E57>0,IF(G57="F",(E57*F57-10000)/(100*F57+10000),IF(G57="U",(E57*F57-10000)/(100*E57+10000),0)),0)) -> 0.044878049 | J57: 1025 | K57: =IF(E57<0,(H57*J57*-E57*(1+F57/100))/(E57+F57),(100*H57*J57*(100+F57))/(E57*F57-10000)) -> 513.75306 | L57: =IF(E57<0,((100-E57)*H57*J57)/(E57+F57),100*((100+E57)*H57*J57)/(E57*F57-10000)) -> 511.24694 | M57: =H57*J57 -> 23.056235 | N57: =IF(G57="F",(F57*J57)/(100+F57),IF(G57="U",IF(E57<0,(-E57*J57)/(100-E57),IF(E57>0,(100*J57)/(E57+100),0)),0)) -> 525 | O57: =IF(AND(G57="F",E57<>""),(100*J57)/(100+F57),IF(G57="U",IF(E57<0,(100*J57)/(100-E57),IF(E57>0,(E57*J57)/(E57+100),0)),0)) -> 500 | P57: =I57*J57 -> 46 | Q57: F | R57: F | S57: =IF((Q57="F"),IF(R57=G57,P57,0),IF(Q57="E",M57,0)) -> 46
A58: 45267 | B58: Fanduel | C58: Unibet | D58: Partizan v Milano | E58: -132 | F58: 225 | G58: F | H58: =IF(E58<0,100*(E58+F58)/(10000-200*E58-E58*F58),IF(E58>0,(E58*F58-10000)/(100*(E58+F58+200)),0)) -> 0.14069592 | I58: =IF(E58<0,IF(G58="F",-100*(E58+F58)/(E58*(F58+100)),IF(G58="U",-(F58+E58)/(E58-100),0)),IF(E58>0,IF(G58="F",(E58*F58-10000)/(100*F58+10000),IF(G58="U",(E58*F58-10000)/(100*E58+10000),0)),0)) -> 0.21678322 | J58: 127.53 | K58: =IF(E58<0,(H58*J58*-E58*(1+F58/100))/(E58+F58),(100*H58*J58*(100+F58))/(E58*F58-10000)) -> 82.769092 | L58: =IF(E58<0,((100-E58)*H58*J58)/(E58+F58),100*((100+E58)*H58*J58)/(E58*F58-10000)) -> 44.760908 | M58: =H58*J58 -> 17.94295 | N58: =IF(G58="F",(F58*J58)/(100+F58),IF(G58="U",IF(E58<0,(-E58*J58)/(100-E58),IF(E58>0,(100*J58)/(E58+100),0)),0)) -> 88.29 | O58: =IF(AND(G58="F",E58<>""),(100*J58)/(100+F58),IF(G58="U",IF(E58<0,(100*J58)/(100-E58),IF(E58>0,(E58*J58)/(E58+100),0)),0)) -> 39.24 | P58: =I58*J58 -> 27.646364 | Q58: F | R58: F | S58: =IF((Q58="F"),IF(R58=G58,P58,0),IF(Q58="E",M58,0)) -> 27.646364
A59: 45267 | B59: Fanduel | C59: BetRivers | D59: Partizan v Milano | E59: -132 | F59: 225 | G59: F | H59: =IF(E59<0,100*(E59+F59)/(10000-200*E59-E59*F59),IF(E59>0,(E59*F59-10000)/(100*(E59+F59+200)),0)) -> 0.14069592 | I59: =IF(E59<0,IF(G59="F",-100*(E59+F59)/(E59*(F59+100)),IF(G59="U",-(F59+E59)/(E59-100),0)),IF(E59>0,IF(G59="F",(E59*F59-10000)/(100*F59+10000),IF(G59="U",(E59*F59-10000)/(100*E59+10000),0)),0)) -> 0.21678322 | J59: 520.78 | K59: =IF(E59<0,(H59*J59*-E59*(1+F59/100))/(E59+F59),(100*H59*J59*(100+F59))/(E59*F59-10000)) -> 337.99489 | L59: =IF(E59<0,((100-E59)*H59*J59)/(E59+F59),100*((100+E59)*H59*J59)/(E59*F59-10000)) -> 182.78511 | M59: =H59*J59 -> 73.271619 | N59: =IF(G59="F",(F59*J59)/(100+F59),IF(G59="U",IF(E59<0,(-E59*J59)/(100-E59),IF(E59>0,(100*J59)/(E59+100),0)),0)) -> 360.54 | O59: =IF(AND(G59="F",E59<>""),(100*J59)/(100+F59),IF(G59="U",IF(E59<0,(100*J59)/(100-E59),IF(E59>0,(E59*J59)/(E59+100),0)),0)) -> 160.24 | P59: =I59*J59 -> 112.89636 | Q59: F | R59: F | S59: =IF((Q59="F"),IF(R59=G59,P59,0),IF(Q59="E",M59,0)) -> 112.89636
A60: 45267 | B60: Fanduel | C60: NorthStar | D60: Partizan v Milano | E60: -132 | F60: 248 | G60: F | H60: =IF(E60<0,100*(E60+F60)/(10000-200*E60-E60*F60),IF(E60>0,(E60*F60-10000)/(100*(E60+F60+200)),0)) -> 0.16778523 | I60: =IF(E60<0,IF(G60="F",-100*(E60+F60)/(E60*(F60+100)),IF(G60="U",-(F60+E60)/(E60-100),0)),IF(E60>0,IF(G60="F",(E60*F60-10000)/(100*F60+10000),IF(G60="U",(E60*F60-10000)/(100*E60+10000),0)),0)) -> 0.25252525 | J60: 348 | K60: =IF(E60<0,(H60*J60*-E60*(1+F60/100))/(E60+F60),(100*H60*J60*(100+F60))/(E60*F60-10000)) -> 231.22148 | L60: =IF(E60<0,((100-E60)*H60*J60)/(E60+F60),100*((100+E60)*H60*J60)/(E60*F60-10000)) -> 116.77852 | M60: =H60*J60 -> 58.389262 | N60: =IF(G60="F",(F60*J60)/(100+F60),IF(G60="U",IF(E60<0,(-E60*J60)/(100-E60),IF(E60>0,(100*J60)/(E60+100),0)),0)) -> 248 | O60: =IF(AND(G60="F",E60<>""),(100*J60)/(100+F60),IF(G60="U",IF(E60<0,(100*J60)/(100-E60),IF(E60>0,(E60*J60)/(E60+100),0)),0)) -> 100 | P60: =I60*J60 -> 87.878788 | Q60: F | R60: F | S60: =IF((Q60="F"),IF(R60=G60,P60,0),IF(Q60="E",M60,0)) -> 87.878788
A61: 45267 | B61: Fanduel | C61: NorthStar | D61: Partizan v Milano | E61: -132 | F61: 225 | G61: F | H61: =IF(E61<0,100*(E61+F61)/(10000-200*E61-E61*F61),IF(E61>0,(E61*F61-10000)/(100*(E61+F61+200)),0)) -> 0.14069592 | I61: =IF(E61<0,IF(G61="F",-100*(E61+F61)/(E61*(F61+100)),IF(G61="U",-(F61+E61)/(E61-100),0)),IF(E61>0,IF(G61="F",(E61*F61-10000)/(100*F61+10000),IF(G61="U",(E61*F61-10000)/(100*E61+10000),0)),0)) -> 0.21678322 | J61: 25.71 | K61: =IF(E61<0,(H61*J61*-E61*(1+F61/100))/(E61+F61),(100*H61*J61*(100+F61))/(E61*F61-10000)) -> 16.686218 | L61: =IF(E61<0,((100-E61)*H61*J61)/(E61+F61),100*((100+E61)*H61*J61)/(E61*F61-10000)) -> 9.0237821 | M61: =H61*J61 -> 3.617292 | N61: =IF(G61="F",(F61*J61)/(100+F61),IF(G61="U",IF(E61<0,(-E61*J61)/(100-E61),IF(E61>0,(100*J61)/(E61+100),0)),0)) -> 17.799231 | O61: =IF(AND(G61="F",E61<>""),(100*J61)/(100+F61),IF(G61="U",IF(E61<0,(100*J61)/(100-E61),IF(E61>0,(E61*J61)/(E61+100),0)),0)) -> 7.9107692 | P61: =I61*J61 -> 5.5734965 | Q61: F | R61: F | S61: =IF((Q61="F"),IF(R61=G61,P61,0),IF(Q61="E",M61,0)) -> 5.5734965
A62: 45269 | B62: Unibet | C62: Tonybet | D62: Bristol Bears v Lyon OU | E62: -315 | F62: 330 | G62: F | H62: =IF(E62<0,100*(E62+F62)/(10000-200*E62-E62*F62),IF(E62>0,(E62*F62-10000)/(100*(E62+F62+200)),0)) -> 0.0084769709 | I62: =IF(E62<0,IF(G62="F",-100*(E62+F62)/(E62*(F62+100)),IF(G62="U",-(F62+E62)/(E62-100),0)),IF(E62>0,IF(G62="F",(E62*F62-10000)/(100*F62+10000),IF(G62="U",(E62*F62-10000)/(100*E62+10000),0)),0)) -> 0.011074197 | J62: 179.77 | K62: =IF(E62<0,(H62*J62*-E62*(1+F62/100))/(E62+F62),(100*H62*J62*(100+F62))/(E62*F62-10000)) -> 137.60863 | L62: =IF(E62<0,((100-E62)*H62*J62)/(E62+F62),100*((100+E62)*H62*J62)/(E62*F62-10000)) -> 42.161373 | M62: =H62*J62 -> 1.5239051 | N62: =IF(G62="F",(F62*J62)/(100+F62),IF(G62="U",IF(E62<0,(-E62*J62)/(100-E62),IF(E62>0,(100*J62)/(E62+100),0)),0)) -> 137.96302 | O62: =IF(AND(G62="F",E62<>""),(100*J62)/(100+F62),IF(G62="U",IF(E62<0,(100*J62)/(100-E62),IF(E62>0,(E62*J62)/(E62+100),0)),0)) -> 41.806977 | P62: =I62*J62 -> 1.9908084 | Q62: F | R62: F | S62: =IF((Q62="F"),IF(R62=G62,P62,0),IF(Q62="E",M62,0)) -> 1.9908084
A63: 45269 | B63: BetRivers/NorthStar | C63: Tonybet | D63: Bristol Bears v Lyon OU | E63: -315 | F63: 330 | G63: F | H63: =IF(E63<0,100*(E63+F63)/(10000-200*E63-E63*F63),IF(E63>0,(E63*F63-10000)/(100*(E63+F63+200)),0)) -> 0.0084769709 | I63: =IF(E63<0,IF(G63="F",-100*(E63+F63)/(E63*(F63+100)),IF(G63="U",-(F63+E63)/(E63-100),0)),IF(E63>0,IF(G63="F",(E63*F63-10000)/(100*F63+10000),IF(G63="U",(E63*F63-10000)/(100*E63+10000),0)),0)) -> 0.011074197 | J63: 895.21 | K63: =IF(E63<0,(H63*J63*-E63*(1+F63/100))/(E63+F63),(100*H63*J63*(100+F63))/(E63*F63-10000)) -> 685.25682 | L63: =IF(E63<0,((100-E63)*H63*J63)/(E63+F63),100*((100+E63)*H63*J63)/(E63*F63-10000)) -> 209.95318 | M63: =H63*J63 -> 7.5886691 | N63: =IF(G63="F",(F63*J63)/(100+F63),IF(G63="U",IF(E63<0,(-E63*J63)/(100-E63),IF(E63>0,(100*J63)/(E63+100),0)),0)) -> 687.02163 | O63: =IF(AND(G63="F",E63<>""),(100*J63)/(100+F63),IF(G63="U",IF(E63<0,(100*J63)/(100-E63),IF(E63>0,(E63*J63)/(E63+100),0)),0)) -> 208.18837 | P63: =I63*J63 -> 9.913732 | Q63: F | R63: F | S63: =IF((Q63="F"),IF(R63=G63,P63,0),IF(Q63="E",M63,0)) -> 9.913732
A64: 45279 | B64: BetVictor | C64: Fanduel | D64: Boris Krcmar v Keegan Brown | E64: -125 | F64: 132 | G64: F | H64: =IF(E64<0,100*(E64+F64)/(10000-200*E64-E64*F64),IF(E64>0,(E64*F64-10000)/(100*(E64+F64+200)),0)) -> 0.013592233 | I64: =IF(E64<0,IF(G64="F",-100*(E64+F64)/(E64*(F64+100)),IF(G64="U",-(F64+E64)/(E64-100),0)),IF(E64>0,IF(G64="F",(E64*F64-10000)/(100*F64+10000),IF(G64="U",(E64*F64-10000)/(100*E64+10000),0)),0)) -> 0.024137931 | J64: 348 | K64: =IF(E64<0,(H64*J64*-E64*(1+F64/100))/(E64+F64),(100*H64*J64*(100+F64))/(E64*F64-10000)) -> 195.96117 | L64: =IF(E64<0,((100-E64)*H64*J64)/(E64+F64),100*((100+E64)*H64*J64)/(E64*F64-10000)) -> 152.03883 | M64: =H64*J64 -> 4.7300971 | N64: =IF(G64="F",(F64*J64)/(100+F64),IF(G64="U",IF(E64<0,(-E64*J64)/(100-E64),IF(E64>0,(100*J64)/(E64+100),0)),0)) -> 198 | O64: =IF(AND(G64="F",E64<>""),(100*J64)/(100+F64),IF(G64="U",IF(E64<0,(100*J64)/(100-E64),IF(E64>0,(E64*J64)/(E64+100),0)),0)) -> 150 | P64: =I64*J64 -> 8.4 | Q64: F | R64: F | S64: =IF((Q64="F"),IF(R64=G64,P64,0),IF(Q64="E",M64,0)) -> 8.4
A65: 45267 | B65: TonyBet | C65: BetRivers | D65: Partizan v Milano | E65: -154 | F65: 163 | G65: F | H65: =IF(E65<0,100*(E65+F65)/(10000-200*E65-E65*F65),IF(E65>0,(E65*F65-10000)/(100*(E65+F65+200)),0)) -> 0.013656642 | I65: =IF(E65<0,IF(G65="F",-100*(E65+F65)/(E65*(F65+100)),IF(G65="U",-(F65+E65)/(E65-100),0)),IF(E65>0,IF(G65="F",(E65*F65-10000)/(100*F65+10000),IF(G65="U",(E65*F65-10000)/(100*E65+10000),0)),0)) -> 0.022221125 | J65: 581.73 | K65: =IF(E65<0,(H65*J65*-E65*(1+F65/100))/(E65+F65),(100*H65*J65*(100+F65))/(E65*F65-10000)) -> 357.51917 | L65: =IF(E65<0,((100-E65)*H65*J65)/(E65+F65),100*((100+E65)*H65*J65)/(E65*F65-10000)) -> 224.21083 | M65: =H65*J65 -> 7.9444782 | N65: =IF(G65="F",(F65*J65)/(100+F65),IF(G65="U",IF(E65<0,(-E65*J65)/(100-E65),IF(E65>0,(100*J65)/(E65+100),0)),0)) -> 360.53989 | O65: =IF(AND(G65="F",E65<>""),(100*J65)/(100+F65),IF(G65="U",IF(E65<0,(100*J65)/(100-E65),IF(E65>0,(E65*J65)/(E65+100),0)),0)) -> 221.19011 | P65: =I65*J65 -> 12.926695 | Q65: F | R65: F | S65: =IF((Q65="F"),IF(R65=G65,P65,0),IF(Q65="E",M65,0)) -> 12.926695
A66: 45266 | B66: BetRivers/NorthStar | C66: Bet888 | D66: Jason Robertson PowerPlay Points (U/O 0.5) | E66: -275 | F66: 285 | G66: F | H66: =IF(E66<0,100*(E66+F66)/(10000-200*E66-E66*F66),IF(E66>0,(E66*F66-10000)/(100*(E66+F66+200)),0)) -> 0.0069747167 | I66: =IF(E66<0,IF(G66="F",-100*(E66+F66)/(E66*(F66+100)),IF(G66="U",-(F66+E66)/(E66-100),0)),IF(E66>0,IF(G66="F",(E66*F66-10000)/(100*F66+10000),IF(G66="U",(E66*F66-10000)/(100*E66+10000),0)),0)) -> 0.0094451004 | J66: 1155 | K66: =IF(E66<0,(H66*J66*-E66*(1+F66/100))/(E66+F66),(100*H66*J66*(100+F66))/(E66*F66-10000)) -> 852.90759 | L66: =IF(E66<0,((100-E66)*H66*J66)/(E66+F66),100*((100+E66)*H66*J66)/(E66*F66-10000)) -> 302.09241 | M66: =H66*J66 -> 8.0557977 | N66: =IF(G66="F",(F66*J66)/(100+F66),IF(G66="U",IF(E66<0,(-E66*J66)/(100-E66),IF(E66>0,(100*J66)/(E66+100),0)),0)) -> 855 | O66: =IF(AND(G66="F",E66<>""),(100*J66)/(100+F66),IF(G66="U",IF(E66<0,(100*J66)/(100-E66),IF(E66>0,(E66*J66)/(E66+100),0)),0)) -> 300 | P66: =I66*J66 -> 10.909091 | Q66: F | R66: F | S66: =IF((Q66="F"),IF(R66=G66,P66,0),IF(Q66="E",M66,0)) -> 10.909091
A67: 45266 | B67: Unibet | C67: Bet888 | D67: Jason Robertson PowerPlay Points (U/O 0.5) | E67: -275 | F67: 285 | G67: F | H67: =IF(E67<0,100*(E67+F67)/(10000-200*E67-E67*F67),IF(E67>0,(E67*F67-10000)/(100*(E67+F67+200)),0)) -> 0.0069747167 | I67: =IF(E67<0,IF(G67="F",-100*(E67+F67)/(E67*(F67+100)),IF(G67="U",-(F67+E67)/(E67-100),0)),IF(E67>0,IF(G67="F",(E67*F67-10000)/(100*F67+10000),IF(G67="U",(E67*F67-10000)/(100*E67+10000),0)),0)) -> 0.0094451004 | J67: 193.2 | K67: =IF(E67<0,(H67*J67*-E67*(1+F67/100))/(E67+F67),(100*H67*J67*(100+F67))/(E67*F67-10000)) -> 142.66818 | L67: =IF(E67<0,((100-E67)*H67*J67)/(E67+F67),100*((100+E67)*H67*J67)/(E67*F67-10000)) -> 50.531822 | M67: =H67*J67 -> 1.3475153 | N67: =IF(G67="F",(F67*J67)/(100+F67),IF(G67="U",IF(E67<0,(-E67*J67)/(100-E67),IF(E67>0,(100*J67)/(E67+100),0)),0)) -> 143.01818 | O67: =IF(AND(G67="F",E67<>""),(100*J67)/(100+F67),IF(G67="U",IF(E67<0,(100*J67)/(100-E67),IF(E67>0,(E67*J67)/(E67+100),0)),0)) -> 50.181818 | P67: =I67*J67 -> 1.8247934 | Q67: F | R67: F | S67: =IF((Q67="F"),IF(R67=G67,P67,0),IF(Q67="E",M67,0)) -> 1.8247934
A68: 45266 | B68: Betano | C68: BetRivers/Unibet | D68: Jabari Smith Jr. Rebounds (U/O 9.5) | E68: -114 | F68: 132 | G68: F | H68: =IF(E68<0,100*(E68+F68)/(10000-200*E68-E68*F68),IF(E68>0,(E68*F68-10000)/(100*(E68+F68+200)),0)) -> 0.037619127 | I68: =IF(E68<0,IF(G68="F",-100*(E68+F68)/(E68*(F68+100)),IF(G68="U",-(F68+E68)/(E68-100),0)),IF(E68>0,IF(G68="F",(E68*F68-10000)/(100*F68+10000),IF(G68="U",(E68*F68-10000)/(100*E68+10000),0)),0)) -> 0.068058076 | J68: 236.39 | K68: =IF(E68<0,(H68*J68*-E68*(1+F68/100))/(E68+F68),(100*H68*J68*(100+F68))/(E68*F68-10000)) -> 130.66466 | L68: =IF(E68<0,((100-E68)*H68*J68)/(E68+F68),100*((100+E68)*H68*J68)/(E68*F68-10000)) -> 105.72534 | M68: =H68*J68 -> 8.8927855 | N68: =IF(G68="F",(F68*J68)/(100+F68),IF(G68="U",IF(E68<0,(-E68*J68)/(100-E68),IF(E68>0,(100*J68)/(E68+100),0)),0)) -> 134.49776 | O68: =IF(AND(G68="F",E68<>""),(100*J68)/(100+F68),IF(G68="U",IF(E68<0,(100*J68)/(100-E68),IF(E68>0,(E68*J68)/(E68+100),0)),0)) -> 101.89224 | P68: =I68*J68 -> 16.088249 | Q68: F | R68: U | S68: =IF((Q68="F"),IF(R68=G68,P68,0),IF(Q68="E",M68,0)) -> 0
... A119: 45284 | B119: BetMGM | C119: Bet365 | D119: DK Metcalf Longest Reception Yards (O/U 22.5) | E119: -110 | F119: 115 | G119: U | H119: =IF(E119<0,100*(E119+F119)/(10000-200*E119-E119*F119),IF(E119>0,(E119*F119-10000)/(100*(E119+F119+200)),0)) -> 0.011198208 | I119: =IF(E119<0,IF(G119="F",-100*(E119+F119)/(E119*(F119+100)),IF(G119="U",-(F119+E119)/(E119-100),0)),IF(E119>0,IF(G119="F",(E119*F119-10000)/(100*F119+10000),IF(G119="U",(E119*F119-10000)/(100*E119+10000),0)),0)) -> 0.023809524 | J119: 1145.45 | K119: =IF(E119<0,(H119*J119*-E119*(1+F119/100))/(E119+F119),(100*H119*J119*(100+F119))/(E119*F119-10000)) -> 606.71652 | L119: =IF(E119<0,((100-E119)*H119*J119)/(E119+F119),100*((100+E119)*H119*J119)/(E119*F119-10000)) -> 538.73348 | M119: =H119*J119 -> 12.826988 | N119: =IF(G119="F",(F119*J119)/(100+F119),IF(G119="U",IF(E119<0,(-E119*J119)/(100-E119),IF(E119>0,(100*J119)/(E119+100),0)),0)) -> 599.99762 | O119: =IF(AND(G119="F",E119<>""),(100*J119)/(100+F119),IF(G119="U",IF(E119<0,(100*J119)/(100-E119),IF(E119>0,(E119*J119)/(E119+100),0)),0)) -> 545.45238 | P119: =I119*J119 -> 27.272619 | Q119: F | R119: F | S119: =IF((Q119="F"),IF(R119=G119,P119,0),IF(Q119="E",M119,0)) -> 0
D120: Franz Jorge Soler | E120: -325 | F120: 300 | H120: =IF(E120<0,100*(E120+F120)/(10000-200*E120-E120*F120),IF(E120>0,(E120*F120-10000)/(100*(E120+F120+200)),0)) -> -0.014492754 | I120: =IF(E120<0,IF(G120="F",-100*(E120+F120)/(E120*(F120+100)),IF(G120="U",-(F120+E120)/(E120-100),0)),IF(E120>0,IF(G120="F",(E120*F120-10000)/(100*F120+10000),IF(G120="U",(E120*F120-10000)/(100*E120+10000),0)),0)) -> 0 | J120: 2156.26 | K120: =IF(E120<0,(H120*J120*-E120*(1+F120/100))/(E120+F120),(100*H120*J120*(100+F120))/(E120*F120-10000)) -> 1625.0075 | L120: =IF(E120<0,((100-E120)*H120*J120)/(E120+F120),100*((100+E120)*H120*J120)/(E120*F120-10000)) -> 531.25246 | M120: =H120*J120 -> -31.250145 | N120: =IF(G120="F",(F120*J120)/(100+F120),IF(G120="U",IF(E120<0,(-E120*J120)/(100-E120),IF(E120>0,(100*J120)/(E120+100),0)),0)) -> 0 | O120: =IF(AND(G120="F",E120<>""),(100*J120)/(100+F120),IF(G120="U",IF(E120<0,(100*J120)/(100-E120),IF(E120>0,(E120*J120)/(E120+100),0)),0)) -> 0 | P120: =I120*J120 -> 0 | S120: =IF((Q120="F"),IF(R120=G120,P120,0),IF(Q120="E",M120,0)) -> 0
D121: Roman/Franz Jorge Soler | E121: -325 | F121: 300 | H121: =IF(E121<0,100*(E121+F121)/(10000-200*E121-E121*F121),IF(E121>0,(E121*F121-10000)/(100*(E121+F121+200)),0)) -> -0.014492754 | I121: =IF(E121<0,IF(G121="F",-100*(E121+F121)/(E121*(F121+100)),IF(G121="U",-(F121+E121)/(E121-100),0)),IF(E121>0,IF(G121="F",(E121*F121-10000)/(100*F121+10000),IF(G121="U",(E121*F121-10000)/(100*E121+10000),0)),0)) -> 0 | J121: 278.66 | K121: =IF(E121<0,(H121*J121*-E121*(1+F121/100))/(E121+F121),(100*H121*J121*(100+F121))/(E121*F121-10000)) -> 210.00464 | L121: =IF(E121<0,((100-E121)*H121*J121)/(E121+F121),100*((100+E121)*H121*J121)/(E121*F121-10000)) -> 68.655362 | M121: =H121*J121 -> -4.0385507 | N121: =IF(G121="F",(F121*J121)/(100+F121),IF(G121="U",IF(E121<0,(-E121*J121)/(100-E121),IF(E121>0,(100*J121)/(E121+100),0)),0)) -> 0 | O121: =IF(AND(G121="F",E121<>""),(100*J121)/(100+F121),IF(G121="U",IF(E121<0,(100*J121)/(100-E121),IF(E121>0,(E121*J121)/(E121+100),0)),0)) -> 0 | P121: =I121*J121 -> 0 | S121: =IF((Q121="F"),IF(R121=G121,P121,0),IF(Q121="E",M121,0)) -> 0
D122: Franz Eddie Roasrio | E122: -180 | F122: 175 | H122: =IF(E122<0,100*(E122+F122)/(10000-200*E122-E122*F122),IF(E122>0,(E122*F122-10000)/(100*(E122+F122+200)),0)) -> -0.0064516129 | I122: =IF(E122<0,IF(G122="F",-100*(E122+F122)/(E122*(F122+100)),IF(G122="U",-(F122+E122)/(E122-100),0)),IF(E122>0,IF(G122="F",(E122*F122-10000)/(100*F122+10000),IF(G122="U",(E122*F122-10000)/(100*E122+10000),0)),0)) -> 0 | J122: 1409.09 | K122: =IF(E122<0,(H122*J122*-E122*(1+F122/100))/(E122+F122),(100*H122*J122*(100+F122))/(E122*F122-10000)) -> 899.99942 | L122: =IF(E122<0,((100-E122)*H122*J122)/(E122+F122),100*((100+E122)*H122*J122)/(E122*F122-10000)) -> 509.09058 | M122: =H122*J122 -> -9.0909032 | N122: =IF(G122="F",(F122*J122)/(100+F122),IF(G122="U",IF(E122<0,(-E122*J122)/(100-E122),IF(E122>0,(100*J122)/(E122+100),0)),0)) -> 0 | O122: =IF(AND(G122="F",E122<>""),(100*J122)/(100+F122),IF(G122="U",IF(E122<0,(100*J122)/(100-E122),IF(E122>0,(E122*J122)/(E122+100),0)),0)) -> 0 | P122: =I122*J122 -> 0 | S122: =IF((Q122="F"),IF(R122=G122,P122,0),IF(Q122="E",M122,0)) -> 0
D123: Roman/Franz Breanna Stewart | E123: -110 | F123: 105 | H123: =IF(E123<0,100*(E123+F123)/(10000-200*E123-E123*F123),IF(E123>0,(E123*F123-10000)/(100*(E123+F123+200)),0)) -> -0.011481056 | I123: =IF(E123<0,IF(G123="F",-100*(E123+F123)/(E123*(F123+100)),IF(G123="U",-(F123+E123)/(E123-100),0)),IF(E123>0,IF(G123="F",(E123*F123-10000)/(100*F123+10000),IF(G123="U",(E123*F123-10000)/(100*E123+10000),0)),0)) -> 0 | J123: 394.03 | K123: =IF(E123<0,(H123*J123*-E123*(1+F123/100))/(E123+F123),(100*H123*J123*(100+F123))/(E123*F123-10000)) -> 204.02701 | L123: =IF(E123<0,((100-E123)*H123*J123)/(E123+F123),100*((100+E123)*H123*J123)/(E123*F123-10000)) -> 190.00299 | M123: =H123*J123 -> -4.5238806 | N123: =IF(G123="F",(F123*J123)/(100+F123),IF(G123="U",IF(E123<0,(-E123*J123)/(100-E123),IF(E123>0,(100*J123)/(E123+100),0)),0)) -> 0 | O123: =IF(AND(G123="F",E123<>""),(100*J123)/(100+F123),IF(G123="U",IF(E123<0,(100*J123)/(100-E123),IF(E123>0,(E123*J123)/(E123+100),0)),0)) -> 0 | P123: =I123*J123 -> 0 | S123: =IF((Q123="F"),IF(R123=G123,P123,0),IF(Q123="E",M123,0)) -> 0
D124: Franz Tyler Freeman | E124: -165 | F124: 164.99 | H124: =IF(E124<0,100*(E124+F124)/(10000-200*E124-E124*F124),IF(E124>0,(E124*F124-10000)/(100*(E124+F124+200)),0)) -> -1.4240278e-05 | I124: =IF(E124<0,IF(G124="F",-100*(E124+F124)/(E124*(F124+100)),IF(G124="U",-(F124+E124)/(E124-100),0)),IF(E124>0,IF(G124="F",(E124*F124-10000)/(100*F124+10000),IF(G124="U",(E124*F124-10000)/(100*E124+10000),0)),0)) -> 0 | J124: 1325 | K124: =IF(E124<0,(H124*J124*-E124*(1+F124/100))/(E124+F124),(100*H124*J124*(100+F124))/(E124*F124-10000)) -> 824.98825 | L124: =IF(E124<0,((100-E124)*H124*J124)/(E124+F124),100*((100+E124)*H124*J124)/(E124*F124-10000)) -> 500.01175 | M124: =H124*J124 -> -0.018868368 | N124: =IF(G124="F",(F124*J124)/(100+F124),IF(G124="U",IF(E124<0,(-E124*J124)/(100-E124),IF(E124>0,(100*J124)/(E124+100),0)),0)) -> 0 | O124: =IF(AND(G124="F",E124<>""),(100*J124)/(100+F124),IF(G124="U",IF(E124<0,(100*J124)/(100-E124),IF(E124>0,(E124*J124)/(E124+100),0)),0)) -> 0 | P124: =I124*J124 -> 0 | S124: =IF((Q124="F"),IF(R124=G124,P124,0),IF(Q124="E",M124,0)) -> 0
D125: Franz Daniel Schneeman | E125: -180 | F125: 175 | H125: =IF(E125<0,100*(E125+F125)/(10000-200*E125-E125*F125),IF(E125>0,(E125*F125-10000)/(100*(E125+F125+200)),0)) -> -0.0064516129 | I125: =IF(E125<0,IF(G125="F",-100*(E125+F125)/(E125*(F125+100)),IF(G125="U",-(F125+E125)/(E125-100),0)),IF(E125>0,IF(G125="F",(E125*F125-10000)/(100*F125+10000),IF(G125="U",(E125*F125-10000)/(100*E125+10000),0)),0)) -> 0 | J125: 1409.09 | K125: =IF(E125<0,(H125*J125*-E125*(1+F125/100))/(E125+F125),(100*H125*J125*(100+F125))/(E125*F125-10000)) -> 899.99942 | L125: =IF(E125<0,((100-E125)*H125*J125)/(E125+F125),100*((100+E125)*H125*J125)/(E125*F125-10000)) -> 509.09058 | M125: =H125*J125 -> -9.0909032 | N125: =IF(G125="F",(F125*J125)/(100+F125),IF(G125="U",IF(E125<0,(-E125*J125)/(100-E125),IF(E125>0,(100*J125)/(E125+100),0)),0)) -> 0 | O125: =IF(AND(G125="F",E125<>""),(100*J125)/(100+F125),IF(G125="U",IF(E125<0,(100*J125)/(100-E125),IF(E125>0,(E125*J125)/(E125+100),0)),0)) -> 0 | P125: =I125*J125 -> 0 | S125: =IF((Q125="F"),IF(R125=G125,P125,0),IF(Q125="E",M125,0)) -> 0
D126: Franz Tyler Stephenson | E126: -175 | F126: 170 | H126: =IF(E126<0,100*(E126+F126)/(10000-200*E126-E126*F126),IF(E126>0,(E126*F126-10000)/(100*(E126+F126+200)),0)) -> -0.0066889632 | I126: =IF(E126<0,IF(G126="F",-100*(E126+F126)/(E126*(F126+100)),IF(G126="U",-(F126+E126)/(E126-100),0)),IF(E126>0,IF(G126="F",(E126*F126-10000)/(100*F126+10000),IF(G126="U",(E126*F126-10000)/(100*E126+10000),0)),0)) -> 0 | J126: 1291.14 | K126: =IF(E126<0,(H126*J126*-E126*(1+F126/100))/(E126+F126),(100*H126*J126*(100+F126))/(E126*F126-10000)) -> 816.13866 | L126: =IF(E126<0,((100-E126)*H126*J126)/(E126+F126),100*((100+E126)*H126*J126)/(E126*F126-10000)) -> 475.00134 | M126: =H126*J126 -> -8.636388 | N126: =IF(G126="F",(F126*J126)/(100+F126),IF(G126="U",IF(E126<0,(-E126*J126)/(100-E126),IF(E126>0,(100*J126)/(E126+100),0)),0)) -> 0 | O126: =IF(AND(G126="F",E126<>""),(100*J126)/(100+F126),IF(G126="U",IF(E126<0,(100*J126)/(100-E126),IF(E126>0,(E126*J126)/(E126+100),0)),0)) -> 0 | P126: =I126*J126 -> 0 | S126: =IF((Q126="F"),IF(R126=G126,P126,0),IF(Q126="E",M126,0)) -> 0
D127: Wenceel Perez Total Bases | E127: -175 | F127: 163 | H127: =IF(E127<0,100*(E127+F127)/(10000-200*E127-E127*F127),IF(E127>0,(E127*F127-10000)/(100*(E127+F127+200)),0)) -> -0.016320979 | I127: =IF(E127<0,IF(G127="F",-100*(E127+F127)/(E127*(F127+100)),IF(G127="U",-(F127+E127)/(E127-100),0)),IF(E127>0,IF(G127="F",(E127*F127-10000)/(100*F127+10000),IF(G127="U",(E127*F127-10000)/(100*E127+10000),0)),0)) -> 0 | J127: 962.01 | K127: =IF(E127<0,(H127*J127*-E127*(1+F127/100))/(E127+F127),(100*H127*J127*(100+F127))/(E127*F127-10000)) -> 602.19667 | L127: =IF(E127<0,((100-E127)*H127*J127)/(E127+F127),100*((100+E127)*H127*J127)/(E127*F127-10000)) -> 359.81333 | M127: =H127*J127 -> -15.700945 | N127: =IF(G127="F",(F127*J127)/(100+F127),IF(G127="U",IF(E127<0,(-E127*J127)/(100-E127),IF(E127>0,(100*J127)/(E127+100),0)),0)) -> 0 | O127: =IF(AND(G127="F",E127<>""),(100*J127)/(100+F127),IF(G127="U",IF(E127<0,(100*J127)/(100-E127),IF(E127>0,(E127*J127)/(E127+100),0)),0)) -> 0 | P127: =I127*J127 -> 0 | S127: =IF((Q127="F"),IF(R127=G127,P127,0),IF(Q127="E",M127,0)) -> 0
D128: Blake Snell Strikeouts | E128: -150 | F128: 160 | H128: =IF(E128<0,100*(E128+F128)/(10000-200*E128-E128*F128),IF(E128>0,(E128*F128-10000)/(100*(E128+F128+200)),0)) -> 0.015625 | I128: =IF(E128<0,IF(G128="F",-100*(E128+F128)/(E128*(F128+100)),IF(G128="U",-(F128+E128)/(E128-100),0)),IF(E128>0,IF(G128="F",(E128*F128-10000)/(100*F128+10000),IF(G128="U",(E128*F128-10000)/(100*E128+10000),0)),0)) -> 0 | J128: 518 | K128: =IF(E128<0,(H128*J128*-E128*(1+F128/100))/(E128+F128),(100*H128*J128*(100+F128))/(E128*F128-10000)) -> 315.65625 | L128: =IF(E128<0,((100-E128)*H128*J128)/(E128+F128),100*((100+E128)*H128*J128)/(E128*F128-10000)) -> 202.34375 | M128: =H128*J128 -> 8.09375 | N128: =IF(G128="F",(F128*J128)/(100+F128),IF(G128="U",IF(E128<0,(-E128*J128)/(100-E128),IF(E128>0,(100*J128)/(E128+100),0)),0)) -> 0 | O128: =IF(AND(G128="F",E128<>""),(100*J128)/(100+F128),IF(G128="U",IF(E128<0,(100*J128)/(100-E128),IF(E128>0,(E128*J128)/(E128+100),0)),0)) -> 0 | P128: =I128*J128 -> 0 | S128: =IF((Q128="F"),IF(R128=G128,P128,0),IF(Q128="E",M128,0)) -> 0
D129: Miguel Rojas Total Bases | E129: -170 | F129: 155 | H129: =IF(E129<0,100*(E129+F129)/(10000-200*E129-E129*F129),IF(E129>0,(E129*F129-10000)/(100*(E129+F129+200)),0)) -> -0.021321962 | I129: =IF(E129<0,IF(G129="F",-100*(E129+F129)/(E129*(F129+100)),IF(G129="U",-(F129+E129)/(E129-100),0)),IF(E129>0,IF(G129="F",(E129*F129-10000)/(100*F129+10000),IF(G129="U",(E129*F129-10000)/(100*E129+10000),0)),0)) -> 0 | J129: 984.89 | K129: =IF(E129<0,(H129*J129*-E129*(1+F129/100))/(E129+F129),(100*H129*J129*(100+F129))/(E129*F129-10000)) -> 606.89384 | L129: =IF(E129<0,((100-E129)*H129*J129)/(E129+F129),100*((100+E129)*H129*J129)/(E129*F129-10000)) -> 377.99616 | M129: =H129*J129 -> -20.999787 | N129: =IF(G129="F",(F129*J129)/(100+F129),IF(G129="U",IF(E129<0,(-E129*J129)/(100-E129),IF(E129>0,(100*J129)/(E129+100),0)),0)) -> 0 | O129: =IF(AND(G129="F",E129<>""),(100*J129)/(100+F129),IF(G129="U",IF(E129<0,(100*J129)/(100-E129),IF(E129>0,(E129*J129)/(E129+100),0)),0)) -> 0 | P129: =I129*J129 -> 0 | S129: =IF((Q129="F"),IF(R129=G129,P129,0),IF(Q129="E",M129,0)) -> 0
D130: MJ Melendez Total Bases | E130: -135 | F130: 138 | H130: =IF(E130<0,100*(E130+F130)/(10000-200*E130-E130*F130),IF(E130>0,(E130*F130-10000)/(100*(E130+F130+200)),0)) -> 0.0053927737 | I130: =IF(E130<0,IF(G130="F",-100*(E130+F130)/(E130*(F130+100)),IF(G130="U",-(F130+E130)/(E130-100),0)),IF(E130>0,IF(G130="F",(E130*F130-10000)/(100*F130+10000),IF(G130="U",(E130*F130-10000)/(100*E130+10000),0)),0)) -> 0 | J130: 1180 | K130: =IF(E130<0,(H130*J130*-E130*(1+F130/100))/(E130+F130),(100*H130*J130*(100+F130))/(E130*F130-10000)) -> 681.52795 | L130: =IF(E130<0,((100-E130)*H130*J130)/(E130+F130),100*((100+E130)*H130*J130)/(E130*F130-10000)) -> 498.47205 | M130: =H130*J130 -> 6.3634729 | N130: =IF(G130="F",(F130*J130)/(100+F130),IF(G130="U",IF(E130<0,(-E130*J130)/(100-E130),IF(E130>0,(100*J130)/(E130+100),0)),0)) -> 0 | O130: =IF(AND(G130="F",E130<>""),(100*J130)/(100+F130),IF(G130="U",IF(E130<0,(100*J130)/(100-E130),IF(E130>0,(E130*J130)/(E130+100),0)),0)) -> 0 | P130: =I130*J130 -> 0 | S130: =IF((Q130="F"),IF(R130=G130,P130,0),IF(Q130="E",M130,0)) -> 0
D131: Mickey Moniak Total Bases | E131: -180 | F131: 160 | H131: =IF(E131<0,100*(E131+F131)/(10000-200*E131-E131*F131),IF(E131>0,(E131*F131-10000)/(100*(E131+F131+200)),0)) -> -0.026737968 | I131: =IF(E131<0,IF(G131="F",-100*(E131+F131)/(E131*(F131+100)),IF(G131="U",-(F131+E131)/(E131-100),0)),IF(E131>0,IF(G131="F",(E131*F131-10000)/(100*F131+10000),IF(G131="U",(E131*F131-10000)/(100*E131+10000),0)),0)) -> 0 | J131: 208.64 | K131: =IF(E131<0,(H131*J131*-E131*(1+F131/100))/(E131+F131),(100*H131*J131*(100+F131))/(E131*F131-10000)) -> 130.53947 | L131: =IF(E131<0,((100-E131)*H131*J131)/(E131+F131),100*((100+E131)*H131*J131)/(E131*F131-10000)) -> 78.100535 | M131: =H131*J131 -> -5.5786096 | N131: =IF(G131="F",(F131*J131)/(100+F131),IF(G131="U",IF(E131<0,(-E131*J131)/(100-E131),IF(E131>0,(100*J131)/(E131+100),0)),0)) -> 0 | O131: =IF(AND(G131="F",E131<>""),(100*J131)/(100+F131),IF(G131="U",IF(E131<0,(100*J131)/(100-E131),IF(E131>0,(E131*J131)/(E131+100),0)),0)) -> 0 | P131: =I131*J131 -> 0 | S131: =IF((Q131="F"),IF(R131=G131,P131,0),IF(Q131="E",M131,0)) -> 0
D132: Phoenix Mercurcy Moneyline+D132 | E132: -140 | F132: 130 | H132: =IF(E132<0,100*(E132+F132)/(10000-200*E132-E132*F132),IF(E132>0,(E132*F132-10000)/(100*(E132+F132+200)),0)) -> -0.017793594 | I132: =IF(E132<0,IF(G132="F",-100*(E132+F132)/(E132*(F132+100)),IF(G132="U",-(F132+E132)/(E132-100),0)),IF(E132>0,IF(G132="F",(E132*F132-10000)/(100*F132+10000),IF(G132="U",(E132*F132-10000)/(100*E132+10000),0)),0)) -> 0 | J132: 1343.92 | K132: =IF(E132<0,(H132*J132*-E132*(1+F132/100))/(E132+F132),(100*H132*J132*(100+F132))/(E132*F132-10000)) -> 770.00399 | L132: =IF(E132<0,((100-E132)*H132*J132)/(E132+F132),100*((100+E132)*H132*J132)/(E132*F132-10000)) -> 573.91601 | M132: =H132*J132 -> -23.913167 | N132: =IF(G132="F",(F132*J132)/(100+F132),IF(G132="U",IF(E132<0,(-E132*J132)/(100-E132),IF(E132>0,(100*J132)/(E132+100),0)),0)) -> 0 | O132: =IF(AND(G132="F",E132<>""),(100*J132)/(100+F132),IF(G132="U",IF(E132<0,(100*J132)/(100-E132),IF(E132>0,(E132*J132)/(E132+100),0)),0)) -> 0 | P132: =I132*J132 -> 0 | S132: =IF((Q132="F"),IF(R132=G132,P132,0),IF(Q132="E",M132,0)) -> 0
H133: =IF(E133<0,100*(E133+F133)/(10000-200*E133-E133*F133),IF(E133>0,(E133*F133-10000)/(100*(E133+F133+200)),0)) -> 0 | I133: =IF(E133<0,IF(G133="F",-100*(E133+F133)/(E133*(F133+100)),IF(G133="U",-(F133+E133)/(E133-100),0)),IF(E133>0,IF(G133="F",(E133*F133-10000)/(100*F133+10000),IF(G133="U",(E133*F133-10000)/(100*E133+10000),0)),0)) -> 0 | J133: 0 | K133: =IF(E133<0,(H133*J133*-E133*(1+F133/100))/(E133+F133),(100*H133*J133*(100+F133))/(E133*F133-10000)) -> 0 | L133: =IF(E133<0,((100-E133)*H133*J133)/(E133+F133),100*((100+E133)*H133*J133)/(E133*F133-10000)) -> 0 | M133: =H133*J133 -> 0 | N133: =IF(G133="F",(F133*J133)/(100+F133),IF(G133="U",IF(E133<0,(-E133*J133)/(100-E133),IF(E133>0,(100*J133)/(E133+100),0)),0)) -> 0 | O133: =IF(AND(G133="F",E133<>""),(100*J133)/(100+F133),IF(G133="U",IF(E133<0,(100*J133)/(100-E133),IF(E133>0,(E133*J133)/(E133+100),0)),0)) -> 0 | P133: =I133*J133 -> 0 | S133: =IF((Q133="F"),IF(R133=G133,P133,0),IF(Q133="E",M133,0)) -> 0
H134: =IF(E134<0,100*(E134+F134)/(10000-200*E134-E134*F134),IF(E134>0,(E134*F134-10000)/(100*(E134+F134+200)),0)) -> 0 | I134: =IF(E134<0,IF(G134="F",-100*(E134+F134)/(E134*(F134+100)),IF(G134="U",-(F134+E134)/(E134-100),0)),IF(E134>0,IF(G134="F",(E134*F134-10000)/(100*F134+10000),IF(G134="U",(E134*F134-10000)/(100*E134+10000),0)),0)) -> 0 | J134: 0 | K134: =IF(E134<0,(H134*J134*-E134*(1+F134/100))/(E134+F134),(100*H134*J134*(100+F134))/(E134*F134-10000)) -> 0 | L134: =IF(E134<0,((100-E134)*H134*J134)/(E134+F134),100*((100+E134)*H134*J134)/(E134*F134-10000)) -> 0 | M134: =H134*J134 -> 0 | N134: =IF(G134="F",(F134*J134)/(100+F134),IF(G134="U",IF(E134<0,(-E134*J134)/(100-E134),IF(E134>0,(100*J134)/(E134+100),0)),0)) -> 0 | O134: =IF(AND(G134="F",E134<>""),(100*J134)/(100+F134),IF(G134="U",IF(E134<0,(100*J134)/(100-E134),IF(E134>0,(E134*J134)/(E134+100),0)),0)) -> 0 | P134: =I134*J134 -> 0 | S134: =IF((Q134="F"),IF(R134=G134,P134,0),IF(Q134="E",M134,0)) -> 0
H135: =IF(E135<0,100*(E135+F135)/(10000-200*E135-E135*F135),IF(E135>0,(E135*F135-10000)/(100*(E135+F135+200)),0)) -> 0 | I135: =IF(E135<0,IF(G135="F",-100*(E135+F135)/(E135*(F135+100)),IF(G135="U",-(F135+E135)/(E135-100),0)),IF(E135>0,IF(G135="F",(E135*F135-10000)/(100*F135+10000),IF(G135="U",(E135*F135-10000)/(100*E135+10000),0)),0)) -> 0 | J135: 0 | K135: =IF(E135<0,(H135*J135*-E135*(1+F135/100))/(E135+F135),(100*H135*J135*(100+F135))/(E135*F135-10000)) -> 0 | L135: =IF(E135<0,((100-E135)*H135*J135)/(E135+F135),100*((100+E135)*H135*J135)/(E135*F135-10000)) -> 0 | M135: =H135*J135 -> 0 | N135: =IF(G135="F",(F135*J135)/(100+F135),IF(G135="U",IF(E135<0,(-E135*J135)/(100-E135),IF(E135>0,(100*J135)/(E135+100),0)),0)) -> 0 | O135: =IF(AND(G135="F",E135<>""),(100*J135)/(100+F135),IF(G135="U",IF(E135<0,(100*J135)/(100-E135),IF(E135>0,(E135*J135)/(E135+100),0)),0)) -> 0 | P135: =I135*J135 -> 0 | S135: =IF((Q135="F"),IF(R135=G135,P135,0),IF(Q135="E",M135,0)) -> 0
H136: =IF(E136<0,100*(E136+F136)/(10000-200*E136-E136*F136),IF(E136>0,(E136*F136-10000)/(100*(E136+F136+200)),0)) -> 0 | I136: =IF(E136<0,IF(G136="F",-100*(E136+F136)/(E136*(F136+100)),IF(G136="U",-(F136+E136)/(E136-100),0)),IF(E136>0,IF(G136="F",(E136*F136-10000)/(100*F136+10000),IF(G136="U",(E136*F136-10000)/(100*E136+10000),0)),0)) -> 0 | J136: 0 | K136: =IF(E136<0,(H136*J136*-E136*(1+F136/100))/(E136+F136),(100*H136*J136*(100+F136))/(E136*F136-10000)) -> 0 | L136: =IF(E136<0,((100-E136)*H136*J136)/(E136+F136),100*((100+E136)*H136*J136)/(E136*F136-10000)) -> 0 | M136: =H136*J136 -> 0 | N136: =IF(G136="F",(F136*J136)/(100+F136),IF(G136="U",IF(E136<0,(-E136*J136)/(100-E136),IF(E136>0,(100*J136)/(E136+100),0)),0)) -> 0 | O136: =IF(AND(G136="F",E136<>""),(100*J136)/(100+F136),IF(G136="U",IF(E136<0,(100*J136)/(100-E136),IF(E136>0,(E136*J136)/(E136+100),0)),0)) -> 0 | P136: =I136*J136 -> 0 | S136: =IF((Q136="F"),IF(R136=G136,P136,0),IF(Q136="E",M136,0)) -> 0
H137: =IF(E137<0,100*(E137+F137)/(10000-200*E137-E137*F137),IF(E137>0,(E137*F137-10000)/(100*(E137+F137+200)),0)) -> 0 | I137: =IF(E137<0,IF(G137="F",-100*(E137+F137)/(E137*(F137+100)),IF(G137="U",-(F137+E137)/(E137-100),0)),IF(E137>0,IF(G137="F",(E137*F137-10000)/(100*F137+10000),IF(G137="U",(E137*F137-10000)/(100*E137+10000),0)),0)) -> 0 | J137: 0 | K137: =IF(E137<0,(H137*J137*-E137*(1+F137/100))/(E137+F137),(100*H137*J137*(100+F137))/(E137*F137-10000)) -> 0 | L137: =IF(E137<0,((100-E137)*H137*J137)/(E137+F137),100*((100+E137)*H137*J137)/(E137*F137-10000)) -> 0 | M137: =H137*J137 -> 0 | N137: =IF(G137="F",(F137*J137)/(100+F137),IF(G137="U",IF(E137<0,(-E137*J137)/(100-E137),IF(E137>0,(100*J137)/(E137+100),0)),0)) -> 0 | O137: =IF(AND(G137="F",E137<>""),(100*J137)/(100+F137),IF(G137="U",IF(E137<0,(100*J137)/(100-E137),IF(E137>0,(E137*J137)/(E137+100),0)),0)) -> 0 | P137: =I137*J137 -> 0 | S137: =IF((Q137="F"),IF(R137=G137,P137,0),IF(Q137="E",M137,0)) -> 0
H138: =IF(E138<0,100*(E138+F138)/(10000-200*E138-E138*F138),IF(E138>0,(E138*F138-10000)/(100*(E138+F138+200)),0)) -> 0 | I138: =IF(E138<0,IF(G138="F",-100*(E138+F138)/(E138*(F138+100)),IF(G138="U",-(F138+E138)/(E138-100),0)),IF(E138>0,IF(G138="F",(E138*F138-10000)/(100*F138+10000),IF(G138="U",(E138*F138-10000)/(100*E138+10000),0)),0)) -> 0 | J138: 0 | K138: =IF(E138<0,(H138*J138*-E138*(1+F138/100))/(E138+F138),(100*H138*J138*(100+F138))/(E138*F138-10000)) -> 0 | L138: =IF(E138<0,((100-E138)*H138*J138)/(E138+F138),100*((100+E138)*H138*J138)/(E138*F138-10000)) -> 0 | M138: =H138*J138 -> 0 | N138: =IF(G138="F",(F138*J138)/(100+F138),IF(G138="U",IF(E138<0,(-E138*J138)/(100-E138),IF(E138>0,(100*J138)/(E138+100),0)),0)) -> 0 | O138: =IF(AND(G138="F",E138<>""),(100*J138)/(100+F138),IF(G138="U",IF(E138<0,(100*J138)/(100-E138),IF(E138>0,(E138*J138)/(E138+100),0)),0)) -> 0 | P138: =I138*J138 -> 0 | S138: =IF((Q138="F"),IF(R138=G138,P138,0),IF(Q138="E",M138,0)) -> 0
H139: =IF(E139<0,100*(E139+F139)/(10000-200*E139-E139*F139),IF(E139>0,(E139*F139-10000)/(100*(E139+F139+200)),0)) -> 0 | I139: =IF(E139<0,IF(G139="F",-100*(E139+F139)/(E139*(F139+100)),IF(G139="U",-(F139+E139)/(E139-100),0)),IF(E139>0,IF(G139="F",(E139*F139-10000)/(100*F139+10000),IF(G139="U",(E139*F139-10000)/(100*E139+10000),0)),0)) -> 0 | J139: 0 | K139: =IF(E139<0,(H139*J139*-E139*(1+F139/100))/(E139+F139),(100*H139*J139*(100+F139))/(E139*F139-10000)) -> 0 | L139: =IF(E139<0,((100-E139)*H139*J139)/(E139+F139),100*((100+E139)*H139*J139)/(E139*F139-10000)) -> 0 | M139: =H139*J139 -> 0 | N139: =IF(G139="F",(F139*J139)/(100+F139),IF(G139="U",IF(E139<0,(-E139*J139)/(100-E139),IF(E139>0,(100*J139)/(E139+100),0)),0)) -> 0 | O139: =IF(AND(G139="F",E139<>""),(100*J139)/(100+F139),IF(G139="U",IF(E139<0,(100*J139)/(100-E139),IF(E139>0,(E139*J139)/(E139+100),0)),0)) -> 0 | P139: =I139*J139 -> 0 | S139: =IF((Q139="F"),IF(R139=G139,P139,0),IF(Q139="E",M139,0)) -> 0
H140: =IF(E140<0,100*(E140+F140)/(10000-200*E140-E140*F140),IF(E140>0,(E140*F140-10000)/(100*(E140+F140+200)),0)) -> 0 | I140: =IF(E140<0,IF(G140="F",-100*(E140+F140)/(E140*(F140+100)),IF(G140="U",-(F140+E140)/(E140-100),0)),IF(E140>0,IF(G140="F",(E140*F140-10000)/(100*F140+10000),IF(G140="U",(E140*F140-10000)/(100*E140+10000),0)),0)) -> 0 | J140: 0 | K140: =IF(E140<0,(H140*J140*-E140*(1+F140/100))/(E140+F140),(100*H140*J140*(100+F140))/(E140*F140-10000)) -> 0 | L140: =IF(E140<0,((100-E140)*H140*J140)/(E140+F140),100*((100+E140)*H140*J140)/(E140*F140-10000)) -> 0 | M140: =H140*J140 -> 0 | N140: =IF(G140="F",(F140*J140)/(100+F140),IF(G140="U",IF(E140<0,(-E140*J140)/(100-E140),IF(E140>0,(100*J140)/(E140+100),0)),0)) -> 0 | O140: =IF(AND(G140="F",E140<>""),(100*J140)/(100+F140),IF(G140="U",IF(E140<0,(100*J140)/(100-E140),IF(E140>0,(E140*J140)/(E140+100),0)),0)) -> 0 | P140: =I140*J140 -> 0 | S140: =IF((Q140="F"),IF(R140=G140,P140,0),IF(Q140="E",M140,0)) -> 0
C144: NSB
C145: franz put | D145: roman put
B146: magomed ribeiro | C146: 1000 bc +315 | D146: 2486.84 -375
D147: loaned franz 2k
D148: placed bet $210 at -325 jorge soler

Sheet +EV Betting
A1: Date | B1: Prop | C1: Sportsbook | D1: PinnaclePickLine | E1: PinnacleOppLine | F1: WagerLine | G1: TrueOdds | H1: KellyWager | I1: ActualWager | J1: Payout | K1: EV ($) | L1: EV (%) | M1: Event(Y/N) | N1: Profit/Loss | O1: BANKROLL ($) | P1: TOTAL WAGERED | S1: DATE | T1: Daily P/L | U1: Overall P/L | V1: Wagered | W1: # Wagers | X1: EV ($) | Y1: Overall EV ($) | Z1: AVG | AD1: Unique Pinny TrueOdds | AE1: # Occurences | AF1: Hit Rate | AG1: Difference from True Odds to Real Life Results | AH1: Average of Difference (Pinny Accuracy) | AO1: Pinny Equiv Payout | AP1: Pinny Equiv P/L | AQ1: Reg P/L | AR1: Cumulative Difference | AS1: Total Pinny Equiv P/L | AW1: April | AX1: May
A2: 45255 | B2: North Texas Moneyline (v UAB) | C2: TheScore | D2: -131 | E2: 130 | F2: -130 | G2: =IF(AND(D2<0,E2<0),(D2*E2-100*D2)/(2*D2*E2-100*D2-100*E2),IF(OR(AND(D2<0,E2>0),AND(D2>0,E2<0)),IF(D2<=E2,(100*D2+D2*E2)/(200*D2+D2*E2-10000),(100*E2-10000)/(200*E2+D2*E2-10000)),0)) -> 0.56603419 | H2: =IF(F2<0,G2+(1-G2)*(F2/100),IF(F2>0,G2-(1-G2)*(100/F2),0))*$O$2/2 -> 4.6965997 | I2: 200 | J2: =IF(F2<0,I2/(F2/-100),I2*F2/100) -> 153.84615 | K2: =G2*J2-(1-G2)*I2 -> 0.28902152 | L2: =IF(F2>0,(G2*F2/100-(1-G2)),IF(F2<0,(G2*100/-F2-(1-G2)),0)) -> 0.0014451076 | M2: Y | N2: =IF(ISERROR(SEARCH("(Bonus Bet)",B2)),IF(M2="Y",J2,IF(M2="N",-I2,0)),IF(M2="N",0,IF(M2="Y",J2,0))) -> 153.84615 | O2: 5000 | P2: =SUM(I:I) -> 381866.31 | R2: WEEK 1 | S2: 45254 | T2: {=SUM(_xlfn._xlws.FILTER(N:N,A:A=S2,0))} -> 83.333333 | U2: =T2 -> 83.333333 | V2: {=SUM(_xlfn._xlws.FILTER(I:I,A:A=S2,0))} -> 200 | W2: {=COUNT(_xlfn._xlws.FILTER(I:I,A:A=S2,""))} -> 1 | X2: {=SUM(_xlfn._xlws.FILTER(K:K,A:A=S2,0))} -> 0 | Y2: =0 -> 0 | Z2: =AVERAGEIF(W:W,"<>0") -> 25.16129 | AA2: Bets/Day | AD2: {=_xlfn.UNIQUE(G2:G4000,FALSE,FALSE)} -> 0.56603419 | AE2: {=COUNTIF(G2:G4000,AD2:AD2001)} -> 2 | AF2: =COUNTIFS($G$2:$G$4000,AD2,$M$2:$M$4000,"=Y")/AE2 -> 1 | AG2: =AD2-AF2 -> -0.43396581 | AH2: =AVERAGEIF(AG:AG,"<>0") -> 0.0086328667 | AK2: {=_xlfn._xlws.FILTER(AD2:AD2000,(AD2:AD2000<0.1)*(AD2:AD2000>0))} -> 0.090334237 | AL2: {=COUNTIF(G2:G4000,AK2:AK48)} -> 1 | AM2: =COUNTIFS($G$2:$G$4000,AK2,$M$2:$M$4000,"=Y") -> 0 | AO2: =IF(D2<0,I2/(D2/-100),I2*D2/100) -> 152.67176 | AP2: =IF(ISERROR(SEARCH("(Bonus Bet)",B2)),IF(M2="Y",AO2,IF(M2="N",-I2,0)),IF(M2="N",0,IF(M2="Y",AO2,0))) -> 152.67176 | AQ2: =N2 -> 153.84615 | AR2: =AQ2-AP2 -> 1.1743981 | AS2: =SUM(AP:AP) -> -25279.526 | AV2: In | AW2: -4020.9 | AX2: -2034.78
A3: 45257 | B3: Alexander Mattison Under 2.5 Receptions | C3: Fanduel | D3: -154 | E3: 154 | F3: -154 | G3: =IF(AND(D3<0,E3<0),(D3*E3-100*D3)/(2*D3*E3-100*D3-100*E3),IF(OR(AND(D3<0,E3>0),AND(D3>0,E3<0)),IF(D3<=E3,(100*D3+D3*E3)/(200*D3+D3*E3-10000),(100*E3-10000)/(200*E3+D3*E3-10000)),0)) -> 0.60629921 | H3: =IF(F3<0,G3+(1-G3)*(F3/100),IF(F3>0,G3-(1-G3)*(100/F3),0))*$O$2/2 -> 2.7755576e-13 | I3: 200 | J3: =IF(F3<0,I3/(F3/-100),I3*F3/100) -> 129.87013 | K3: =G3*J3-(1-G3)*I3 -> 0 | L3: =IF(F3>0,(G3*F3/100-(1-G3)),IF(F3<0,(G3*100/-F3-(1-G3)),0)) -> 5.5511151e-17 | M3: Y | N3: =IF(ISERROR(SEARCH("(Bonus Bet)",B3)),IF(M3="Y",J3,IF(M3="N",-I3,0)),IF(M3="N",0,IF(M3="Y",J3,0))) -> 129.87013 | O3: OVERALL EV ($) | P3: AVERAGE EV (%) | R3: =SUM(T2:T10) -> 1240.7935 | S3: 45255 | T3: {=SUM(_xlfn._xlws.FILTER(N:N,A:A=S3,0))} -> 153.84615 | U3: =U2+T3 -> 237.17949 | V3: {=SUM(_xlfn._xlws.FILTER(I:I,A:A=S3,0))} -> 200 | W3: {=COUNT(_xlfn._xlws.FILTER(I:I,A:A=S3,""))} -> 1 | X3: {=SUM(_xlfn._xlws.FILTER(K:K,A:A=S3,0))} -> 0.28902152 | Y3: =Y2+X3 -> 0.28902152 | Z3: =AVERAGEIF(V:V,"<>0") -> 2463.6536 | AA3: Wagered/Day | AD3: 0.60629921 | AE3: 2 | AF3: =COUNTIFS($G$2:$G$4000,AD3,$M$2:$M$4000,"=Y")/AE3 -> 1 | AG3: =AD3-AF3 -> -0.39370079 | AK3: 0.097786724 | AL3: 1 | AM3: =COUNTIFS($G$2:$G$4000,AK3,$M$2:$M$4000,"=Y") -> 0 | AO3: =IF(D3<0,I3/(D3/-100),I3*D3/100) -> 129.87013 | AP3: =IF(ISERROR(SEARCH("(Bonus Bet)",B3)),IF(M3="Y",AO3,IF(M3="N",-I3,0)),IF(M3="N",0,IF(M3="Y",AO3,0))) -> 129.87013 | AQ3: =N3 -> 129.87013 | AR3: =AQ3-AP3+AR2 -> 1.1743981 | AV3: Out | AW3: 3767.28 | AX3: 1569.73
A4: 45256 | B4: Seth Jarvis Under 2.5 Shots on Goal | C4: DraftKings | D4: -110 | E4: 110 | F4: -110 | G4: =IF(AND(D4<0,E4<0),(D4*E4-100*D4)/(2*D4*E4-100*D4-100*E4),IF(OR(AND(D4<0,E4>0),AND(D4>0,E4<0)),IF(D4<=E4,(100*D4+D4*E4)/(200*D4+D4*E4-10000),(100*E4-10000)/(200*E4+D4*E4-10000)),0)) -> 0.52380952 | H4: =IF(F4<0,G4+(1-G4)*(F4/100),IF(F4>0,G4-(1-G4)*(100/F4),0))*$O$2/2 -> 0 | I4: 200 | J4: =IF(F4<0,I4/(F4/-100),I4*F4/100) -> 181.81818 | K4: =G4*J4-(1-G4)*I4 -> 0 | L4: =IF(F4>0,(G4*F4/100-(1-G4)),IF(F4<0,(G4*100/-F4-(1-G4)),0)) -> 5.5511151e-17 | M4: Y | N4: =IF(ISERROR(SEARCH("(Bonus Bet)",B4)),IF(M4="Y",J4,IF(M4="N",-I4,0)),IF(M4="N",0,IF(M4="Y",J4,0))) -> 181.81818 | O4: =SUM(K:K) -> 22401.594 | P4: =AVERAGEIF(L:L,"<>0") -> 0.058637668 | S4: 45256 | T4: {=SUM(_xlfn._xlws.FILTER(N:N,A:A=S4,0))} -> 335.66434 | U4: =U3+T4 -> 572.84382 | V4: {=SUM(_xlfn._xlws.FILTER(I:I,A:A=S4,0))} -> 400 | W4: {=COUNT(_xlfn._xlws.FILTER(I:I,A:A=S4,""))} -> 2 | X4: {=SUM(_xlfn._xlws.FILTER(K:K,A:A=S4,0))} -> 0.28902152 | Y4: =Y3+X4 -> 0.57804304 | Z4: =Z3/Z2 -> 97.914438 | AA4: per Wager | AD4: 0.52380952 | AE4: 1 | AF4: =COUNTIFS($G$2:$G$4000,AD4,$M$2:$M$4000,"=Y")/AE4 -> 1 | AG4: =AD4-AF4 -> -0.47619048 | AK4: 0.097128243 | AL4: 1 | AM4: =COUNTIFS($G$2:$G$4000,AK4,$M$2:$M$4000,"=Y") -> 0 | AO4: =IF(D4<0,I4/(D4/-100),I4*D4/100) -> 181.81818 | AP4: =IF(ISERROR(SEARCH("(Bonus Bet)",B4)),IF(M4="Y",AO4,IF(M4="N",-I4,0)),IF(M4="N",0,IF(M4="Y",AO4,0))) -> 181.81818 | AQ4: =N4 -> 181.81818 | AR4: =AQ4-AP4+AR3 -> 1.1743981
A5: 45256 | B5: Zay Flowers Over 4.5 Total Receptions | C5: Fanduel | D5: -131 | E5: 130 | F5: -130 | G5: =IF(AND(D5<0,E5<0),(D5*E5-100*D5)/(2*D5*E5-100*D5-100*E5),IF(OR(AND(D5<0,E5>0),AND(D5>0,E5<0)),IF(D5<=E5,(100*D5+D5*E5)/(200*D5+D5*E5-10000),(100*E5-10000)/(200*E5+D5*E5-10000)),0)) -> 0.56603419 | H5: =IF(F5<0,G5+(1-G5)*(F5/100),IF(F5>0,G5-(1-G5)*(100/F5),0))*$O$2/2 -> 4.6965997 | I5: 200 | J5: =IF(F5<0,I5/(F5/-100),I5*F5/100) -> 153.84615 | K5: =G5*J5-(1-G5)*I5 -> 0.28902152 | L5: =IF(F5>0,(G5*F5/100-(1-G5)),IF(F5<0,(G5*100/-F5-(1-G5)),0)) -> 0.0014451076 | M5: Y | N5: =IF(ISERROR(SEARCH("(Bonus Bet)",B5)),IF(M5="Y",J5,IF(M5="N",-I5,0)),IF(M5="N",0,IF(M5="Y",J5,0))) -> 153.84615 | P5: TOTAL PROFIT/LOSS | S5: 45257 | T5: {=SUM(_xlfn._xlws.FILTER(N:N,A:A=S5,0))} -> 103.78317 | U5: =U4+T5 -> 676.627 | V5: {=SUM(_xlfn._xlws.FILTER(I:I,A:A=S5,0))} -> 600 | W5: {=COUNT(_xlfn._xlws.FILTER(I:I,A:A=S5,""))} -> 3 | X5: {=SUM(_xlfn._xlws.FILTER(K:K,A:A=S5,0))} -> 3.0405981 | Y5: =Y4+X5 -> 3.6186412 | AD5: 0.70588235 | AE5: 1 | AF5: =COUNTIFS($G$2:$G$4000,AD5,$M$2:$M$4000,"=Y")/AE5 -> 1 | AG5: =AD5-AF5 -> -0.29411765 | AK5: 0.054003766 | AL5: 1 | AM5: =COUNTIFS($G$2:$G$4000,AK5,$M$2:$M$4000,"=Y") -> 0 | AO5: =IF(D5<0,I5/(D5/-100),I5*D5/100) -> 152.67176 | AP5: =IF(ISERROR(SEARCH("(Bonus Bet)",B5)),IF(M5="Y",AO5,IF(M5="N",-I5,0)),IF(M5="N",0,IF(M5="Y",AO5,0))) -> 152.67176 | AQ5: =N5 -> 153.84615 | AR5: =AQ5-AP5+AR4 -> 2.3487962
A6: 45254 | B6: Eurospin Pinerolo Moneyline (v Bergamo) | C6: Unibet | D6: -240 | E6: 240 | F6: -240 | G6: =IF(AND(D6<0,E6<0),(D6*E6-100*D6)/(2*D6*E6-100*D6-100*E6),IF(OR(AND(D6<0,E6>0),AND(D6>0,E6<0)),IF(D6<=E6,(100*D6+D6*E6)/(200*D6+D6*E6-10000),(100*E6-10000)/(200*E6+D6*E6-10000)),0)) -> 0.70588235 | H6: =IF(F6<0,G6+(1-G6)*(F6/100),IF(F6>0,G6-(1-G6)*(100/F6),0))*$O$2/2 -> 5.5511151e-13 | I6: 200 | J6: =IF(F6<0,I6/(F6/-100),I6*F6/100) -> 83.333333 | K6: =G6*J6-(1-G6)*I6 -> 0 | L6: =IF(F6>0,(G6*F6/100-(1-G6)),IF(F6<0,(G6*100/-F6-(1-G6)),0)) -> 5.5511151e-17 | M6: Y | N6: =IF(ISERROR(SEARCH("(Bonus Bet)",B6)),IF(M6="Y",J6,IF(M6="N",-I6,0)),IF(M6="N",0,IF(M6="Y",J6,0))) -> 83.333333 | P6: =SUM(N:N) -> 16259.954 | S6: 45258 | T6: {=SUM(_xlfn._xlws.FILTER(N:N,A:A=S6,0))} -> 160.62378 | U6: =U5+T6 -> 837.25078 | V6: {=SUM(_xlfn._xlws.FILTER(I:I,A:A=S6,0))} -> 600 | W6: {=COUNT(_xlfn._xlws.FILTER(I:I,A:A=S6,""))} -> 4 | X6: {=SUM(_xlfn._xlws.FILTER(K:K,A:A=S6,0))} -> 53.472588 | Y6: =Y5+X6 -> 57.091229 | AD6: 0.56195695 | AE6: 1 | AF6: =COUNTIFS($G$2:$G$4000,AD6,$M$2:$M$4000,"=Y")/AE6 -> 0 | AG6: =AD6-AF6 -> 0.56195695 | AK6: 0.095510984 | AL6: 1 | AM6: =COUNTIFS($G$2:$G$4000,AK6,$M$2:$M$4000,"=Y") -> 0 | AO6: =IF(D6<0,I6/(D6/-100),I6*D6/100) -> 83.333333 | AP6: =IF(ISERROR(SEARCH("(Bonus Bet)",B6)),IF(M6="Y",AO6,IF(M6="N",-I6,0)),IF(M6="N",0,IF(M6="Y",AO6,0))) -> 83.333333 | AQ6: =N6 -> 83.333333 | AR6: =AQ6-AP6+AR5 -> 2.3487962
A7: 45262 | B7: Jamey-Lyn Horth Moneyline (v Hardy) | C7: NorthStar | D7: -143 | E7: 118 | F7: -107 | G7: =IF(AND(D7<0,E7<0),(D7*E7-100*D7)/(2*D7*E7-100*D7-100*E7),IF(OR(AND(D7<0,E7>0),AND(D7>0,E7<0)),IF(D7<=E7,(100*D7+D7*E7)/(200*D7+D7*E7-10000),(100*E7-10000)/(200*E7+D7*E7-10000)),0)) -> 0.56195695 | H7: =IF(F7<0,G7+(1-G7)*(F7/100),IF(F7>0,G7-(1-G7)*(100/F7),0))*$O$2/2 -> 233.12723 | I7: 150 | J7: =IF(F7<0,I7/(F7/-100),I7*F7/100) -> 140.18692 | K7: =G7*J7-(1-G7)*I7 -> 13.072555 | L7: =IF(F7>0,(G7*F7/100-(1-G7)),IF(F7<0,(G7*100/-F7-(1-G7)),0)) -> 0.087150367 | M7: N | N7: =IF(ISERROR(SEARCH("(Bonus Bet)",B7)),IF(M7="Y",J7,IF(M7="N",-I7,0)),IF(M7="N",0,IF(M7="Y",J7,0))) -> -150 | P7: PROFIT MARGIN | S7: 45259 | T7: {=SUM(_xlfn._xlws.FILTER(N:N,A:A=S7,0))} -> -173.80171 | U7: =U6+T7 -> 663.44907 | V7: {=SUM(_xlfn._xlws.FILTER(I:I,A:A=S7,0))} -> 1753.83 | W7: {=COUNT(_xlfn._xlws.FILTER(I:I,A:A=S7,""))} -> 8 | X7: {=SUM(_xlfn._xlws.FILTER(K:K,A:A=S7,0))} -> 66.161087 | Y7: =Y6+X7 -> 123.25232 | AD7: 0.56608812 | AE7: 1 | AF7: =COUNTIFS($G$2:$G$4000,AD7,$M$2:$M$4000,"=Y")/AE7 -> 1 | AG7: =AD7-AF7 -> -0.43391188 | AK7: 0.069005262 | AL7: 1 | AM7: =COUNTIFS($G$2:$G$4000,AK7,$M$2:$M$4000,"=Y") -> 0 | AO7: =IF(D7<0,I7/(D7/-100),I7*D7/100) -> 104.8951 | AP7: =IF(ISERROR(SEARCH("(Bonus Bet)",B7)),IF(M7="Y",AO7,IF(M7="N",-I7,0)),IF(M7="N",0,IF(M7="Y",AO7,0))) -> -150 | AQ7: =N7 -> -150 | AR7: =AQ7-AP7+AR6 -> 2.3487962
A8: 45262 | B8: Drakkar Klose Moneyline (v Solecki) | C8: DraftKings | D8: -160 | E8: 112 | F8: -130 | G8: =IF(AND(D8<0,E8<0),(D8*E8-100*D8)/(2*D8*E8-100*D8-100*E8),IF(OR(AND(D8<0,E8>0),AND(D8>0,E8<0)),IF(D8<=E8,(100*D8+D8*E8)/(200*D8+D8*E8-10000),(100*E8-10000)/(200*E8+D8*E8-10000)),0)) -> 0.56608812 | H8: =IF(F8<0,G8+(1-G8)*(F8/100),IF(F8>0,G8-(1-G8)*(100/F8),0))*$O$2/2 -> 5.0066756 | I8: 200 | J8: =IF(F8<0,I8/(F8/-100),I8*F8/100) -> 153.84615 | K8: =G8*J8-(1-G8)*I8 -> 0.30810311 | L8: =IF(F8>0,(G8*F8/100-(1-G8)),IF(F8<0,(G8*100/-F8-(1-G8)),0)) -> 0.0015405156 | M8: Y | N8: =IF(ISERROR(SEARCH("(Bonus Bet)",B8)),IF(M8="Y",J8,IF(M8="N",-I8,0)),IF(M8="N",0,IF(M8="Y",J8,0))) -> 153.84615 | P8: =P6/P2 -> 0.042580226 | S8: 45260 | T8: {=SUM(_xlfn._xlws.FILTER(N:N,A:A=S8,0))} -> 509.40873 | U8: =U7+T8 -> 1172.8578 | V8: {=SUM(_xlfn._xlws.FILTER(I:I,A:A=S8,0))} -> 1000 | W8: {=COUNT(_xlfn._xlws.FILTER(I:I,A:A=S8,""))} -> 5 | X8: {=SUM(_xlfn._xlws.FILTER(K:K,A:A=S8,0))} -> 67.413947 | Y8: =Y7+X8 -> 190.66626 | AD8: 0.58827199 | AE8: 1 | AF8: =COUNTIFS($G$2:$G$4000,AD8,$M$2:$M$4000,"=Y")/AE8 -> 0 | AG8: =AD8-AF8 -> 0.58827199 | AK8: 0.0751976 | AL8: 1 | AM8: =COUNTIFS($G$2:$G$4000,AK8,$M$2:$M$4000,"=Y") -> 0 | AO8: =IF(D8<0,I8/(D8/-100),I8*D8/100) -> 125 | AP8: =IF(ISERROR(SEARCH("(Bonus Bet)",B8)),IF(M8="Y",AO8,IF(M8="N",-I8,0)),IF(M8="N",0,IF(M8="Y",AO8,0))) -> 125 | AQ8: =N8 -> 153.84615 | AR8: =AQ8-AP8+AR7 -> 31.19495
A9: 45262 | B9: Rob Font Moneyline (v Figueiredo) | C9: DraftKings | D9: -164 | E9: 130 | F9: -135 | G9: =IF(AND(D9<0,E9<0),(D9*E9-100*D9)/(2*D9*E9-100*D9-100*E9),IF(OR(AND(D9<0,E9>0),AND(D9>0,E9<0)),IF(D9<=E9,(100*D9+D9*E9)/(200*D9+D9*E9-10000),(100*E9-10000)/(200*E9+D9*E9-10000)),0)) -> 0.58827199 | H9: =IF(F9<0,G9+(1-G9)*(F9/100),IF(F9>0,G9-(1-G9)*(100/F9),0))*$O$2/2 -> 81.097941 | I9: 200 | J9: =IF(F9<0,I9/(F9/-100),I9*F9/100) -> 148.14815 | K9: =G9*J9-(1-G9)*I9 -> 4.8058039 | L9: =IF(F9>0,(G9*F9/100-(1-G9)),IF(F9<0,(G9*100/-F9-(1-G9)),0)) -> 0.02402902 | M9: N | N9: =IF(ISERROR(SEARCH("(Bonus Bet)",B9)),IF(M9="Y",J9,IF(M9="N",-I9,0)),IF(M9="N",0,IF(M9="Y",J9,0))) -> -200 | S9: 45261 | T9: {=SUM(_xlfn._xlws.FILTER(N:N,A:A=S9,0))} -> 293.22651 | U9: =U8+T9 -> 1466.0843 | V9: {=SUM(_xlfn._xlws.FILTER(I:I,A:A=S9,0))} -> 608.33 | W9: {=COUNT(_xlfn._xlws.FILTER(I:I,A:A=S9,""))} -> 2 | X9: {=SUM(_xlfn._xlws.FILTER(K:K,A:A=S9,0))} -> 30.955526 | Y9: =Y8+X9 -> 221.62179 | AD9: 0.56560284 | AE9: 1 | AF9: =COUNTIFS($G$2:$G$4000,AD9,$M$2:$M$4000,"=Y")/AE9 -> 1 | AG9: =AD9-AF9 -> -0.43439716 | AK9: 0.094463783 | AL9: 1 | AM9: =COUNTIFS($G$2:$G$4000,AK9,$M$2:$M$4000,"=Y") -> 0 | AO9: =IF(D9<0,I9/(D9/-100),I9*D9/100) -> 121.95122 | AP9: =IF(ISERROR(SEARCH("(Bonus Bet)",B9)),IF(M9="Y",AO9,IF(M9="N",-I9,0)),IF(M9="N",0,IF(M9="Y",AO9,0))) -> -200 | AQ9: =N9 -> -200 | AR9: =AQ9-AP9+AR8 -> 31.19495
A10: 45262 | B10: Sean Brady Moneyline (v Gastelum) | C10: BetVictor | D10: -145 | E10: 120 | F10: -125 | G10: =IF(AND(D10<0,E10<0),(D10*E10-100*D10)/(2*D10*E10-100*D10-100*E10),IF(OR(AND(D10<0,E10>0),AND(D10>0,E10<0)),IF(D10<=E10,(100*D10+D10*E10)/(200*D10+D10*E10-10000),(100*E10-10000)/(200*E10+D10*E10-10000)),0)) -> 0.56560284 | H10: =IF(F10<0,G10+(1-G10)*(F10/100),IF(F10>0,G10-(1-G10)*(100/F10),0))*$O$2/2 -> 56.515957 | I10: 200 | J10: =IF(F10<0,I10/(F10/-100),I10*F10/100) -> 160 | K10: =G10*J10-(1-G10)*I10 -> 3.6170213 | L10: =IF(F10>0,(G10*F10/100-(1-G10)),IF(F10<0,(G10*100/-F10-(1-G10)),0)) -> 0.018085106 | M10: Y | N10: =IF(ISERROR(SEARCH("(Bonus Bet)",B10)),IF(M10="Y",J10,IF(M10="N",-I10,0)),IF(M10="N",0,IF(M10="Y",J10,0))) -> 160 | P10: AVERAGE WEEKLY INCOME | S10: 45262 | T10: {=SUM(_xlfn._xlws.FILTER(N:N,A:A=S10,0))} -> -225.29082 | U10: =U9+T10 -> 1240.7935 | V10: {=SUM(_xlfn._xlws.FILTER(I:I,A:A=S10,0))} -> 3024.29 | W10: {=COUNT(_xlfn._xlws.FILTER(I:I,A:A=S10,""))} -> 12 | X10: {=SUM(_xlfn._xlws.FILTER(K:K,A:A=S10,0))} -> 182.23998 | Y10: =Y9+X10 -> 403.86177 | AD10: 0.56331878 | AE10: 3 | AF10: =COUNTIFS($G$2:$G$4000,AD10,$M$2:$M$4000,"=Y")/AE10 -> 0 | AG10: =AD10-AF10 -> 0.56331878 | AK10: 0.072367829 | AL10: 1 | AM10: =COUNTIFS($G$2:$G$4000,AK10,$M$2:$M$4000,"=Y") -> 0 | AO10: =IF(D10<0,I10/(D10/-100),I10*D10/100) -> 137.93103 | AP10: =IF(ISERROR(SEARCH("(Bonus Bet)",B10)),IF(M10="Y",AO10,IF(M10="N",-I10,0)),IF(M10="N",0,IF(M10="Y",AO10,0))) -> 137.93103 | AQ10: =N10 -> 160 | AR10: =AQ10-AP10+AR9 -> 53.263916
A11: 45257 | B11: Senators/Panthers Over 6.5 Total Goals | C11: Betano | D11: -150 | E11: 115 | F11: -125 | G11: =IF(AND(D11<0,E11<0),(D11*E11-100*D11)/(2*D11*E11-100*D11-100*E11),IF(OR(AND(D11<0,E11>0),AND(D11>0,E11<0)),IF(D11<=E11,(100*D11+D11*E11)/(200*D11+D11*E11-10000),(100*E11-10000)/(200*E11+D11*E11-10000)),0)) -> 0.56331878 | H11: =IF(F11<0,G11+(1-G11)*(F11/100),IF(F11>0,G11-(1-G11)*(100/F11),0))*$O$2/2 -> 43.668122 | I11: 200 | J11: =IF(F11<0,I11/(F11/-100),I11*F11/100) -> 160 | K11: =G11*J11-(1-G11)*I11 -> 2.7947598 | L11: =IF(F11>0,(G11*F11/100-(1-G11)),IF(F11<0,(G11*100/-F11-(1-G11)),0)) -> 0.013973799 | M11: N | N11: =IF(ISERROR(SEARCH("(Bonus Bet)",B11)),IF(M11="Y",J11,IF(M11="N",-I11,0)),IF(M11="N",0,IF(M11="Y",J11,0))) -> -200 | P11: =AVERAGEIF(R:R,"<>0") -> 677.49807 | R11: WEEK 2 | S11: 45263 | T11: {=SUM(_xlfn._xlws.FILTER(N:N,A:A=S11,0))} -> 527.57079 | U11: =U10+T11 -> 1768.3643 | V11: {=SUM(_xlfn._xlws.FILTER(I:I,A:A=S11,0))} -> 600 | W11: {=COUNT(_xlfn._xlws.FILTER(I:I,A:A=S11,""))} -> 3 | X11: {=SUM(_xlfn._xlws.FILTER(K:K,A:A=S11,0))} -> 49.295677 | Y11: =Y10+X11 -> 453.15745 | AD11: 0.5355412 | AE11: 1 | AF11: =COUNTIFS($G$2:$G$4000,AD11,$M$2:$M$4000,"=Y")/AE11 -> 1 | AG11: =AD11-AF11 -> -0.4644588 | AK11: 0.064102564 | AL11: 1 | AM11: =COUNTIFS($G$2:$G$4000,AK11,$M$2:$M$4000,"=Y") -> 0 | AO11: =IF(D11<0,I11/(D11/-100),I11*D11/100) -> 133.33333 | AP11: =IF(ISERROR(SEARCH("(Bonus Bet)",B11)),IF(M11="Y",AO11,IF(M11="N",-I11,0)),IF(M11="N",0,IF(M11="Y",AO11,0))) -> -200 | AQ11: =N11 -> -200 | AR11: =AQ11-AP11+AR10 -> 53.263916
A12: 45257 | B12: Sharks/Capitals Under 6 Total Goals | C12: BetVictor | D12: -130 | E12: 104 | F12: -115 | G12: =IF(AND(D12<0,E12<0),(D12*E12-100*D12)/(2*D12*E12-100*D12-100*E12),IF(OR(AND(D12<0,E12>0),AND(D12>0,E12<0)),IF(D12<=E12,(100*D12+D12*E12)/(200*D12+D12*E12-10000),(100*E12-10000)/(200*E12+D12*E12-10000)),0)) -> 0.5355412 | H12: =IF(F12<0,G12+(1-G12)*(F12/100),IF(F12>0,G12-(1-G12)*(100/F12),0))*$O$2/2 -> 3.5339257 | I12: 200 | J12: =IF(F12<0,I12/(F12/-100),I12*F12/100) -> 173.91304 | K12: =G12*J12-(1-G12)*I12 -> 0.24583831 | L12: =IF(F12>0,(G12*F12/100-(1-G12)),IF(F12<0,(G12*100/-F12-(1-G12)),0)) -> 0.0012291915 | M12: Y | N12: =IF(ISERROR(SEARCH("(Bonus Bet)",B12)),IF(M12="Y",J12,IF(M12="N",-I12,0)),IF(M12="N",0,IF(M12="Y",J12,0))) -> 173.91304 | R12: =SUM(T11:T17) -> 563.6635 | S12: 45264 | T12: {=SUM(_xlfn._xlws.FILTER(N:N,A:A=S12,0))} -> -600 | U12: =U11+T12 -> 1168.3643 | V12: {=SUM(_xlfn._xlws.FILTER(I:I,A:A=S12,0))} -> 600 | W12: {=COUNT(_xlfn._xlws.FILTER(I:I,A:A=S12,""))} -> 3 | X12: {=SUM(_xlfn._xlws.FILTER(K:K,A:A=S12,0))} -> 50.118532 | Y12: =Y11+X12 -> 503.27598 | AD12: 0.86741242 | AE12: 1 | AF12: =COUNTIFS($G$2:$G$4000,AD12,$M$2:$M$4000,"=Y")/AE12 -> 0 | AG12: =AD12-AF12 -> 0.86741242 | AK12: 0.074682599 | AL12: 1 | AM12: =COUNTIFS($G$2:$G$4000,AK12,$M$2:$M$4000,"=Y") -> 0 | AO12: =IF(D12<0,I12/(D12/-100),I12*D12/100) -> 153.84615 | AP12: =IF(ISERROR(SEARCH("(Bonus Bet)",B12)),IF(M12="Y",AO12,IF(M12="N",-I12,0)),IF(M12="N",0,IF(M12="Y",AO12,0))) -> 153.84615 | AQ12: =N12 -> 173.91304 | AR12: =AQ12-AP12+AR11 -> 73.330805
A13: 45258 | B13: Crvena Zvezda Moneyline (v Brno) | C13: DraftKings | D13: -1429 | E13: 600 | F13: -700 | G13: =IF(AND(D13<0,E13<0),(D13*E13-100*D13)/(2*D13*E13-100*D13-100*E13),IF(OR(AND(D13<0,E13>0),AND(D13>0,E13<0)),IF(D13<=E13,(100*D13+D13*E13)/(200*D13+D13*E13-10000),(100*E13-10000)/(200*E13+D13*E13-10000)),0)) -> 0.86741242 | H13: =IF(F13<0,G13+(1-G13)*(F13/100),IF(F13>0,G13-(1-G13)*(100/F13),0))*$O$2/2 -> -151.75165 | I13: 0 | J13: =IF(F13<0,I13/(F13/-100),I13*F13/100) -> 0 | K13: =G13*J13-(1-G13)*I13 -> 0 | L13: =IF(F13>0,(G13*F13/100-(1-G13)),IF(F13<0,(G13*100/-F13-(1-G13)),0)) -> -0.0086715227 | M13: VOID | N13: =IF(ISERROR(SEARCH("(Bonus Bet)",B13)),IF(M13="Y",J13,IF(M13="N",-I13,0)),IF(M13="N",0,IF(M13="Y",J13,0))) -> 0 | P13: 1-UNIT EQUIV PROFIT | S13: 45265 | T13: {=SUM(_xlfn._xlws.FILTER(N:N,A:A=S13,0))} -> 195.26751 | U13: =U12+T13 -> 1363.6318 | V13: {=SUM(_xlfn._xlws.FILTER(I:I,A:A=S13,0))} -> 803.2 | W13: {=COUNT(_xlfn._xlws.FILTER(I:I,A:A=S13,""))} -> 4 | X13: {=SUM(_xlfn._xlws.FILTER(K:K,A:A=S13,0))} -> 59.498714 | Y13: =Y12+X13 -> 562.77469 | AD13: 0.5505618 | AE13: 4 | AF13: =COUNTIFS($G$2:$G$4000,AD13,$M$2:$M$4000,"=Y")/AE13 -> 0.5 | AG13: =AD13-AF13 -> 0.050561798 | AK13: 0.08193525 | AL13: 2 | AM13: =COUNTIFS($G$2:$G$4000,AK13,$M$2:$M$4000,"=Y") -> 0 | AO13: =IF(D13<0,I13/(D13/-100),I13*D13/100) -> 0 | AP13: =IF(ISERROR(SEARCH("(Bonus Bet)",B13)),IF(M13="Y",AO13,IF(M13="N",-I13,0)),IF(M13="N",0,IF(M13="Y",AO13,0))) -> 0 | AQ13: =N13 -> 0 | AR13: =AQ13-AP13+AR12 -> 73.330805
A14: 45258 | B14: Domantas Sabonis Over 19.5 Points | C14: Fanduel | D14: -140 | E14: 110 | F14: -104 | G14: =IF(AND(D14<0,E14<0),(D14*E14-100*D14)/(2*D14*E14-100*D14-100*E14),IF(OR(AND(D14<0,E14>0),AND(D14>0,E14<0)),IF(D14<=E14,(100*D14+D14*E14)/(200*D14+D14*E14-10000),(100*E14-10000)/(200*E14+D14*E14-10000)),0)) -> 0.5505618 | H14: =IF(F14<0,G14+(1-G14)*(F14/100),IF(F14>0,G14-(1-G14)*(100/F14),0))*$O$2/2 -> 207.86517 | I14: 200 | J14: =IF(F14<0,I14/(F14/-100),I14*F14/100) -> 192.30769 | K14: =G14*J14-(1-G14)*I14 -> 15.989628 | L14: =IF(F14>0,(G14*F14/100-(1-G14)),IF(F14<0,(G14*100/-F14-(1-G14)),0)) -> 0.079948142 | M14: N | N14: =IF(ISERROR(SEARCH("(Bonus Bet)",B14)),IF(M14="Y",J14,IF(M14="N",-I14,0)),IF(M14="N",0,IF(M14="Y",J14,0))) -> -200 | P14: {=SUM(IF(_xlfn._xlws.FILTER(F:F,M:M="Y",0)<0,200/(_xlfn._xlws.FILTER(F:F,M:M="Y",0)/-100),200*_xlfn._xlws.FILTER(F:F,M:M="Y",0)/100))-COUNTIF(M:M,"N")*200} -> 21081.119 | S14: 45266 | T14: {=SUM(_xlfn._xlws.FILTER(N:N,A:A=S14,0))} -> 95.528509 | U14: =U13+T14 -> 1459.1603 | V14: {=SUM(_xlfn._xlws.FILTER(I:I,A:A=S14,0))} -> 888.57 | W14: {=COUNT(_xlfn._xlws.FILTER(I:I,A:A=S14,""))} -> 9 | X14: {=SUM(_xlfn._xlws.FILTER(K:K,A:A=S14,0))} -> 72.498044 | Y14: =Y13+X14 -> 635.27274 | AD14: 0.5751634 | AE14: 14 | AF14: =COUNTIFS($G$2:$G$4000,AD14,$M$2:$M$4000,"=Y")/AE14 -> 0.71428571 | AG14: =AD14-AF14 -> -0.13912232 | AK14: 0.077346331 | AL14: 1 | AM14: =COUNTIFS($G$2:$G$4000,AK14,$M$2:$M$4000,"=Y") -> 0 | AO14: =IF(D14<0,I14/(D14/-100),I14*D14/100) -> 142.85714 | AP14: =IF(ISERROR(SEARCH("(Bonus Bet)",B14)),IF(M14="Y",AO14,IF(M14="N",-I14,0)),IF(M14="N",0,IF(M14="Y",AO14,0))) -> -200 | AQ14: =N14 -> -200 | AR14: =AQ14-AP14+AR13 -> 73.330805
A15: 45258 | B15: Brook Lopez Over 6.5 Rebounds + Assists | C15: Betano | D15: -160 | E15: 120 | F15: -108 | G15: =IF(AND(D15<0,E15<0),(D15*E15-100*D15)/(2*D15*E15-100*D15-100*E15),IF(OR(AND(D15<0,E15>0),AND(D15>0,E15<0)),IF(D15<=E15,(100*D15+D15*E15)/(200*D15+D15*E15-10000),(100*E15-10000)/(200*E15+D15*E15-10000)),0)) -> 0.5751634 | H15: =IF(F15<0,G15+(1-G15)*(F15/100),IF(F15>0,G15-(1-G15)*(100/F15),0))*$O$2/2 -> 290.84967 | I15: 200 | J15: =IF(F15<0,I15/(F15/-100),I15*F15/100) -> 185.18519 | K15: =G15*J15-(1-G15)*I15 -> 21.54442 | L15: =IF(F15>0,(G15*F15/100-(1-G15)),IF(F15<0,(G15*100/-F15-(1-G15)),0)) -> 0.1077221 | M15: Y | N15: =IF(ISERROR(SEARCH("(Bonus Bet)",B15)),IF(M15="Y",J15,IF(M15="N",-I15,0)),IF(M15="N",0,IF(M15="Y",J15,0))) -> 185.18519 | P15: KELLY-EQUIV PROFIT | S15: 45267 | T15: {=SUM(_xlfn._xlws.FILTER(N:N,A:A=S15,0))} -> -80.523636 | U15: =U14+T15 -> 1378.6367 | V15: {=SUM(_xlfn._xlws.FILTER(I:I,A:A=S15,0))} -> 176.12 | W15: {=COUNT(_xlfn._xlws.FILTER(I:I,A:A=S15,""))} -> 2 | X15: {=SUM(_xlfn._xlws.FILTER(K:K,A:A=S15,0))} -> 17.033102 | Y15: =Y14+X15 -> 652.30584 | AD15: 0.77208605 | AE15: 1 | AF15: =COUNTIFS($G$2:$G$4000,AD15,$M$2:$M$4000,"=Y")/AE15 -> 1 | AG15: =AD15-AF15 -> -0.22791395 | AK15: 0.096000255 | AL15: 1 | AM15: =COUNTIFS($G$2:$G$4000,AK15,$M$2:$M$4000,"=Y") -> 0 | AO15: =IF(D15<0,I15/(D15/-100),I15*D15/100) -> 125 | AP15: =IF(ISERROR(SEARCH("(Bonus Bet)",B15)),IF(M15="Y",AO15,IF(M15="N",-I15,0)),IF(M15="N",0,IF(M15="Y",AO15,0))) -> 125 | AQ15: =N15 -> 185.18519 | AR15: =AQ15-AP15+AR14 -> 133.51599
A16: 45258 | B16: Quinn Hughes Under 0.5 PowerPlay Points | C16: Unibet | D16: -160 | E16: 120 | F16: -114 | G16: =IF(AND(D16<0,E16<0),(D16*E16-100*D16)/(2*D16*E16-100*D16-100*E16),IF(OR(AND(D16<0,E16>0),AND(D16>0,E16<0)),IF(D16<=E16,(100*D16+D16*E16)/(200*D16+D16*E16-10000),(100*E16-10000)/(200*E16+D16*E16-10000)),0)) -> 0.5751634 | H16: =IF(F16<0,G16+(1-G16)*(F16/100),IF(F16>0,G16-(1-G16)*(100/F16),0))*$O$2/2 -> 227.12418 | I16: 200 | J16: =IF(F16<0,I16/(F16/-100),I16*F16/100) -> 175.4386 | K16: =G16*J16-(1-G16)*I16 -> 15.938539 | L16: =IF(F16>0,(G16*F16/100-(1-G16)),IF(F16<0,(G16*100/-F16-(1-G16)),0)) -> 0.079692696 | M16: Y | N16: =IF(ISERROR(SEARCH("(Bonus Bet)",B16)),IF(M16="Y",J16,IF(M16="N",-I16,0)),IF(M16="N",0,IF(M16="Y",J16,0))) -> 175.4386 | P16: {=SUM(IF(_xlfn._xlws.FILTER(F:F,M:M="Y",0)<0,(_xlfn._xlws.FILTER(H:H,M:M="Y",0))/(_xlfn._xlws.FILTER(F:F,M:M="Y",0)/-100),(_xlfn._xlws.FILTER(H:H,M:M="Y",0))*_xlfn._xlws.FILTER(F:F,M:M="Y",0)/100))-SUM((_xlfn._xlws.FILTER(H:H,M:M="N",0)))} -> 18316.562 | S16: 45268 | T16: {=SUM(_xlfn._xlws.FILTER(N:N,A:A=S16,0))} -> -10.57354 | U16: =U15+T16 -> 1368.0631 | V16: {=SUM(_xlfn._xlws.FILTER(I:I,A:A=S16,0))} -> 591.83 | W16: {=COUNT(_xlfn._xlws.FILTER(I:I,A:A=S16,""))} -> 8 | X16: {=SUM(_xlfn._xlws.FILTER(K:K,A:A=S16,0))} -> 51.011484 | Y16: =Y15+X16 -> 703.31732 | AD16: 0.59748787 | AE16: 1 | AF16: =COUNTIFS($G$2:$G$4000,AD16,$M$2:$M$4000,"=Y")/AE16 -> 0 | AG16: =AD16-AF16 -> 0.59748787 | AK16: 0.099178237 | AL16: 1 | AM16: =COUNTIFS($G$2:$G$4000,AK16,$M$2:$M$4000,"=Y") -> 0 | AO16: =IF(D16<0,I16/(D16/-100),I16*D16/100) -> 125 | AP16: =IF(ISERROR(SEARCH("(Bonus Bet)",B16)),IF(M16="Y",AO16,IF(M16="N",-I16,0)),IF(M16="N",0,IF(M16="Y",AO16,0))) -> 125 | AQ16: =N16 -> 175.4386 | AR16: =AQ16-AP16+AR15 -> 183.95459
A17: 45259 | B17: New Mexico Moneyline (v Louisiana State) | C17: Fanduel | D17: -417 | E17: 320 | F17: -330 | G17: =IF(AND(D17<0,E17<0),(D17*E17-100*D17)/(2*D17*E17-100*D17-100*E17),IF(OR(AND(D17<0,E17>0),AND(D17>0,E17<0)),IF(D17<=E17,(100*D17+D17*E17)/(200*D17+D17*E17-10000),(100*E17-10000)/(200*E17+D17*E17-10000)),0)) -> 0.77208605 | H17: =IF(F17<0,G17+(1-G17)*(F17/100),IF(F17>0,G17-(1-G17)*(100/F17),0))*$O$2/2 -> 49.925057 | I17: 200 | J17: =IF(F17<0,I17/(F17/-100),I17*F17/100) -> 60.606061 | K17: =G17*J17-(1-G17)*I17 -> 1.2103044 | L17: =IF(F17>0,(G17*F17/100-(1-G17)),IF(F17<0,(G17*100/-F17-(1-G17)),0)) -> 0.0060515221 | M17: Y | N17: =IF(ISERROR(SEARCH("(Bonus Bet)",B17)),IF(M17="Y",J17,IF(M17="N",-I17,0)),IF(M17="N",0,IF(M17="Y",J17,0))) -> 60.606061 | S17: 45269 | T17: {=SUM(_xlfn._xlws.FILTER(N:N,A:A=S17,0))} -> 436.39387 | U17: =U16+T17 -> 1804.457 | V17: {=SUM(_xlfn._xlws.FILTER(I:I,A:A=S17,0))} -> 1622.24 | W17: {=COUNT(_xlfn._xlws.FILTER(I:I,A:A=S17,""))} -> 5 | X17: {=SUM(_xlfn._xlws.FILTER(K:K,A:A=S17,0))} -> 51.39204 | Y17: =Y16+X17 -> 754.70936 | AD17: 0.70909091 | AE17: 2 | AF17: =COUNTIFS($G$2:$G$4000,AD17,$M$2:$M$4000,"=Y")/AE17 -> 1 | AG17: =AD17-AF17 -> -0.29090909 | AK17: 0.089683578 | AL17: 3 | AM17: =COUNTIFS($G$2:$G$4000,AK17,$M$2:$M$4000,"=Y") -> 3 | AO17: =IF(D17<0,I17/(D17/-100),I17*D17/100) -> 47.961631 | AP17: =IF(ISERROR(SEARCH("(Bonus Bet)",B17)),IF(M17="Y",AO17,IF(M17="N",-I17,0)),IF(M17="N",0,IF(M17="Y",AO17,0))) -> 47.961631 | AQ17: =N17 -> 60.606061 | AR17: =AQ17-AP17+AR16 -> 196.59902
A18: 45259 | B18: Fred Vanvleet Under 4.5 Rebounds | C18: Bet365 | D18: -182 | E18: 130 | F18: -140 | G18: =IF(AND(D18<0,E18<0),(D18*E18-100*D18)/(2*D18*E18-100*D18-100*E18),IF(OR(AND(D18<0,E18>0),AND(D18>0,E18<0)),IF(D18<=E18,(100*D18+D18*E18)/(200*D18+D18*E18-10000),(100*E18-10000)/(200*E18+D18*E18-10000)),0)) -> 0.59748787 | H18: =IF(F18<0,G18+(1-G18)*(F18/100),IF(F18>0,G18-(1-G18)*(100/F18),0))*$O$2/2 -> 84.927205 | I18: 200 | J18: =IF(F18<0,I18/(F18/-100),I18*F18/100) -> 142.85714 | K18: =G18*J18-(1-G18)*I18 -> 4.8529832 | L18: =IF(F18>0,(G18*F18/100-(1-G18)),IF(F18<0,(G18*100/-F18-(1-G18)),0)) -> 0.024264916 | M18: VOID | N18: =IF(ISERROR(SEARCH("(Bonus Bet)",B18)),IF(M18="Y",J18,IF(M18="N",-I18,0)),IF(M18="N",0,IF(M18="Y",J18,0))) -> 0 | R18: WEEK 3 | S18: 45270 | T18: {=SUM(_xlfn._xlws.FILTER(N:N,A:A=S18,0))} -> 112.71873 | U18: =U17+T18 -> 1917.1757 | V18: {=SUM(_xlfn._xlws.FILTER(I:I,A:A=S18,0))} -> 1385.39 | W18: {=COUNT(_xlfn._xlws.FILTER(I:I,A:A=S18,""))} -> 11 | X18: {=SUM(_xlfn._xlws.FILTER(K:K,A:A=S18,0))} -> 91.145639 | Y18: =Y17+X18 -> 845.855 | AD18: 0.65517241 | AE18: 3 | AF18: =COUNTIFS($G$2:$G$4000,AD18,$M$2:$M$4000,"=Y")/AE18 -> 1 | AG18: =AD18-AF18 -> -0.34482759 | AK18: 0.083619941 | AL18: 1 | AM18: =COUNTIFS($G$2:$G$4000,AK18,$M$2:$M$4000,"=Y") -> 0 | AO18: =IF(D18<0,I18/(D18/-100),I18*D18/100) -> 109.89011 | AP18: =IF(ISERROR(SEARCH("(Bonus Bet)",B18)),IF(M18="Y",AO18,IF(M18="N",-I18,0)),IF(M18="N",0,IF(M18="Y",AO18,0))) -> 0 | AQ18: =N18 -> 0 | AR18: =AQ18-AP18+AR17 -> 196.59902
A19: 45261 | B19: GTS Katowice Moneyline (v Częstochowa) | C19: Unibet | D19: -300 | E19: 225 | F19: -200 | G19: =IF(AND(D19<0,E19<0),(D19*E19-100*D19)/(2*D19*E19-100*D19-100*E19),IF(OR(AND(D19<0,E19>0),AND(D19>0,E19<0)),IF(D19<=E19,(100*D19+D19*E19)/(200*D19+D19*E19-10000),(100*E19-10000)/(200*E19+D19*E19-10000)),0)) -> 0.70909091 | H19: =IF(F19<0,G19+(1-G19)*(F19/100),IF(F19>0,G19-(1-G19)*(100/F19),0))*$O$2/2 -> 318.18182 | I19: 294.76 | J19: =IF(F19<0,I19/(F19/-100),I19*F19/100) -> 147.38 | K19: =G19*J19-(1-G19)*I19 -> 18.757455 | L19: =IF(F19>0,(G19*F19/100-(1-G19)),IF(F19<0,(G19*100/-F19-(1-G19)),0)) -> 0.063636364 | M19: Y | N19: =IF(ISERROR(SEARCH("(Bonus Bet)",B19)),IF(M19="Y",J19,IF(M19="N",-I19,0)),IF(M19="N",0,IF(M19="Y",J19,0))) -> 147.38 | P19: Hits | R19: =SUM(T18:T24) -> -967.82778 | S19: 45271 | T19: {=SUM(_xlfn._xlws.FILTER(N:N,A:A=S19,0))} -> -311.46942 | U19: =U18+T19 -> 1605.7063 | V19: {=SUM(_xlfn._xlws.FILTER(I:I,A:A=S19,0))} -> 2730.94 | W19: {=COUNT(_xlfn._xlws.FILTER(I:I,A:A=S19,""))} -> 17 | X19: {=SUM(_xlfn._xlws.FILTER(K:K,A:A=S19,0))} -> 158.92396 | Y19: =Y18+X19 -> 1004.779 | AD19: 0.75425331 | AE19: 1 | AF19: =COUNTIFS($G$2:$G$4000,AD19,$M$2:$M$4000,"=Y")/AE19 -> 1 | AG19: =AD19-AF19 -> -0.24574669 | AK19: 0.068191192 | AL19: 2 | AM19: =COUNTIFS($G$2:$G$4000,AK19,$M$2:$M$4000,"=Y") -> 0 | AO19: =IF(D19<0,I19/(D19/-100),I19*D19/100) -> 98.253333 | AP19: =IF(ISERROR(SEARCH("(Bonus Bet)",B19)),IF(M19="Y",AO19,IF(M19="N",-I19,0)),IF(M19="N",0,IF(M19="Y",AO19,0))) -> 98.253333 | AQ19: =N19 -> 147.38 | AR19: =AQ19-AP19+AR18 -> 245.72568
A20: 45261 | B20: GTS Katowice Moneyline (v Częstochowa) | C20: Unibet | D20: -300 | E20: 225 | F20: -215 | G20: =IF(AND(D20<0,E20<0),(D20*E20-100*D20)/(2*D20*E20-100*D20-100*E20),IF(OR(AND(D20<0,E20>0),AND(D20>0,E20<0)),IF(D20<=E20,(100*D20+D20*E20)/(200*D20+D20*E20-10000),(100*E20-10000)/(200*E20+D20*E20-10000)),0)) -> 0.70909091 | H20: =IF(F20<0,G20+(1-G20)*(F20/100),IF(F20>0,G20-(1-G20)*(100/F20),0))*$O$2/2 -> 209.09091 | I20: 313.57 | J20: =IF(F20<0,I20/(F20/-100),I20*F20/100) -> 145.84651 | K20: =G20*J20-(1-G20)*I20 -> 12.198072 | L20: =IF(F20>0,(G20*F20/100-(1-G20)),IF(F20<0,(G20*100/-F20-(1-G20)),0)) -> 0.038900634 | M20: Y | N20: =IF(ISERROR(SEARCH("(Bonus Bet)",B20)),IF(M20="Y",J20,IF(M20="N",-I20,0)),IF(M20="N",0,IF(M20="Y",J20,0))) -> 145.84651 | P20: =COUNTIF(M2:M4000,"Y") -> 1870 | S20: 45272 | T20: {=SUM(_xlfn._xlws.FILTER(N:N,A:A=S20,0))} -> -422.29025 | U20: =U19+T20 -> 1183.4161 | V20: {=SUM(_xlfn._xlws.FILTER(I:I,A:A=S20,0))} -> 2080.52 | W20: {=COUNT(_xlfn._xlws.FILTER(I:I,A:A=S20,""))} -> 15 | X20: {=SUM(_xlfn._xlws.FILTER(K:K,A:A=S20,0))} -> 149.63075 | Y20: =Y19+X20 -> 1154.4097 | AD20: 0.74406902 | AE20: 1 | AF20: =COUNTIFS($G$2:$G$4000,AD20,$M$2:$M$4000,"=Y")/AE20 -> 0 | AG20: =AD20-AF20 -> 0.74406902 | AK20: 0.064432502 | AL20: 1 | AM20: =COUNTIFS($G$2:$G$4000,AK20,$M$2:$M$4000,"=Y") -> 0 | AO20: =IF(D20<0,I20/(D20/-100),I20*D20/100) -> 104.52333 | AP20: =IF(ISERROR(SEARCH("(Bonus Bet)",B20)),IF(M20="Y",AO20,IF(M20="N",-I20,0)),IF(M20="N",0,IF(M20="Y",AO20,0))) -> 104.52333 | AQ20: =N20 -> 145.84651 | AR20: =AQ20-AP20+AR19 -> 287.04886
A21: 45259 | B21: Alex Ovechkin Under 0.5 PowerPlay Points | C21: Bet365 | D21: -200 | E21: 185 | F21: -175 | G21: =IF(AND(D21<0,E21<0),(D21*E21-100*D21)/(2*D21*E21-100*D21-100*E21),IF(OR(AND(D21<0,E21>0),AND(D21>0,E21<0)),IF(D21<=E21,(100*D21+D21*E21)/(200*D21+D21*E21-10000),(100*E21-10000)/(200*E21+D21*E21-10000)),0)) -> 0.65517241 | H21: =IF(F21<0,G21+(1-G21)*(F21/100),IF(F21>0,G21-(1-G21)*(100/F21),0))*$O$2/2 -> 129.31034 | I21: 200 | J21: =IF(F21<0,I21/(F21/-100),I21*F21/100) -> 114.28571 | K21: =G21*J21-(1-G21)*I21 -> 5.91133 | L21: =IF(F21>0,(G21*F21/100-(1-G21)),IF(F21<0,(G21*100/-F21-(1-G21)),0)) -> 0.02955665 | M21: Y | N21: =IF(ISERROR(SEARCH("(Bonus Bet)",B21)),IF(M21="Y",J21,IF(M21="N",-I21,0)),IF(M21="N",0,IF(M21="Y",J21,0))) -> 114.28571 | P21: Misses | S21: 45273 | T21: {=SUM(_xlfn._xlws.FILTER(N:N,A:A=S21,0))} -> -25 | U21: =U20+T21 -> 1158.4161 | V21: {=SUM(_xlfn._xlws.FILTER(I:I,A:A=S21,0))} -> 25 | W21: {=COUNT(_xlfn._xlws.FILTER(I:I,A:A=S21,""))} -> 1 | X21: {=SUM(_xlfn._xlws.FILTER(K:K,A:A=S21,0))} -> 4.0454545 | Y21: =Y20+X21 -> 1158.4552 | AD21: 0.60682876 | AE21: 1 | AF21: =COUNTIFS($G$2:$G$4000,AD21,$M$2:$M$4000,"=Y")/AE21 -> 1 | AG21: =AD21-AF21 -> -0.39317124 | AK21: 0.070748794 | AL21: 1 | AM21: =COUNTIFS($G$2:$G$4000,AK21,$M$2:$M$4000,"=Y") -> 0 | AO21: =IF(D21<0,I21/(D21/-100),I21*D21/100) -> 100 | AP21: =IF(ISERROR(SEARCH("(Bonus Bet)",B21)),IF(M21="Y",AO21,IF(M21="N",-I21,0)),IF(M21="N",0,IF(M21="Y",AO21,0))) -> 100 | AQ21: =N21 -> 114.28571 | AR21: =AQ21-AP21+AR20 -> 301.33458
A22: 45259 | B22: Notre Dame (W) Moneyline (v Tennessee (W)) | C22: Unibet | D22: -420 | E22: 280 | F22: -286 | G22: =IF(AND(D22<0,E22<0),(D22*E22-100*D22)/(2*D22*E22-100*D22-100*E22),IF(OR(AND(D22<0,E22>0),AND(D22>0,E22<0)),IF(D22<=E22,(100*D22+D22*E22)/(200*D22+D22*E22-10000),(100*E22-10000)/(200*E22+D22*E22-10000)),0)) -> 0.75425331 | H22: =IF(F22<0,G22+(1-G22)*(F22/100),IF(F22>0,G22-(1-G22)*(100/F22),0))*$O$2/2 -> 128.54442 | I22: 153.12 | J22: =IF(F22<0,I22/(F22/-100),I22*F22/100) -> 53.538462 | K22: =G22*J22-(1-G22)*I22 -> 2.7528283 | L22: =IF(F22>0,(G22*F22/100-(1-G22)),IF(F22<0,(G22*100/-F22-(1-G22)),0)) -> 0.017978241 | M22: Y | N22: =IF(ISERROR(SEARCH("(Bonus Bet)",B22)),IF(M22="Y",J22,IF(M22="N",-I22,0)),IF(M22="N",0,IF(M22="Y",J22,0))) -> 53.538462 | P22: =COUNTIF(M2:M4000,"N") -> 1967 | S22: 45274 | T22: {=SUM(_xlfn._xlws.FILTER(N:N,A:A=S22,0))} -> -315.99 | U22: =U21+T22 -> 842.42606 | V22: {=SUM(_xlfn._xlws.FILTER(I:I,A:A=S22,0))} -> 315.99 | W22: {=COUNT(_xlfn._xlws.FILTER(I:I,A:A=S22,""))} -> 2 | X22: {=SUM(_xlfn._xlws.FILTER(K:K,A:A=S22,0))} -> 55.535925 | Y22: =Y21+X22 -> 1213.9911 | AD22: 0.57858048 | AE22: 1 | AF22: =COUNTIFS($G$2:$G$4000,AD22,$M$2:$M$4000,"=Y")/AE22 -> 1 | AG22: =AD22-AF22 -> -0.42141952 | AK22: 0.077154692 | AL22: 1 | AM22: =COUNTIFS($G$2:$G$4000,AK22,$M$2:$M$4000,"=Y") -> 0 | AO22: =IF(D22<0,I22/(D22/-100),I22*D22/100) -> 36.457143 | AP22: =IF(ISERROR(SEARCH("(Bonus Bet)",B22)),IF(M22="Y",AO22,IF(M22="N",-I22,0)),IF(M22="N",0,IF(M22="Y",AO22,0))) -> 36.457143 | AQ22: =N22 -> 53.538462 | AR22: =AQ22-AP22+AR21 -> 318.41589
A23: 45259 | B23: Alex Ovechkin Under 0.5 PowerPlay Points | C23: Bet888 | D23: -200 | E23: 185 | F23: -188 | G23: =IF(AND(D23<0,E23<0),(D23*E23-100*D23)/(2*D23*E23-100*D23-100*E23),IF(OR(AND(D23<0,E23>0),AND(D23>0,E23<0)),IF(D23<=E23,(100*D23+D23*E23)/(200*D23+D23*E23-10000),(100*E23-10000)/(200*E23+D23*E23-10000)),0)) -> 0.65517241 | H23: =IF(F23<0,G23+(1-G23)*(F23/100),IF(F23>0,G23-(1-G23)*(100/F23),0))*$O$2/2 -> 17.241379 | I23: 142.5 | J23: =IF(F23<0,I23/(F23/-100),I23*F23/100) -> 75.797872 | K23: =G23*J23-(1-G23)*I23 -> 0.52274395 | L23: =IF(F23>0,(G23*F23/100-(1-G23)),IF(F23<0,(G23*100/-F23-(1-G23)),0)) -> 0.0036683786 | M23: Y | N23: =IF(ISERROR(SEARCH("(Bonus Bet)",B23)),IF(M23="Y",J23,IF(M23="N",-I23,0)),IF(M23="N",0,IF(M23="Y",J23,0))) -> 75.797872 | P23: Days | S23: 45275 | T23: {=SUM(_xlfn._xlws.FILTER(N:N,A:A=S23,0))} -> 0 | U23: =U22+T23 -> 842.42606 | V23: {=SUM(_xlfn._xlws.FILTER(I:I,A:A=S23,0))} -> 0 | W23: {=COUNT(_xlfn._xlws.FILTER(I:I,A:A=S23,""))} -> 0 | X23: {=SUM(_xlfn._xlws.FILTER(K:K,A:A=S23,0))} -> 0 | Y23: =Y22+X23 -> 1213.9911 | AD23: 0.53051643 | AE23: 1 | AF23: =COUNTIFS($G$2:$G$4000,AD23,$M$2:$M$4000,"=Y")/AE23 -> 1 | AG23: =AD23-AF23 -> -0.46948357 | AK23: 0.092931688 | AL23: 1 | AM23: =COUNTIFS($G$2:$G$4000,AK23,$M$2:$M$4000,"=Y") -> 0 | AO23: =IF(D23<0,I23/(D23/-100),I23*D23/100) -> 71.25 | AP23: =IF(ISERROR(SEARCH("(Bonus Bet)",B23)),IF(M23="Y",AO23,IF(M23="N",-I23,0)),IF(M23="N",0,IF(M23="Y",AO23,0))) -> 71.25 | AQ23: =N23 -> 75.797872 | AR23: =AQ23-AP23+AR22 -> 322.96377
A24: 45259 | B24: Mississippi State Moneyline (v Miami) | C24: BetVictor | D24: -345 | E24: 275 | F24: -250 | G24: =IF(AND(D24<0,E24<0),(D24*E24-100*D24)/(2*D24*E24-100*D24-100*E24),IF(OR(AND(D24<0,E24>0),AND(D24>0,E24<0)),IF(D24<=E24,(100*D24+D24*E24)/(200*D24+D24*E24-10000),(100*E24-10000)/(200*E24+D24*E24-10000)),0)) -> 0.74406902 | H24: =IF(F24<0,G24+(1-G24)*(F24/100),IF(F24>0,G24-(1-G24)*(100/F24),0))*$O$2/2 -> 260.60388 | I24: 458.21 | J24: =IF(F24<0,I24/(F24/-100),I24*F24/100) -> 183.284 | K24: =G24*J24-(1-G24)*I24 -> 19.105809 | L24: =IF(F24>0,(G24*F24/100-(1-G24)),IF(F24<0,(G24*100/-F24-(1-G24)),0)) -> 0.041696621 | M24: N | N24: =IF(ISERROR(SEARCH("(Bonus Bet)",B24)),IF(M24="Y",J24,IF(M24="N",-I24,0)),IF(M24="N",0,IF(M24="Y",J24,0))) -> -458.21 | P24: =TODAY()-S2 -> 788 | S24: 45276 | T24: {=SUM(_xlfn._xlws.FILTER(N:N,A:A=S24,0))} -> -5.7968462 | U24: =U23+T24 -> 836.62921 | V24: {=SUM(_xlfn._xlws.FILTER(I:I,A:A=S24,0))} -> 657.92 | W24: {=COUNT(_xlfn._xlws.FILTER(I:I,A:A=S24,""))} -> 10 | X24: {=SUM(_xlfn._xlws.FILTER(K:K,A:A=S24,0))} -> 57.622445 | Y24: =Y23+X24 -> 1271.6135 | AD24: 0.60264901 | AE24: 3 | AF24: =COUNTIFS($G$2:$G$4000,AD24,$M$2:$M$4000,"=Y")/AE24 -> 0.33333333 | AG24: =AD24-AF24 -> 0.26931567 | AK24: 0.078075619 | AL24: 1 | AM24: =COUNTIFS($G$2:$G$4000,AK24,$M$2:$M$4000,"=Y") -> 0 | AO24: =IF(D24<0,I24/(D24/-100),I24*D24/100) -> 132.81449 | AP24: =IF(ISERROR(SEARCH("(Bonus Bet)",B24)),IF(M24="Y",AO24,IF(M24="N",-I24,0)),IF(M24="N",0,IF(M24="Y",AO24,0))) -> -458.21 | AQ24: =N24 -> -458.21 | AR24: =AQ24-AP24+AR23 -> 322.96377
A25: 45263 | B25: Russell Wilson Passing TDs (U/O 1.5) | C25: Fanduel | D25: -204 | E25: 130 | F25: -122 | G25: =IF(AND(D25<0,E25<0),(D25*E25-100*D25)/(2*D25*E25-100*D25-100*E25),IF(OR(AND(D25<0,E25>0),AND(D25>0,E25<0)),IF(D25<=E25,(100*D25+D25*E25)/(200*D25+D25*E25-10000),(100*E25-10000)/(200*E25+D25*E25-10000)),0)) -> 0.60682876 | H25: =IF(F25<0,G25+(1-G25)*(F25/100),IF(F25>0,G25-(1-G25)*(100/F25),0))*$O$2/2 -> 317.89964 | I25: 200 | J25: =IF(F25<0,I25/(F25/-100),I25*F25/100) -> 163.93443 | K25: =G25*J25-(1-G25)*I25 -> 20.845878 | L25: =IF(F25>0,(G25*F25/100-(1-G25)),IF(F25<0,(G25*100/-F25-(1-G25)),0)) -> 0.10422939 | M25: Y | N25: =IF(ISERROR(SEARCH("(Bonus Bet)",B25)),IF(M25="Y",J25,IF(M25="N",-I25,0)),IF(M25="N",0,IF(M25="Y",J25,0))) -> 163.93443 | P25: Average Daily Income | R25: WEEK 4 | S25: 45277 | T25: {=SUM(_xlfn._xlws.FILTER(N:N,A:A=S25,0))} -> 66.477266 | U25: =U24+T25 -> 903.10648 | V25: {=SUM(_xlfn._xlws.FILTER(I:I,A:A=S25,0))} -> 2820.62 | W25: {=COUNT(_xlfn._xlws.FILTER(I:I,A:A=S25,""))} -> 18 | X25: {=SUM(_xlfn._xlws.FILTER(K:K,A:A=S25,0))} -> 172.84594 | Y25: =Y24+X25 -> 1444.4595 | AD25: 0.59465904 | AE25: 1 | AF25: =COUNTIFS($G$2:$G$4000,AD25,$M$2:$M$4000,"=Y")/AE25 -> 1 | AG25: =AD25-AF25 -> -0.40534096 | AK25: 0.090350293 | AL25: 1 | AM25: =COUNTIFS($G$2:$G$4000,AK25,$M$2:$M$4000,"=Y") -> 0 | AO25: =IF(D25<0,I25/(D25/-100),I25*D25/100) -> 98.039216 | AP25: =IF(ISERROR(SEARCH("(Bonus Bet)",B25)),IF(M25="Y",AO25,IF(M25="N",-I25,0)),IF(M25="N",0,IF(M25="Y",AO25,0))) -> 98.039216 | AQ25: =N25 -> 163.93443 | AR25: =AQ25-AP25+AR24 -> 388.85898
A26: 45259 | B26: Keyonte George Under 14.5 Points | C26: Betano | D26: -166 | E26: 120 | F26: -111 | G26: =IF(AND(D26<0,E26<0),(D26*E26-100*D26)/(2*D26*E26-100*D26-100*E26),IF(OR(AND(D26<0,E26>0),AND(D26>0,E26<0)),IF(D26<=E26,(100*D26+D26*E26)/(200*D26+D26*E26-10000),(100*E26-10000)/(200*E26+D26*E26-10000)),0)) -> 0.57858048 | H26: =IF(F26<0,G26+(1-G26)*(F26/100),IF(F26>0,G26-(1-G26)*(100/F26),0))*$O$2/2 -> 277.01204 | I26: 200 | J26: =IF(F26<0,I26/(F26/-100),I26*F26/100) -> 180.18018 | K26: =G26*J26-(1-G26)*I26 -> 19.964832 | L26: =IF(F26>0,(G26*F26/100-(1-G26)),IF(F26<0,(G26*100/-F26-(1-G26)),0)) -> 0.099824159 | M26: Y | N26: =IF(ISERROR(SEARCH("(Bonus Bet)",B26)),IF(M26="Y",J26,IF(M26="N",-I26,0)),IF(M26="N",0,IF(M26="Y",J26,0))) -> 180.18018 | P26: =P6/P24 -> 20.634459 | R26: =SUM(T25:T31) -> 2690.9222 | S26: 45278 | T26: {=SUM(_xlfn._xlws.FILTER(N:N,A:A=S26,0))} -> 902.99963 | U26: =U25+T26 -> 1806.1061 | V26: {=SUM(_xlfn._xlws.FILTER(I:I,A:A=S26,0))} -> 1196.38 | W26: {=COUNT(_xlfn._xlws.FILTER(I:I,A:A=S26,""))} -> 12 | X26: {=SUM(_xlfn._xlws.FILTER(K:K,A:A=S26,0))} -> 80.772448 | Y26: =Y25+X26 -> 1525.2319 | AD26: 0.56953642 | AE26: 1 | AF26: =COUNTIFS($G$2:$G$4000,AD26,$M$2:$M$4000,"=Y")/AE26 -> 1 | AG26: =AD26-AF26 -> -0.43046358 | AK26: 0.08159402 | AL26: 1 | AM26: =COUNTIFS($G$2:$G$4000,AK26,$M$2:$M$4000,"=Y") -> 0 | AO26: =IF(D26<0,I26/(D26/-100),I26*D26/100) -> 120.48193 | AP26: =IF(ISERROR(SEARCH("(Bonus Bet)",B26)),IF(M26="Y",AO26,IF(M26="N",-I26,0)),IF(M26="N",0,IF(M26="Y",AO26,0))) -> 120.48193 | AQ26: =N26 -> 180.18018 | AR26: =AQ26-AP26+AR25 -> 448.55723
A27: 45260 | B27: Tyler Lockett Over 45.5 Receiving Yards | C27: Fanduel | D27: -113 | E27: 113 | F27: -113 | G27: =IF(AND(D27<0,E27<0),(D27*E27-100*D27)/(2*D27*E27-100*D27-100*E27),IF(OR(AND(D27<0,E27>0),AND(D27>0,E27<0)),IF(D27<=E27,(100*D27+D27*E27)/(200*D27+D27*E27-10000),(100*E27-10000)/(200*E27+D27*E27-10000)),0)) -> 0.53051643 | H27: =IF(F27<0,G27+(1-G27)*(F27/100),IF(F27>0,G27-(1-G27)*(100/F27),0))*$O$2/2 -> 0 | I27: 200 | J27: =IF(F27<0,I27/(F27/-100),I27*F27/100) -> 176.99115 | K27: =G27*J27-(1-G27)*I27 -> 0 | L27: =IF(F27>0,(G27*F27/100-(1-G27)),IF(F27<0,(G27*100/-F27-(1-G27)),0)) -> 0 | M27: Y | N27: =IF(ISERROR(SEARCH("(Bonus Bet)",B27)),IF(M27="Y",J27,IF(M27="N",-I27,0)),IF(M27="N",0,IF(M27="Y",J27,0))) -> 176.99115 | P27: Yearly Projection | S27: 45279 | T27: {=SUM(_xlfn._xlws.FILTER(N:N,A:A=S27,0))} -> 120.20859 | U27: =U26+T27 -> 1926.3147 | V27: {=SUM(_xlfn._xlws.FILTER(I:I,A:A=S27,0))} -> 1084.79 | W27: {=COUNT(_xlfn._xlws.FILTER(I:I,A:A=S27,""))} -> 6 | X27: {=SUM(_xlfn._xlws.FILTER(K:K,A:A=S27,0))} -> 74.712066 | Y27: =Y26+X27 -> 1599.944 | AD27: 0.67058824 | AE27: 1 | AF27: =COUNTIFS($G$2:$G$4000,AD27,$M$2:$M$4000,"=Y")/AE27 -> 0 | AG27: =AD27-AF27 -> 0.67058824 | AK27: 0.076429862 | AL27: 1 | AM27: =COUNTIFS($G$2:$G$4000,AK27,$M$2:$M$4000,"=Y") -> 0 | AO27: =IF(D27<0,I27/(D27/-100),I27*D27/100) -> 176.99115 | AP27: =IF(ISERROR(SEARCH("(Bonus Bet)",B27)),IF(M27="Y",AO27,IF(M27="N",-I27,0)),IF(M27="N",0,IF(M27="Y",AO27,0))) -> 176.99115 | AQ27: =N27 -> 176.99115 | AR27: =AQ27-AP27+AR26 -> 448.55723
A28: 45259 | B28: Paul George Under 3.5 Assists | C28: Fanduel | D28: -182 | E28: 135 | F28: -132 | G28: =IF(AND(D28<0,E28<0),(D28*E28-100*D28)/(2*D28*E28-100*D28-100*E28),IF(OR(AND(D28<0,E28>0),AND(D28>0,E28<0)),IF(D28<=E28,(100*D28+D28*E28)/(200*D28+D28*E28-10000),(100*E28-10000)/(200*E28+D28*E28-10000)),0)) -> 0.60264901 | H28: =IF(F28<0,G28+(1-G28)*(F28/100),IF(F28>0,G28-(1-G28)*(100/F28),0))*$O$2/2 -> 195.36424 | I28: 200 | J28: =IF(F28<0,I28/(F28/-100),I28*F28/100) -> 151.51515 | K28: =G28*J28-(1-G28)*I28 -> 11.840257 | L28: =IF(F28>0,(G28*F28/100-(1-G28)),IF(F28<0,(G28*100/-F28-(1-G28)),0)) -> 0.059201284 | M28: N | N28: =IF(ISERROR(SEARCH("(Bonus Bet)",B28)),IF(M28="Y",J28,IF(M28="N",-I28,0)),IF(M28="N",0,IF(M28="Y",J28,0))) -> -200 | P28: =P26*365 -> 7531.5775 | S28: 45280 | T28: {=SUM(_xlfn._xlws.FILTER(N:N,A:A=S28,0))} -> 570.76941 | U28: =U27+T28 -> 2497.0841 | V28: {=SUM(_xlfn._xlws.FILTER(I:I,A:A=S28,0))} -> 2285.41 | W28: {=COUNT(_xlfn._xlws.FILTER(I:I,A:A=S28,""))} -> 31 | X28: {=SUM(_xlfn._xlws.FILTER(K:K,A:A=S28,0))} -> 135.47107 | Y28: =Y27+X28 -> 1735.4151 | AD28: 0.5527333 | AE28: 1 | AF28: =COUNTIFS($G$2:$G$4000,AD28,$M$2:$M$4000,"=Y")/AE28 -> 1 | AG28: =AD28-AF28 -> -0.4472667 | AK28: 0.078390095 | AL28: 1 | AM28: =COUNTIFS($G$2:$G$4000,AK28,$M$2:$M$4000,"=Y") -> 0 | AO28: =IF(D28<0,I28/(D28/-100),I28*D28/100) -> 109.89011 | AP28: =IF(ISERROR(SEARCH("(Bonus Bet)",B28)),IF(M28="Y",AO28,IF(M28="N",-I28,0)),IF(M28="N",0,IF(M28="Y",AO28,0))) -> -200 | AQ28: =N28 -> -200 | AR28: =AQ28-AP28+AR27 -> 448.55723
A29: 45260 | B29: Tony Pollard Under 3.5 Receptions | C29: Fanduel | D29: -172 | E29: 132 | F29: -130 | G29: =IF(AND(D29<0,E29<0),(D29*E29-100*D29)/(2*D29*E29-100*D29-100*E29),IF(OR(AND(D29<0,E29>0),AND(D29>0,E29<0)),IF(D29<=E29,(100*D29+D29*E29)/(200*D29+D29*E29-10000),(100*E29-10000)/(200*E29+D29*E29-10000)),0)) -> 0.59465904 | H29: =IF(F29<0,G29+(1-G29)*(F29/100),IF(F29>0,G29-(1-G29)*(100/F29),0))*$O$2/2 -> 169.28946 | I29: 200 | J29: =IF(F29<0,I29/(F29/-100),I29*F29/100) -> 153.84615 | K29: =G29*J29-(1-G29)*I29 -> 10.417813 | L29: =IF(F29>0,(G29*F29/100-(1-G29)),IF(F29<0,(G29*100/-F29-(1-G29)),0)) -> 0.052089065 | M29: Y | N29: =IF(ISERROR(SEARCH("(Bonus Bet)",B29)),IF(M29="Y",J29,IF(M29="N",-I29,0)),IF(M29="N",0,IF(M29="Y",J29,0))) -> 153.84615 | P29: Hit Rate | S29: 45281 | T29: {=SUM(_xlfn._xlws.FILTER(N:N,A:A=S29,0))} -> -39.239059 | U29: =U28+T29 -> 2457.8451 | V29: {=SUM(_xlfn._xlws.FILTER(I:I,A:A=S29,0))} -> 1839.56 | W29: {=COUNT(_xlfn._xlws.FILTER(I:I,A:A=S29,""))} -> 19 | X29: {=SUM(_xlfn._xlws.FILTER(K:K,A:A=S29,0))} -> 124.73139 | Y29: =Y28+X29 -> 1860.1465 | AD29: 0.57574772 | AE29: 11 | AF29: =COUNTIFS($G$2:$G$4000,AD29,$M$2:$M$4000,"=Y")/AE29 -> 0.90909091 | AG29: =AD29-AF29 -> -0.33334318 | AK29: 0.076432525 | AL29: 2 | AM29: =COUNTIFS($G$2:$G$4000,AK29,$M$2:$M$4000,"=Y") -> 0 | AO29: =IF(D29<0,I29/(D29/-100),I29*D29/100) -> 116.27907 | AP29: =IF(ISERROR(SEARCH("(Bonus Bet)",B29)),IF(M29="Y",AO29,IF(M29="N",-I29,0)),IF(M29="N",0,IF(M29="Y",AO29,0))) -> 116.27907 | AQ29: =N29 -> 153.84615 | AR29: =AQ29-AP29+AR28 -> 486.12431
A30: 45263 | B30: Aston Villa/Bournemouth Over 4.5 Cards | C30: Betano | D30: -160 | E30: 115 | F30: -110 | G30: =IF(AND(D30<0,E30<0),(D30*E30-100*D30)/(2*D30*E30-100*D30-100*E30),IF(OR(AND(D30<0,E30>0),AND(D30>0,E30<0)),IF(D30<=E30,(100*D30+D30*E30)/(200*D30+D30*E30-10000),(100*E30-10000)/(200*E30+D30*E30-10000)),0)) -> 0.56953642 | H30: =IF(F30<0,G30+(1-G30)*(F30/100),IF(F30>0,G30-(1-G30)*(100/F30),0))*$O$2/2 -> 240.06623 | I30: 200 | J30: =IF(F30<0,I30/(F30/-100),I30*F30/100) -> 181.81818 | K30: =G30*J30-(1-G30)*I30 -> 17.459362 | L30: =IF(F30>0,(G30*F30/100-(1-G30)),IF(F30<0,(G30*100/-F30-(1-G30)),0)) -> 0.087296809 | M30: Y | N30: =IF(ISERROR(SEARCH("(Bonus Bet)",B30)),IF(M30="Y",J30,IF(M30="N",-I30,0)),IF(M30="N",0,IF(M30="Y",J30,0))) -> 181.81818 | P30: =P20/(P20+P22) -> 0.48735992 | S30: 45282 | T30: {=SUM(_xlfn._xlws.FILTER(N:N,A:A=S30,0))} -> 797.67608 | U30: =U29+T30 -> 3255.5211 | V30: {=SUM(_xlfn._xlws.FILTER(I:I,A:A=S30,0))} -> 1421.1 | W30: {=COUNT(_xlfn._xlws.FILTER(I:I,A:A=S30,""))} -> 17 | X30: {=SUM(_xlfn._xlws.FILTER(K:K,A:A=S30,0))} -> 117.45151 | Y30: =Y29+X30 -> 1977.598 | AD30: 0.55827068 | AE30: 1 | AF30: =COUNTIFS($G$2:$G$4000,AD30,$M$2:$M$4000,"=Y")/AE30 -> 0 | AG30: =AD30-AF30 -> 0.55827068 | AK30: 0.069891173 | AL30: 1 | AM30: =COUNTIFS($G$2:$G$4000,AK30,$M$2:$M$4000,"=Y") -> 0 | AO30: =IF(D30<0,I30/(D30/-100),I30*D30/100) -> 125 | AP30: =IF(ISERROR(SEARCH("(Bonus Bet)",B30)),IF(M30="Y",AO30,IF(M30="N",-I30,0)),IF(M30="N",0,IF(M30="Y",AO30,0))) -> 125 | AQ30: =N30 -> 181.81818 | AR30: =AQ30-AP30+AR29 -> 542.9425
A31: 45260 | B31: Alex Ovechkin Under 0.5 PowerPlay Points | C31: Bet365 | D31: -250 | E31: 185 | F31: -160 | G31: =IF(AND(D31<0,E31<0),(D31*E31-100*D31)/(2*D31*E31-100*D31-100*E31),IF(OR(AND(D31<0,E31>0),AND(D31>0,E31<0)),IF(D31<=E31,(100*D31+D31*E31)/(200*D31+D31*E31-10000),(100*E31-10000)/(200*E31+D31*E31-10000)),0)) -> 0.67058824 | H31: =IF(F31<0,G31+(1-G31)*(F31/100),IF(F31>0,G31-(1-G31)*(100/F31),0))*$O$2/2 -> 358.82353 | I31: 200 | J31: =IF(F31<0,I31/(F31/-100),I31*F31/100) -> 125 | K31: =G31*J31-(1-G31)*I31 -> 17.941176 | L31: =IF(F31>0,(G31*F31/100-(1-G31)),IF(F31<0,(G31*100/-F31-(1-G31)),0)) -> 0.089705882 | M31: N | N31: =IF(ISERROR(SEARCH("(Bonus Bet)",B31)),IF(M31="Y",J31,IF(M31="N",-I31,0)),IF(M31="N",0,IF(M31="Y",J31,0))) -> -200 | P31: Average Line | S31: 45283 | T31: {=SUM(_xlfn._xlws.FILTER(N:N,A:A=S31,0))} -> 272.03023 | U31: =U30+T31 -> 3527.5514 | V31: {=SUM(_xlfn._xlws.FILTER(I:I,A:A=S31,0))} -> 1057.99 | W31: {=COUNT(_xlfn._xlws.FILTER(I:I,A:A=S31,""))} -> 8 | X31: {=SUM(_xlfn._xlws.FILTER(K:K,A:A=S31,0))} -> 42.567396 | Y31: =Y30+X31 -> 2020.1654 | AD31: 0.6187175 | AE31: 1 | AF31: =COUNTIFS($G$2:$G$4000,AD31,$M$2:$M$4000,"=Y")/AE31 -> 0 | AG31: =AD31-AF31 -> 0.6187175 | AK31: 0.084119154 | AL31: 1 | AM31: =COUNTIFS($G$2:$G$4000,AK31,$M$2:$M$4000,"=Y") -> 0 | AO31: =IF(D31<0,I31/(D31/-100),I31*D31/100) -> 80 | AP31: =IF(ISERROR(SEARCH("(Bonus Bet)",B31)),IF(M31="Y",AO31,IF(M31="N",-I31,0)),IF(M31="N",0,IF(M31="Y",AO31,0))) -> -200 | AQ31: =N31 -> -200 | AR31: =AQ31-AP31+AR30 -> 542.9425
A32: 45260 | B32: Connor McDavid Over 0.5 PowerPlay Points | C32: Bet365 | D32: -143 | E32: 110 | F32: 100 | G32: =IF(AND(D32<0,E32<0),(D32*E32-100*D32)/(2*D32*E32-100*D32-100*E32),IF(OR(AND(D32<0,E32>0),AND(D32>0,E32<0)),IF(D32<=E32,(100*D32+D32*E32)/(200*D32+D32*E32-10000),(100*E32-10000)/(200*E32+D32*E32-10000)),0)) -> 0.5527333 | H32: =IF(F32<0,G32+(1-G32)*(F32/100),IF(F32>0,G32-(1-G32)*(100/F32),0))*$O$2/2 -> 263.66648 | I32: 200 | J32: =IF(F32<0,I32/(F32/-100),I32*F32/100) -> 200 | K32: =G32*J32-(1-G32)*I32 -> 21.093319 | L32: =IF(F32>0,(G32*F32/100-(1-G32)),IF(F32<0,(G32*100/-F32-(1-G32)),0)) -> 0.10546659 | M32: Y | N32: =IF(ISERROR(SEARCH("(Bonus Bet)",B32)),IF(M32="Y",J32,IF(M32="N",-I32,0)),IF(M32="N",0,IF(M32="Y",J32,0))) -> 200 | P32: =IF(AVERAGEIF(G:G,"<>0")<=0.5,100/AVERAGEIF(G:G,"<>0")-100,-100*AVERAGEIF(G:G,"<>0")/(1-AVERAGEIF(G:G,"<>0"))) -> 105.92365 | R32: WEEK 5 | S32: 45284 | T32: {=SUM(_xlfn._xlws.FILTER(N:N,A:A=S32,0))} -> -346.54703 | U32: =U31+T32 -> 3181.0043 | V32: {=SUM(_xlfn._xlws.FILTER(I:I,A:A=S32,0))} -> 1400.52 | W32: {=COUNT(_xlfn._xlws.FILTER(I:I,A:A=S32,""))} -> 9 | X32: {=SUM(_xlfn._xlws.FILTER(K:K,A:A=S32,0))} -> 142.20952 | Y32: =Y31+X32 -> 2162.3749 | AD32: 0.8630137 | AE32: 1 | AF32: =COUNTIFS($G$2:$G$4000,AD32,$M$2:$M$4000,"=Y")/AE32 -> 0 | AG32: =AD32-AF32 -> 0.8630137 | AK32: 0.072048125 | AL32: 1 | AM32: =COUNTIFS($G$2:$G$4000,AK32,$M$2:$M$4000,"=Y") -> 0 | AO32: =IF(D32<0,I32/(D32/-100),I32*D32/100) -> 139.86014 | AP32: =IF(ISERROR(SEARCH("(Bonus Bet)",B32)),IF(M32="Y",AO32,IF(M32="N",-I32,0)),IF(M32="N",0,IF(M32="Y",AO32,0))) -> 139.86014 | AQ32: =N32 -> 200 | AR32: =AQ32-AP32+AR31 -> 603.08236
A33: 45260 | B33: Chet Holmgren Under 2.5 Assists | C33: Fanduel | D33: -161 | E33: 120 | F33: -112 | G33: =IF(AND(D33<0,E33<0),(D33*E33-100*D33)/(2*D33*E33-100*D33-100*E33),IF(OR(AND(D33<0,E33>0),AND(D33>0,E33<0)),IF(D33<=E33,(100*D33+D33*E33)/(200*D33+D33*E33-10000),(100*E33-10000)/(200*E33+D33*E33-10000)),0)) -> 0.57574772 | H33: =IF(F33<0,G33+(1-G33)*(F33/100),IF(F33>0,G33-(1-G33)*(100/F33),0))*$O$2/2 -> 251.46294 | I33: 200 | J33: =IF(F33<0,I33/(F33/-100),I33*F33/100) -> 178.57143 | K33: =G33*J33-(1-G33)*I33 -> 17.961638 | L33: =IF(F33>0,(G33*F33/100-(1-G33)),IF(F33<0,(G33*100/-F33-(1-G33)),0)) -> 0.089808192 | M33: Y | N33: =IF(ISERROR(SEARCH("(Bonus Bet)",B33)),IF(M33="Y",J33,IF(M33="N",-I33,0)),IF(M33="N",0,IF(M33="Y",J33,0))) -> 178.57143 | P33: Pinny Line Difference | R33: =SUM(T32:T38) -> 2702.4446 | S33: 45285 | T33: {=SUM(_xlfn._xlws.FILTER(N:N,A:A=S33,0))} -> 765.2436 | U33: =U32+T33 -> 3946.2479 | V33: {=SUM(_xlfn._xlws.FILTER(I:I,A:A=S33,0))} -> 1155.14 | W33: {=COUNT(_xlfn._xlws.FILTER(I:I,A:A=S33,""))} -> 18 | X33: {=SUM(_xlfn._xlws.FILTER(K:K,A:A=S33,0))} -> 106.40976 | Y33: =Y32+X33 -> 2268.7846 | AD33: 0.62217924 | AE33: 1 | AF33: =COUNTIFS($G$2:$G$4000,AD33,$M$2:$M$4000,"=Y")/AE33 -> 1 | AG33: =AD33-AF33 -> -0.37782076 | AK33: 0.099274271 | AL33: 1 | AM33: =COUNTIFS($G$2:$G$4000,AK33,$M$2:$M$4000,"=Y") -> 0 | AO33: =IF(D33<0,I33/(D33/-100),I33*D33/100) -> 124.2236 | AP33: =IF(ISERROR(SEARCH("(Bonus Bet)",B33)),IF(M33="Y",AO33,IF(M33="N",-I33,0)),IF(M33="N",0,IF(M33="Y",AO33,0))) -> 124.2236 | AQ33: =N33 -> 178.57143 | AR33: =AQ33-AP33+AR32 -> 657.43018
A34: 45262 | B34: Ashton Jeanty Receiving Yards (O/U 29.5) | C34: DraftKings | D34: -135 | E34: 120 | F34: -115 | G34: =IF(AND(D34<0,E34<0),(D34*E34-100*D34)/(2*D34*E34-100*D34-100*E34),IF(OR(AND(D34<0,E34>0),AND(D34>0,E34<0)),IF(D34<=E34,(100*D34+D34*E34)/(200*D34+D34*E34-10000),(100*E34-10000)/(200*E34+D34*E34-10000)),0)) -> 0.55827068 | H34: =IF(F34<0,G34+(1-G34)*(F34/100),IF(F34>0,G34-(1-G34)*(100/F34),0))*$O$2/2 -> 125.70489 | I34: 200 | J34: =IF(F34<0,I34/(F34/-100),I34*F34/100) -> 173.91304 | K34: =G34*J34-(1-G34)*I34 -> 8.7446878 | L34: =IF(F34>0,(G34*F34/100-(1-G34)),IF(F34<0,(G34*100/-F34-(1-G34)),0)) -> 0.043723439 | M34: N | N34: =IF(ISERROR(SEARCH("(Bonus Bet)",B34)),IF(M34="Y",J34,IF(M34="N",-I34,0)),IF(M34="N",0,IF(M34="Y",J34,0))) -> -200 | P34: =AH2 -> 0.0086328667 | S34: 45286 | T34: {=SUM(_xlfn._xlws.FILTER(N:N,A:A=S34,0))} -> -139.61788 | U34: =U33+T34 -> 3806.6301 | V34: {=SUM(_xlfn._xlws.FILTER(I:I,A:A=S34,0))} -> 2008.16 | W34: {=COUNT(_xlfn._xlws.FILTER(I:I,A:A=S34,""))} -> 25 | X34: {=SUM(_xlfn._xlws.FILTER(K:K,A:A=S34,0))} -> 94.975408 | Y34: =Y33+X34 -> 2363.76 | AD34: 0.61518047 | AE34: 2 | AF34: =COUNTIFS($G$2:$G$4000,AD34,$M$2:$M$4000,"=Y")/AE34 -> 0.5 | AG34: =AD34-AF34 -> 0.11518047 | AK34: 0.079020959 | AL34: 2 | AM34: =COUNTIFS($G$2:$G$4000,AK34,$M$2:$M$4000,"=Y") -> 0 | AO34: =IF(D34<0,I34/(D34/-100),I34*D34/100) -> 148.14815 | AP34: =IF(ISERROR(SEARCH("(Bonus Bet)",B34)),IF(M34="Y",AO34,IF(M34="N",-I34,0)),IF(M34="N",0,IF(M34="Y",AO34,0))) -> -200 | AQ34: =N34 -> -200 | AR34: =AQ34-AP34+AR33 -> 657.43018
A35: 45262 | B35: Toledo Moneyline (v George Mason) | C35: Bet365 | D35: -175 | E35: 155 | F35: -145 | G35: =IF(AND(D35<0,E35<0),(D35*E35-100*D35)/(2*D35*E35-100*D35-100*E35),IF(OR(AND(D35<0,E35>0),AND(D35>0,E35<0)),IF(D35<=E35,(100*D35+D35*E35)/(200*D35+D35*E35-10000),(100*E35-10000)/(200*E35+D35*E35-10000)),0)) -> 0.6187175 | H35: =IF(F35<0,G35+(1-G35)*(F35/100),IF(F35>0,G35-(1-G35)*(100/F35),0))*$O$2/2 -> 164.64471 | I35: 200 | J35: =IF(F35<0,I35/(F35/-100),I35*F35/100) -> 137.93103 | K35: =G35*J35-(1-G35)*I35 -> 9.0838463 | L35: =IF(F35>0,(G35*F35/100-(1-G35)),IF(F35<0,(G35*100/-F35-(1-G35)),0)) -> 0.045419231 | M35: N | N35: =IF(ISERROR(SEARCH("(Bonus Bet)",B35)),IF(M35="Y",J35,IF(M35="N",-I35,0)),IF(M35="N",0,IF(M35="Y",J35,0))) -> -200 | P35: Average Edge/Bet | S35: 45287 | T35: {=SUM(_xlfn._xlws.FILTER(N:N,A:A=S35,0))} -> 303.10059 | U35: =U34+T35 -> 4109.7307 | V35: {=SUM(_xlfn._xlws.FILTER(I:I,A:A=S35,0))} -> 1414.18 | W35: {=COUNT(_xlfn._xlws.FILTER(I:I,A:A=S35,""))} -> 30 | X35: {=SUM(_xlfn._xlws.FILTER(K:K,A:A=S35,0))} -> 99.176142 | Y35: =Y34+X35 -> 2462.9362 | AD35: 0.62691131 | AE35: 1 | AF35: =COUNTIFS($G$2:$G$4000,AD35,$M$2:$M$4000,"=Y")/AE35 -> 0 | AG35: =AD35-AF35 -> 0.62691131 | AK35: 0.061762372 | AL35: 1 | AM35: =COUNTIFS($G$2:$G$4000,AK35,$M$2:$M$4000,"=Y") -> 0 | AO35: =IF(D35<0,I35/(D35/-100),I35*D35/100) -> 114.28571 | AP35: =IF(ISERROR(SEARCH("(Bonus Bet)",B35)),IF(M35="Y",AO35,IF(M35="N",-I35,0)),IF(M35="N",0,IF(M35="Y",AO35,0))) -> -200 | AQ35: =N35 -> -200 | AR35: =AQ35-AP35+AR34 -> 657.43018
A36: 45262 | B36: Marshall Moneyline (v Miami OH) | C36: Bet365 | D36: -900 | E36: 600 | F36: -500 | G36: =IF(AND(D36<0,E36<0),(D36*E36-100*D36)/(2*D36*E36-100*D36-100*E36),IF(OR(AND(D36<0,E36>0),AND(D36>0,E36<0)),IF(D36<=E36,(100*D36+D36*E36)/(200*D36+D36*E36-10000),(100*E36-10000)/(200*E36+D36*E36-10000)),0)) -> 0.8630137 | H36: =IF(F36<0,G36+(1-G36)*(F36/100),IF(F36>0,G36-(1-G36)*(100/F36),0))*$O$2/2 -> 445.20548 | I36: 344.39 | J36: =IF(F36<0,I36/(F36/-100),I36*F36/100) -> 68.878 | K36: =G36*J36-(1-G36)*I36 -> 12.265945 | L36: =IF(F36>0,(G36*F36/100-(1-G36)),IF(F36<0,(G36*100/-F36-(1-G36)),0)) -> 0.035616438 | M36: N | N36: =IF(ISERROR(SEARCH("(Bonus Bet)",B36)),IF(M36="Y",J36,IF(M36="N",-I36,0)),IF(M36="N",0,IF(M36="Y",J36,0))) -> -344.39 | P36: =(P6-AS2)/SUM(W:W) -> 10.651149 | S36: 45288 | T36: {=SUM(_xlfn._xlws.FILTER(N:N,A:A=S36,0))} -> 1726.2764 | U36: =U35+T36 -> 5836.007 | V36: {=SUM(_xlfn._xlws.FILTER(I:I,A:A=S36,0))} -> 2480.47 | W36: {=COUNT(_xlfn._xlws.FILTER(I:I,A:A=S36,""))} -> 32 | X36: {=SUM(_xlfn._xlws.FILTER(K:K,A:A=S36,0))} -> 198.59875 | Y36: =Y35+X36 -> 2661.5349 | AD36: 0.65405405 | AE36: 2 | AF36: =COUNTIFS($G$2:$G$4000,AD36,$M$2:$M$4000,"=Y")/AE36 -> 1 | AG36: =AD36-AF36 -> -0.34594595 | AK36: 0.0843048 | AL36: 1 | AM36: =COUNTIFS($G$2:$G$4000,AK36,$M$2:$M$4000,"=Y") -> 0 | AO36: =IF(D36<0,I36/(D36/-100),I36*D36/100) -> 38.265556 | AP36: =IF(ISERROR(SEARCH("(Bonus Bet)",B36)),IF(M36="Y",AO36,IF(M36="N",-I36,0)),IF(M36="N",0,IF(M36="Y",AO36,0))) -> -344.39 | AQ36: =N36 -> -344.39 | AR36: =AQ36-AP36+AR35 -> 657.43018
A37: 45262 | B37: Promitheas Moneyline (v AEK Athens) | C37: Unibet | D37: -193 | E37: 150 | F37: -143 | G37: =IF(AND(D37<0,E37<0),(D37*E37-100*D37)/(2*D37*E37-100*D37-100*E37),IF(OR(AND(D37<0,E37>0),AND(D37>0,E37<0)),IF(D37<=E37,(100*D37+D37*E37)/(200*D37+D37*E37-10000),(100*E37-10000)/(200*E37+D37*E37-10000)),0)) -> 0.62217924 | H37: =IF(F37<0,G37+(1-G37)*(F37/100),IF(F37>0,G37-(1-G37)*(100/F37),0))*$O$2/2 -> 204.73888 | I37: 127.45 | J37: =IF(F37<0,I37/(F37/-100),I37*F37/100) -> 89.125874 | K37: =G37*J37-(1-G37)*I37 -> 7.2990126 | L37: =IF(F37>0,(G37*F37/100-(1-G37)),IF(F37<0,(G37*100/-F37-(1-G37)),0)) -> 0.057269616 | M37: Y | N37: =IF(ISERROR(SEARCH("(Bonus Bet)",B37)),IF(M37="Y",J37,IF(M37="N",-I37,0)),IF(M37="N",0,IF(M37="Y",J37,0))) -> 89.125874 | S37: 45289 | T37: {=SUM(_xlfn._xlws.FILTER(N:N,A:A=S37,0))} -> 383.58575 | U37: =U36+T37 -> 6219.5928 | V37: {=SUM(_xlfn._xlws.FILTER(I:I,A:A=S37,0))} -> 675 | W37: {=COUNT(_xlfn._xlws.FILTER(I:I,A:A=S37,""))} -> 8 | X37: {=SUM(_xlfn._xlws.FILTER(K:K,A:A=S37,0))} -> 16.960972 | Y37: =Y36+X37 -> 2678.4959 | AD37: 0.552594 | AE37: 5 | AF37: =COUNTIFS($G$2:$G$4000,AD37,$M$2:$M$4000,"=Y")/AE37 -> 0.6 | AG37: =AD37-AF37 -> -0.047405997 | AK37: 0.09633354 | AL37: 1 | AM37: =COUNTIFS($G$2:$G$4000,AK37,$M$2:$M$4000,"=Y") -> 0 | AO37: =IF(D37<0,I37/(D37/-100),I37*D37/100) -> 66.036269 | AP37: =IF(ISERROR(SEARCH("(Bonus Bet)",B37)),IF(M37="Y",AO37,IF(M37="N",-I37,0)),IF(M37="N",0,IF(M37="Y",AO37,0))) -> 66.036269 | AQ37: =N37 -> 89.125874 | AR37: =AQ37-AP37+AR36 -> 680.51979
A38: 45262 | B38: Miro Heiskanen Under 2.5 Shots on Goal | C38: Northstar | D38: -190 | E38: 144 | F38: -122 | G38: =IF(AND(D38<0,E38<0),(D38*E38-100*D38)/(2*D38*E38-100*D38-100*E38),IF(OR(AND(D38<0,E38>0),AND(D38>0,E38<0)),IF(D38<=E38,(100*D38+D38*E38)/(200*D38+D38*E38-10000),(100*E38-10000)/(200*E38+D38*E38-10000)),0)) -> 0.61518047 | H38: =IF(F38<0,G38+(1-G38)*(F38/100),IF(F38>0,G38-(1-G38)*(100/F38),0))*$O$2/2 -> 364.25159 | I38: 642.31 | J38: =IF(F38<0,I38/(F38/-100),I38*F38/100) -> 526.48361 | K38: =G38*J38-(1-G38)*I38 -> 76.708997 | L38: =IF(F38>0,(G38*F38/100-(1-G38)),IF(F38<0,(G38*100/-F38-(1-G38)),0)) -> 0.11942675 | M38: Y | N38: =IF(ISERROR(SEARCH("(Bonus Bet)",B38)),IF(M38="Y",J38,IF(M38="N",-I38,0)),IF(M38="N",0,IF(M38="Y",J38,0))) -> 526.48361 | S38: 45290 | T38: {=SUM(_xlfn._xlws.FILTER(N:N,A:A=S38,0))} -> 10.403182 | U38: =U37+T38 -> 6229.996 | V38: {=SUM(_xlfn._xlws.FILTER(I:I,A:A=S38,0))} -> 1001.79 | W38: {=COUNT(_xlfn._xlws.FILTER(I:I,A:A=S38,""))} -> 8 | X38: {=SUM(_xlfn._xlws.FILTER(K:K,A:A=S38,0))} -> 68.869937 | Y38: =Y37+X38 -> 2747.3658 | AD38: 0.53389831 | AE38: 1 | AF38: =COUNTIFS($G$2:$G$4000,AD38,$M$2:$M$4000,"=Y")/AE38 -> 1 | AG38: =AD38-AF38 -> -0.46610169 | AK38: 0.089027037 | AL38: 1 | AM38: =COUNTIFS($G$2:$G$4000,AK38,$M$2:$M$4000,"=Y") -> 0 | AO38: =IF(D38<0,I38/(D38/-100),I38*D38/100) -> 338.05789 | AP38: =IF(ISERROR(SEARCH("(Bonus Bet)",B38)),IF(M38="Y",AO38,IF(M38="N",-I38,0)),IF(M38="N",0,IF(M38="Y",AO38,0))) -> 338.05789 | AQ38: =N38 -> 526.48361 | AR38: =AQ38-AP38+AR37 -> 868.9455
A39: 45262 | B39: Jimmy Butler Over 5.5 Rebounds | C39: Fanduel | D39: -205 | E39: 150 | F39: -134 | G39: =IF(AND(D39<0,E39<0),(D39*E39-100*D39)/(2*D39*E39-100*D39-100*E39),IF(OR(AND(D39<0,E39>0),AND(D39>0,E39<0)),IF(D39<=E39,(100*D39+D39*E39)/(200*D39+D39*E39-10000),(100*E39-10000)/(200*E39+D39*E39-10000)),0)) -> 0.62691131 | H39: =IF(F39<0,G39+(1-G39)*(F39/100),IF(F39>0,G39-(1-G39)*(100/F39),0))*$O$2/2 -> 317.43119 | I39: 360.14 | J39: =IF(F39<0,I39/(F39/-100),I39*F39/100) -> 268.76119 | K39: =G39*J39-(1-G39)*I39 -> 34.125275 | L39: =IF(F39>0,(G39*F39/100-(1-G39)),IF(F39<0,(G39*100/-F39-(1-G39)),0)) -> 0.09475558 | M39: N | N39: =IF(ISERROR(SEARCH("(Bonus Bet)",B39)),IF(M39="Y",J39,IF(M39="N",-I39,0)),IF(M39="N",0,IF(M39="Y",J39,0))) -> -360.14 | R39: WEEK 6 | S39: 45291 | T39: {=SUM(_xlfn._xlws.FILTER(N:N,A:A=S39,0))} -> -328.80729 | U39: =U38+T39 -> 5901.1887 | V39: {=SUM(_xlfn._xlws.FILTER(I:I,A:A=S39,0))} -> 3320.87 | W39: {=COUNT(_xlfn._xlws.FILTER(I:I,A:A=S39,""))} -> 45 | X39: {=SUM(_xlfn._xlws.FILTER(K:K,A:A=S39,0))} -> 344.45692 | Y39: =Y38+X39 -> 3091.8228 | AD39: 0.56896552 | AE39: 7 | AF39: =COUNTIFS($G$2:$G$4000,AD39,$M$2:$M$4000,"=Y")/AE39 -> 0.14285714 | AG39: =AD39-AF39 -> 0.42610837 | AK39: 0.099892579 | AL39: 1 | AM39: =COUNTIFS($G$2:$G$4000,AK39,$M$2:$M$4000,"=Y") -> 0 | AO39: =IF(D39<0,I39/(D39/-100),I39*D39/100) -> 175.67805 | AP39: =IF(ISERROR(SEARCH("(Bonus Bet)",B39)),IF(M39="Y",AO39,IF(M39="N",-I39,0)),IF(M39="N",0,IF(M39="Y",AO39,0))) -> -360.14 | AQ39: =N39 -> -360.14 | AR39: =AQ39-AP39+AR38 -> 868.9455
A40: 45262 | B40: Kevin Durant Under 1.5 Blocks | C40: BetRivers | D40: -220 | E40: 175 | F40: -165 | G40: =IF(AND(D40<0,E40<0),(D40*E40-100*D40)/(2*D40*E40-100*D40-100*E40),IF(OR(AND(D40<0,E40>0),AND(D40>0,E40<0)),IF(D40<=E40,(100*D40+D40*E40)/(200*D40+D40*E40-10000),(100*E40-10000)/(200*E40+D40*E40-10000)),0)) -> 0.65405405 | H40: =IF(F40<0,G40+(1-G40)*(F40/100),IF(F40>0,G40-(1-G40)*(100/F40),0))*$O$2/2 -> 208.10811 | I40: 200 | J40: =IF(F40<0,I40/(F40/-100),I40*F40/100) -> 121.21212 | K40: =G40*J40-(1-G40)*I40 -> 10.09009 | L40: =IF(F40>0,(G40*F40/100-(1-G40)),IF(F40<0,(G40*100/-F40-(1-G40)),0)) -> 0.05045045 | M40: Y | N40: =IF(ISERROR(SEARCH("(Bonus Bet)",B40)),IF(M40="Y",J40,IF(M40="N",-I40,0)),IF(M40="N",0,IF(M40="Y",J40,0))) -> 121.21212 | R40: =SUM(T39:T45) -> 838.12125 | S40: 45292 | T40: {=SUM(_xlfn._xlws.FILTER(N:N,A:A=S40,0))} -> 75 | U40: =U39+T40 -> 5976.1887 | V40: {=SUM(_xlfn._xlws.FILTER(I:I,A:A=S40,0))} -> 50 | W40: {=COUNT(_xlfn._xlws.FILTER(I:I,A:A=S40,""))} -> 1 | X40: {=SUM(_xlfn._xlws.FILTER(K:K,A:A=S40,0))} -> 17.694838 | Y40: =Y39+X40 -> 3109.5176 | AD40: 0.53920696 | AE40: 1 | AF40: =COUNTIFS($G$2:$G$4000,AD40,$M$2:$M$4000,"=Y")/AE40 -> 0 | AG40: =AD40-AF40 -> 0.53920696 | AK40: 0.095298799 | AL40: 1 | AM40: =COUNTIFS($G$2:$G$4000,AK40,$M$2:$M$4000,"=Y") -> 0 | AO40: =IF(D40<0,I40/(D40/-100),I40*D40/100) -> 90.909091 | AP40: =IF(ISERROR(SEARCH("(Bonus Bet)",B40)),IF(M40="Y",AO40,IF(M40="N",-I40,0)),IF(M40="N",0,IF(M40="Y",AO40,0))) -> 90.909091 | AQ40: =N40 -> 121.21212 | AR40: =AQ40-AP40+AR39 -> 899.24853
A41: 45263 | B41: Najee Harris Over 55.5 Rushing Yards | C41: BetRivers | D41: -135 | E41: 115 | F41: -110 | G41: =IF(AND(D41<0,E41<0),(D41*E41-100*D41)/(2*D41*E41-100*D41-100*E41),IF(OR(AND(D41<0,E41>0),AND(D41>0,E41<0)),IF(D41<=E41,(100*D41+D41*E41)/(200*D41+D41*E41-10000),(100*E41-10000)/(200*E41+D41*E41-10000)),0)) -> 0.552594 | H41: =IF(F41<0,G41+(1-G41)*(F41/100),IF(F41>0,G41-(1-G41)*(100/F41),0))*$O$2/2 -> 151.11851 | I41: 200 | J41: =IF(F41<0,I41/(F41/-100),I41*F41/100) -> 181.81818 | K41: =G41*J41-(1-G41)*I41 -> 10.990437 | L41: =IF(F41>0,(G41*F41/100-(1-G41)),IF(F41<0,(G41*100/-F41-(1-G41)),0)) -> 0.054952187 | M41: Y | N41: =IF(ISERROR(SEARCH("(Bonus Bet)",B41)),IF(M41="Y",J41,IF(M41="N",-I41,0)),IF(M41="N",0,IF(M41="Y",J41,0))) -> 181.81818 | S41: 45293 | T41: {=SUM(_xlfn._xlws.FILTER(N:N,A:A=S41,0))} -> 49.813523 | U41: =U40+T41 -> 6026.0022 | V41: {=SUM(_xlfn._xlws.FILTER(I:I,A:A=S41,0))} -> 915.32 | W41: {=COUNT(_xlfn._xlws.FILTER(I:I,A:A=S41,""))} -> 20 | X41: {=SUM(_xlfn._xlws.FILTER(K:K,A:A=S41,0))} -> 24.54603 | Y41: =Y40+X41 -> 3134.0636 | AD41: 0.5620438 | AE41: 1 | AF41: =COUNTIFS($G$2:$G$4000,AD41,$M$2:$M$4000,"=Y")/AE41 -> 1 | AG41: =AD41-AF41 -> -0.4379562 | AK41: 0.074740665 | AL41: 1 | AM41: =COUNTIFS($G$2:$G$4000,AK41,$M$2:$M$4000,"=Y") -> 1 | AO41: =IF(D41<0,I41/(D41/-100),I41*D41/100) -> 148.14815 | AP41: =IF(ISERROR(SEARCH("(Bonus Bet)",B41)),IF(M41="Y",AO41,IF(M41="N",-I41,0)),IF(M41="N",0,IF(M41="Y",AO41,0))) -> 148.14815 | AQ41: =N41 -> 181.81818 | AR41: =AQ41-AP41+AR40 -> 932.91856
A42: 45262 | B42: Keegan Murray Under 5.5 Rebounds | C42: Fanduel | D42: -120 | E42: 110 | F42: -112 | G42: =IF(AND(D42<0,E42<0),(D42*E42-100*D42)/(2*D42*E42-100*D42-100*E42),IF(OR(AND(D42<0,E42>0),AND(D42>0,E42<0)),IF(D42<=E42,(100*D42+D42*E42)/(200*D42+D42*E42-10000),(100*E42-10000)/(200*E42+D42*E42-10000)),0)) -> 0.53389831 | H42: =IF(F42<0,G42+(1-G42)*(F42/100),IF(F42>0,G42-(1-G42)*(100/F42),0))*$O$2/2 -> 29.661017 | I42: 200 | J42: =IF(F42<0,I42/(F42/-100),I42*F42/100) -> 178.57143 | K42: =G42*J42-(1-G42)*I42 -> 2.1186441 | L42: =IF(F42>0,(G42*F42/100-(1-G42)),IF(F42<0,(G42*100/-F42-(1-G42)),0)) -> 0.01059322 | M42: Y | N42: =IF(ISERROR(SEARCH("(Bonus Bet)",B42)),IF(M42="Y",J42,IF(M42="N",-I42,0)),IF(M42="N",0,IF(M42="Y",J42,0))) -> 178.57143 | S42: 45294 | T42: {=SUM(_xlfn._xlws.FILTER(N:N,A:A=S42,0))} -> 1256.6964 | U42: =U41+T42 -> 7282.6986 | V42: {=SUM(_xlfn._xlws.FILTER(I:I,A:A=S42,0))} -> 3311.2 | W42: {=COUNT(_xlfn._xlws.FILTER(I:I,A:A=S42,""))} -> 45 | X42: {=SUM(_xlfn._xlws.FILTER(K:K,A:A=S42,0))} -> 179.16097 | Y42: =Y41+X42 -> 3313.2246 | AD42: 0.7571885 | AE42: 1 | AF42: =COUNTIFS($G$2:$G$4000,AD42,$M$2:$M$4000,"=Y")/AE42 -> 1 | AG42: =AD42-AF42 -> -0.2428115 | AK42: 0.075489738 | AL42: 1 | AM42: =COUNTIFS($G$2:$G$4000,AK42,$M$2:$M$4000,"=Y") -> 0 | AO42: =IF(D42<0,I42/(D42/-100),I42*D42/100) -> 166.66667 | AP42: =IF(ISERROR(SEARCH("(Bonus Bet)",B42)),IF(M42="Y",AO42,IF(M42="N",-I42,0)),IF(M42="N",0,IF(M42="Y",AO42,0))) -> 166.66667 | AQ42: =N42 -> 178.57143 | AR42: =AQ42-AP42+AR41 -> 944.82332
A43: 45264 | B43: Zion Williamson Over 24.5 Points | C43: Fanduel | D43: -150 | E43: 120 | F43: -104 | G43: =IF(AND(D43<0,E43<0),(D43*E43-100*D43)/(2*D43*E43-100*D43-100*E43),IF(OR(AND(D43<0,E43>0),AND(D43>0,E43<0)),IF(D43<=E43,(100*D43+D43*E43)/(200*D43+D43*E43-10000),(100*E43-10000)/(200*E43+D43*E43-10000)),0)) -> 0.56896552 | H43: =IF(F43<0,G43+(1-G43)*(F43/100),IF(F43>0,G43-(1-G43)*(100/F43),0))*$O$2/2 -> 301.72414 | I43: 200 | J43: =IF(F43<0,I43/(F43/-100),I43*F43/100) -> 192.30769 | K43: =G43*J43-(1-G43)*I43 -> 23.209549 | L43: =IF(F43>0,(G43*F43/100-(1-G43)),IF(F43<0,(G43*100/-F43-(1-G43)),0)) -> 0.11604775 | M43: N | N43: =IF(ISERROR(SEARCH("(Bonus Bet)",B43)),IF(M43="Y",J43,IF(M43="N",-I43,0)),IF(M43="N",0,IF(M43="Y",J43,0))) -> -200 | S43: 45295 | T43: {=SUM(_xlfn._xlws.FILTER(N:N,A:A=S43,0))} -> -862.24122 | U43: =U42+T43 -> 6420.4574 | V43: {=SUM(_xlfn._xlws.FILTER(I:I,A:A=S43,0))} -> 2255.18 | W43: {=COUNT(_xlfn._xlws.FILTER(I:I,A:A=S43,""))} -> 24 | X43: {=SUM(_xlfn._xlws.FILTER(K:K,A:A=S43,0))} -> 100.19503 | Y43: =Y42+X43 -> 3413.4196 | AD43: 0.56490728 | AE43: 2 | AF43: =COUNTIFS($G$2:$G$4000,AD43,$M$2:$M$4000,"=Y")/AE43 -> 0.5 | AG43: =AD43-AF43 -> 0.064907275 | AK43: 0.08886993 | AL43: 1 | AM43: =COUNTIFS($G$2:$G$4000,AK43,$M$2:$M$4000,"=Y") -> 0 | AO43: =IF(D43<0,I43/(D43/-100),I43*D43/100) -> 133.33333 | AP43: =IF(ISERROR(SEARCH("(Bonus Bet)",B43)),IF(M43="Y",AO43,IF(M43="N",-I43,0)),IF(M43="N",0,IF(M43="Y",AO43,0))) -> -200 | AQ43: =N43 -> -200 | AR43: =AQ43-AP43+AR42 -> 944.82332
A44: 45264 | B44: Jayson Tatum Under 9.5 Rebounds | C44: Bet365 | D44: -133 | E44: 105 | F44: 100 | G44: =IF(AND(D44<0,E44<0),(D44*E44-100*D44)/(2*D44*E44-100*D44-100*E44),IF(OR(AND(D44<0,E44>0),AND(D44>0,E44<0)),IF(D44<=E44,(100*D44+D44*E44)/(200*D44+D44*E44-10000),(100*E44-10000)/(200*E44+D44*E44-10000)),0)) -> 0.53920696 | H44: =IF(F44<0,G44+(1-G44)*(F44/100),IF(F44>0,G44-(1-G44)*(100/F44),0))*$O$2/2 -> 196.03481 | I44: 200 | J44: =IF(F44<0,I44/(F44/-100),I44*F44/100) -> 200 | K44: =G44*J44-(1-G44)*I44 -> 15.682785 | L44: =IF(F44>0,(G44*F44/100-(1-G44)),IF(F44<0,(G44*100/-F44-(1-G44)),0)) -> 0.078413923 | M44: N | N44: =IF(ISERROR(SEARCH("(Bonus Bet)",B44)),IF(M44="Y",J44,IF(M44="N",-I44,0)),IF(M44="N",0,IF(M44="Y",J44,0))) -> -200 | S44: 45296 | T44: {=SUM(_xlfn._xlws.FILTER(N:N,A:A=S44,0))} -> -42.826105 | U44: =U43+T44 -> 6377.6313 | V44: {=SUM(_xlfn._xlws.FILTER(I:I,A:A=S44,0))} -> 4207.45 | W44: {=COUNT(_xlfn._xlws.FILTER(I:I,A:A=S44,""))} -> 52 | X44: {=SUM(_xlfn._xlws.FILTER(K:K,A:A=S44,0))} -> 147.60216 | Y44: =Y43+X44 -> 3561.0218 | AD44: 0.74388824 | AE44: 1 | AF44: =COUNTIFS($G$2:$G$4000,AD44,$M$2:$M$4000,"=Y")/AE44 -> 1 | AG44: =AD44-AF44 -> -0.25611176 | AK44: 0.0812523 | AL44: 1 | AM44: =COUNTIFS($G$2:$G$4000,AK44,$M$2:$M$4000,"=Y") -> 0 | AO44: =IF(D44<0,I44/(D44/-100),I44*D44/100) -> 150.37594 | AP44: =IF(ISERROR(SEARCH("(Bonus Bet)",B44)),IF(M44="Y",AO44,IF(M44="N",-I44,0)),IF(M44="N",0,IF(M44="Y",AO44,0))) -> -200 | AQ44: =N44 -> -200 | AR44: =AQ44-AP44+AR43 -> 944.82332
A45: 45265 | B45: Vancouver Canucks/NJ Devils Over 6.5 Goals | C45: BetRivers | D45: -140 | E45: 120 | F45: -107 | G45: =IF(AND(D45<0,E45<0),(D45*E45-100*D45)/(2*D45*E45-100*D45-100*E45),IF(OR(AND(D45<0,E45>0),AND(D45>0,E45<0)),IF(D45<=E45,(100*D45+D45*E45)/(200*D45+D45*E45-10000),(100*E45-10000)/(200*E45+D45*E45-10000)),0)) -> 0.5620438 | H45: =IF(F45<0,G45+(1-G45)*(F45/100),IF(F45>0,G45-(1-G45)*(100/F45),0))*$O$2/2 -> 233.57664 | I45: 200.77 | J45: =IF(F45<0,I45/(F45/-100),I45*F45/100) -> 187.63551 | K45: =G45*J45-(1-G45)*I45 -> 17.530909 | L45: =IF(F45>0,(G45*F45/100-(1-G45)),IF(F45<0,(G45*100/-F45-(1-G45)),0)) -> 0.087318371 | M45: Y | N45: =IF(ISERROR(SEARCH("(Bonus Bet)",B45)),IF(M45="Y",J45,IF(M45="N",-I45,0)),IF(M45="N",0,IF(M45="Y",J45,0))) -> 187.63551 | S45: 45297 | T45: {=SUM(_xlfn._xlws.FILTER(N:N,A:A=S45,0))} -> 690.48593 | U45: =U44+T45 -> 7068.1172 | V45: {=SUM(_xlfn._xlws.FILTER(I:I,A:A=S45,0))} -> 2512.42 | W45: {=COUNT(_xlfn._xlws.FILTER(I:I,A:A=S45,""))} -> 32 | X45: {=SUM(_xlfn._xlws.FILTER(K:K,A:A=S45,0))} -> 139.9367 | Y45: =Y44+X45 -> 3700.9585 | AD45: 0.6626506 | AE45: 1 | AF45: =COUNTIFS($G$2:$G$4000,AD45,$M$2:$M$4000,"=Y")/AE45 -> 0 | AG45: =AD45-AF45 -> 0.6626506 | AK45: 0.071470536 | AL45: 1 | AM45: =COUNTIFS($G$2:$G$4000,AK45,$M$2:$M$4000,"=Y") -> 0 | AO45: =IF(D45<0,I45/(D45/-100),I45*D45/100) -> 143.40714 | AP45: =IF(ISERROR(SEARCH("(Bonus Bet)",B45)),IF(M45="Y",AO45,IF(M45="N",-I45,0)),IF(M45="N",0,IF(M45="Y",AO45,0))) -> 143.40714 | AQ45: =N45 -> 187.63551 | AR45: =AQ45-AP45+AR44 -> 989.0517
A46: 45266 | B46: Philadelphia 76ers Moneyline (v Washington) | C46: Betano | D46: -375 | E46: 295 | F46: -250 | G46: =IF(AND(D46<0,E46<0),(D46*E46-100*D46)/(2*D46*E46-100*D46-100*E46),IF(OR(AND(D46<0,E46>0),AND(D46>0,E46<0)),IF(D46<=E46,(100*D46+D46*E46)/(200*D46+D46*E46-10000),(100*E46-10000)/(200*E46+D46*E46-10000)),0)) -> 0.7571885 | H46: =IF(F46<0,G46+(1-G46)*(F46/100),IF(F46>0,G46-(1-G46)*(100/F46),0))*$O$2/2 -> 375.39936 | I46: 189.78 | J46: =IF(F46<0,I46/(F46/-100),I46*F46/100) -> 75.912 | K46: =G46*J46-(1-G46)*I46 -> 11.398927 | L46: =IF(F46>0,(G46*F46/100-(1-G46)),IF(F46<0,(G46*100/-F46-(1-G46)),0)) -> 0.060063898 | M46: Y | N46: =IF(ISERROR(SEARCH("(Bonus Bet)",B46)),IF(M46="Y",J46,IF(M46="N",-I46,0)),IF(M46="N",0,IF(M46="Y",J46,0))) -> 75.912 | R46: WEEK 7 | S46: 45298 | T46: {=SUM(_xlfn._xlws.FILTER(N:N,A:A=S46,0))} -> 1596.0051 | U46: =U45+T46 -> 8664.1223 | V46: {=SUM(_xlfn._xlws.FILTER(I:I,A:A=S46,0))} -> 4831.21 | W46: {=COUNT(_xlfn._xlws.FILTER(I:I,A:A=S46,""))} -> 52 | X46: {=SUM(_xlfn._xlws.FILTER(K:K,A:A=S46,0))} -> 304.91859 | Y46: =Y45+X46 -> 4005.8771 | AD46: 0.5407914 | AE46: 5 | AF46: =COUNTIFS($G$2:$G$4000,AD46,$M$2:$M$4000,"=Y")/AE46 -> 0.8 | AG46: =AD46-AF46 -> -0.2592086 | AK46: 0.047034167 | AL46: 1 | AM46: =COUNTIFS($G$2:$G$4000,AK46,$M$2:$M$4000,"=Y") -> 0 | AO46: =IF(D46<0,I46/(D46/-100),I46*D46/100) -> 50.608 | AP46: =IF(ISERROR(SEARCH("(Bonus Bet)",B46)),IF(M46="Y",AO46,IF(M46="N",-I46,0)),IF(M46="N",0,IF(M46="Y",AO46,0))) -> 50.608 | AQ46: =N46 -> 75.912 | AR46: =AQ46-AP46+AR45 -> 1014.3557
A47: 45264 | B47: CJ McCollum Over 3.5 Rebounds | C47: Bet365 | D47: -144 | E47: 120 | F47: -115 | G47: =IF(AND(D47<0,E47<0),(D47*E47-100*D47)/(2*D47*E47-100*D47-100*E47),IF(OR(AND(D47<0,E47>0),AND(D47>0,E47<0)),IF(D47<=E47,(100*D47+D47*E47)/(200*D47+D47*E47-10000),(100*E47-10000)/(200*E47+D47*E47-10000)),0)) -> 0.56490728 | H47: =IF(F47<0,G47+(1-G47)*(F47/100),IF(F47>0,G47-(1-G47)*(100/F47),0))*$O$2/2 -> 161.3766 | I47: 200 | J47: =IF(F47<0,I47/(F47/-100),I47*F47/100) -> 173.91304 | K47: =G47*J47-(1-G47)*I47 -> 11.226199 | L47: =IF(F47>0,(G47*F47/100-(1-G47)),IF(F47<0,(G47*100/-F47-(1-G47)),0)) -> 0.056130993 | M47: N | N47: =IF(ISERROR(SEARCH("(Bonus Bet)",B47)),IF(M47="Y",J47,IF(M47="N",-I47,0)),IF(M47="N",0,IF(M47="Y",J47,0))) -> -200 | R47: =SUM(T46:T52) -> 2488.1355 | S47: 45299 | T47: {=SUM(_xlfn._xlws.FILTER(N:N,A:A=S47,0))} -> 113.12931 | U47: =U46+T47 -> 8777.2516 | V47: {=SUM(_xlfn._xlws.FILTER(I:I,A:A=S47,0))} -> 2946.96 | W47: {=COUNT(_xlfn._xlws.FILTER(I:I,A:A=S47,""))} -> 38 | X47: {=SUM(_xlfn._xlws.FILTER(K:K,A:A=S47,0))} -> 141.09605 | Y47: =Y46+X47 -> 4146.9731 | AD47: 0.77759302 | AE47: 1 | AF47: =COUNTIFS($G$2:$G$4000,AD47,$M$2:$M$4000,"=Y")/AE47 -> 1 | AG47: =AD47-AF47 -> -0.22240698 | AK47: 0.037940945 | AL47: 1 | AM47: =COUNTIFS($G$2:$G$4000,AK47,$M$2:$M$4000,"=Y") -> 0 | AO47: =IF(D47<0,I47/(D47/-100),I47*D47/100) -> 138.88889 | AP47: =IF(ISERROR(SEARCH("(Bonus Bet)",B47)),IF(M47="Y",AO47,IF(M47="N",-I47,0)),IF(M47="N",0,IF(M47="Y",AO47,0))) -> -200 | AQ47: =N47 -> -200 | AR47: =AQ47-AP47+AR46 -> 1014.3557
A48: 45265 | B48: Tyler Toffoli Under 0.5 PowerPlay Points | C48: BetRivers | D48: -450 | E48: 255 | F48: -250 | G48: =IF(AND(D48<0,E48<0),(D48*E48-100*D48)/(2*D48*E48-100*D48-100*E48),IF(OR(AND(D48<0,E48>0),AND(D48>0,E48<0)),IF(D48<=E48,(100*D48+D48*E48)/(200*D48+D48*E48-10000),(100*E48-10000)/(200*E48+D48*E48-10000)),0)) -> 0.74388824 | H48: =IF(F48<0,G48+(1-G48)*(F48/100),IF(F48>0,G48-(1-G48)*(100/F48),0))*$O$2/2 -> 259.02212 | I48: 144.33 | J48: =IF(F48<0,I48/(F48/-100),I48*F48/100) -> 57.732 | K48: =G48*J48-(1-G48)*I48 -> 5.981546 | L48: =IF(F48>0,(G48*F48/100-(1-G48)),IF(F48<0,(G48*100/-F48-(1-G48)),0)) -> 0.041443539 | M48: Y | N48: =IF(ISERROR(SEARCH("(Bonus Bet)",B48)),IF(M48="Y",J48,IF(M48="N",-I48,0)),IF(M48="N",0,IF(M48="Y",J48,0))) -> 57.732 | S48: 45300 | T48: {=SUM(_xlfn._xlws.FILTER(N:N,A:A=S48,0))} -> -47.491684 | U48: =U47+T48 -> 8729.7599 | V48: {=SUM(_xlfn._xlws.FILTER(I:I,A:A=S48,0))} -> 3617.33 | W48: {=COUNT(_xlfn._xlws.FILTER(I:I,A:A=S48,""))} -> 44 | X48: {=SUM(_xlfn._xlws.FILTER(K:K,A:A=S48,0))} -> 199.14558 | Y48: =Y47+X48 -> 4346.1187 | AD48: 0.58923868 | AE48: 1 | AF48: =COUNTIFS($G$2:$G$4000,AD48,$M$2:$M$4000,"=Y")/AE48 -> 1 | AG48: =AD48-AF48 -> -0.41076132 | AK48: 0.050552953 | AL48: 1 | AM48: =COUNTIFS($G$2:$G$4000,AK48,$M$2:$M$4000,"=Y") -> 0 | AO48: =IF(D48<0,I48/(D48/-100),I48*D48/100) -> 32.073333 | AP48: =IF(ISERROR(SEARCH("(Bonus Bet)",B48)),IF(M48="Y",AO48,IF(M48="N",-I48,0)),IF(M48="N",0,IF(M48="Y",AO48,0))) -> 32.073333 | AQ48: =N48 -> 57.732 | AR48: =AQ48-AP48+AR47 -> 1040.0144
A49: 45265 | B49: Jack Hughes Under 0.5 PowerPlay Points | C49: BetRivers/NorthStar | D49: -250 | E49: 175 | F49: -167 | G49: =IF(AND(D49<0,E49<0),(D49*E49-100*D49)/(2*D49*E49-100*D49-100*E49),IF(OR(AND(D49<0,E49>0),AND(D49>0,E49<0)),IF(D49<=E49,(100*D49+D49*E49)/(200*D49+D49*E49-10000),(100*E49-10000)/(200*E49+D49*E49-10000)),0)) -> 0.6626506 | H49: =IF(F49<0,G49+(1-G49)*(F49/100),IF(F49>0,G49-(1-G49)*(100/F49),0))*$O$2/2 -> 248.19277 | I49: 258.1 | J49: =IF(F49<0,I49/(F49/-100),I49*F49/100) -> 154.5509 | K49: =G49*J49-(1-G49)*I49 -> 15.343366 | L49: =IF(F49>0,(G49*F49/100-(1-G49)),IF(F49<0,(G49*100/-F49-(1-G49)),0)) -> 0.05944737 | M49: N | N49: =IF(ISERROR(SEARCH("(Bonus Bet)",B49)),IF(M49="Y",J49,IF(M49="N",-I49,0)),IF(M49="N",0,IF(M49="Y",J49,0))) -> -258.1 | S49: 45301 | T49: {=SUM(_xlfn._xlws.FILTER(N:N,A:A=S49,0))} -> 755.67973 | U49: =U48+T49 -> 9485.4396 | V49: {=SUM(_xlfn._xlws.FILTER(I:I,A:A=S49,0))} -> 2525.28 | W49: {=COUNT(_xlfn._xlws.FILTER(I:I,A:A=S49,""))} -> 35 | X49: {=SUM(_xlfn._xlws.FILTER(K:K,A:A=S49,0))} -> 116.26254 | Y49: =Y48+X49 -> 4462.3813 | AD49: 0.70657545 | AE49: 1 | AF49: =COUNTIFS($G$2:$G$4000,AD49,$M$2:$M$4000,"=Y")/AE49 -> 1 | AG49: =AD49-AF49 -> -0.29342455 | AO49: =IF(D49<0,I49/(D49/-100),I49*D49/100) -> 103.24 | AP49: =IF(ISERROR(SEARCH("(Bonus Bet)",B49)),IF(M49="Y",AO49,IF(M49="N",-I49,0)),IF(M49="N",0,IF(M49="Y",AO49,0))) -> -258.1 | AQ49: =N49 -> -258.1 | AR49: =AQ49-AP49+AR48 -> 1040.0144
A50: 45265 | B50: Grayson Allen Under 6.5 Rebs + Assists | C50: Fanduel | D50: -135 | E50: 105 | F50: 104 | G50: =IF(AND(D50<0,E50<0),(D50*E50-100*D50)/(2*D50*E50-100*D50-100*E50),IF(OR(AND(D50<0,E50>0),AND(D50>0,E50<0)),IF(D50<=E50,(100*D50+D50*E50)/(200*D50+D50*E50-10000),(100*E50-10000)/(200*E50+D50*E50-10000)),0)) -> 0.5407914 | H50: =IF(F50<0,G50+(1-G50)*(F50/100),IF(F50>0,G50-(1-G50)*(100/F50),0))*$O$2/2 -> 248.11168 | I50: 200 | J50: =IF(F50<0,I50/(F50/-100),I50*F50/100) -> 208 | K50: =G50*J50-(1-G50)*I50 -> 20.642892 | L50: =IF(F50>0,(G50*F50/100-(1-G50)),IF(F50<0,(G50*100/-F50-(1-G50)),0)) -> 0.10321446 | M50: Y | N50: =IF(ISERROR(SEARCH("(Bonus Bet)",B50)),IF(M50="Y",J50,IF(M50="N",-I50,0)),IF(M50="N",0,IF(M50="Y",J50,0))) -> 208 | S50: 45302 | T50: {=SUM(_xlfn._xlws.FILTER(N:N,A:A=S50,0))} -> -636.14467 | U50: =U49+T50 -> 8849.295 | V50: {=SUM(_xlfn._xlws.FILTER(I:I,A:A=S50,0))} -> 4471.34 | W50: {=COUNT(_xlfn._xlws.FILTER(I:I,A:A=S50,""))} -> 55 | X50: {=SUM(_xlfn._xlws.FILTER(K:K,A:A=S50,0))} -> 305.73589 | Y50: =Y49+X50 -> 4768.1172 | AD50: 0.76237624 | AE50: 1 | AF50: =COUNTIFS($G$2:$G$4000,AD50,$M$2:$M$4000,"=Y")/AE50 -> 1 | AG50: =AD50-AF50 -> -0.23762376 | AO50: =IF(D50<0,I50/(D50/-100),I50*D50/100) -> 148.14815 | AP50: =IF(ISERROR(SEARCH("(Bonus Bet)",B50)),IF(M50="Y",AO50,IF(M50="N",-I50,0)),IF(M50="N",0,IF(M50="Y",AO50,0))) -> 148.14815 | AQ50: =N50 -> 208 | AR50: =AQ50-AP50+AR49 -> 1099.8662
A51: 45269 | B51: Bristol Bears Moneyline (v Lyon OU) | C51: BetRivers/NorthStar | D51: -435 | E51: 330 | F51: -315 | G51: =IF(AND(D51<0,E51<0),(D51*E51-100*D51)/(2*D51*E51-100*D51-100*E51),IF(OR(AND(D51<0,E51>0),AND(D51>0,E51<0)),IF(D51<=E51,(100*D51+D51*E51)/(200*D51+D51*E51-10000),(100*E51-10000)/(200*E51+D51*E51-10000)),0)) -> 0.77759302 | H51: =IF(F51<0,G51+(1-G51)*(F51/100),IF(F51>0,G51-(1-G51)*(100/F51),0))*$O$2/2 -> 192.52754 | I51: 255.71 | J51: =IF(F51<0,I51/(F51/-100),I51*F51/100) -> 81.177778 | K51: =G51*J51-(1-G51)*I51 -> 6.2515832 | L51: =IF(F51>0,(G51*F51/100-(1-G51)),IF(F51<0,(G51*100/-F51-(1-G51)),0)) -> 0.024447942 | M51: Y | N51: =IF(ISERROR(SEARCH("(Bonus Bet)",B51)),IF(M51="Y",J51,IF(M51="N",-I51,0)),IF(M51="N",0,IF(M51="Y",J51,0))) -> 81.177778 | S51: 45303 | T51: {=SUM(_xlfn._xlws.FILTER(N:N,A:A=S51,0))} -> 915.01358 | U51: =U50+T51 -> 9764.3085 | V51: {=SUM(_xlfn._xlws.FILTER(I:I,A:A=S51,0))} -> 3477.96 | W51: {=COUNT(_xlfn._xlws.FILTER(I:I,A:A=S51,""))} -> 42 | X51: {=SUM(_xlfn._xlws.FILTER(K:K,A:A=S51,0))} -> 165.71372 | Y51: =Y50+X51 -> 4933.8309 | AD51: 0.59717294 | AE51: 6 | AF51: =COUNTIFS($G$2:$G$4000,AD51,$M$2:$M$4000,"=Y")/AE51 -> 0.16666667 | AG51: =AD51-AF51 -> 0.43050627 | AO51: =IF(D51<0,I51/(D51/-100),I51*D51/100) -> 58.783908 | AP51: =IF(ISERROR(SEARCH("(Bonus Bet)",B51)),IF(M51="Y",AO51,IF(M51="N",-I51,0)),IF(M51="N",0,IF(M51="Y",AO51,0))) -> 58.783908 | AQ51: =N51 -> 81.177778 | AR51: =AQ51-AP51+AR50 -> 1122.2601
A52: 45279 | B52: Boris Mrcmar Moneyline | C52: BetVictor | D52: -162 | E52: 132 | F52: -125 | G52: =IF(AND(D52<0,E52<0),(D52*E52-100*D52)/(2*D52*E52-100*D52-100*E52),IF(OR(AND(D52<0,E52>0),AND(D52>0,E52<0)),IF(D52<=E52,(100*D52+D52*E52)/(200*D52+D52*E52-10000),(100*E52-10000)/(200*E52+D52*E52-10000)),0)) -> 0.58923868 | H52: =IF(F52<0,G52+(1-G52)*(F52/100),IF(F52>0,G52-(1-G52)*(100/F52),0))*$O$2/2 -> 189.46758 | I52: 205 | J52: =IF(F52<0,I52/(F52/-100),I52*F52/100) -> 164 | K52: =G52*J52-(1-G52)*I52 -> 12.429073 | L52: =IF(F52>0,(G52*F52/100-(1-G52)),IF(F52<0,(G52*100/-F52-(1-G52)),0)) -> 0.060629625 | M52: Y | N52: =IF(ISERROR(SEARCH("(Bonus Bet)",B52)),IF(M52="Y",J52,IF(M52="N",-I52,0)),IF(M52="N",0,IF(M52="Y",J52,0))) -> 164 | S52: 45304 | T52: {=SUM(_xlfn._xlws.FILTER(N:N,A:A=S52,0))} -> -208.05583 | U52: =U51+T52 -> 9556.2527 | V52: {=SUM(_xlfn._xlws.FILTER(I:I,A:A=S52,0))} -> 5076.97 | W52: {=COUNT(_xlfn._xlws.FILTER(I:I,A:A=S52,""))} -> 46 | X52: {=SUM(_xlfn._xlws.FILTER(K:K,A:A=S52,0))} -> 201.56423 | Y52: =Y51+X52 -> 5135.3951 | AD52: 0.53385672 | AE52: 1 | AF52: =COUNTIFS($G$2:$G$4000,AD52,$M$2:$M$4000,"=Y")/AE52 -> 0 | AG52: =AD52-AF52 -> 0.53385672 | AO52: =IF(D52<0,I52/(D52/-100),I52*D52/100) -> 126.54321 | AP52: =IF(ISERROR(SEARCH("(Bonus Bet)",B52)),IF(M52="Y",AO52,IF(M52="N",-I52,0)),IF(M52="N",0,IF(M52="Y",AO52,0))) -> 126.54321 | AQ52: =N52 -> 164 | AR52: =AQ52-AP52+AR51 -> 1159.7169
A53: 45267 | B53: Partizan Moneyline (v Milano) | C53: TonyBet | D53: -286 | E53: 225 | F53: -154 | G53: =IF(AND(D53<0,E53<0),(D53*E53-100*D53)/(2*D53*E53-100*D53-100*E53),IF(OR(AND(D53<0,E53>0),AND(D53>0,E53<0)),IF(D53<=E53,(100*D53+D53*E53)/(200*D53+D53*E53-10000),(100*E53-10000)/(200*E53+D53*E53-10000)),0)) -> 0.70657545 | H53: =IF(F53<0,G53+(1-G53)*(F53/100),IF(F53>0,G53-(1-G53)*(100/F53),0))*$O$2/2 -> 636.75409 | I53: 57.96 | J53: =IF(F53<0,I53/(F53/-100),I53*F53/100) -> 37.636364 | K53: =G53*J53-(1-G53)*I53 -> 9.5860433 | L53: =IF(F53>0,(G53*F53/100-(1-G53)),IF(F53<0,(G53*100/-F53-(1-G53)),0)) -> 0.16539067 | M53: Y | N53: =IF(ISERROR(SEARCH("(Bonus Bet)",B53)),IF(M53="Y",J53,IF(M53="N",-I53,0)),IF(M53="N",0,IF(M53="Y",J53,0))) -> 37.636364 | R53: WEEK 8 | S53: 45305 | T53: {=SUM(_xlfn._xlws.FILTER(N:N,A:A=S53,0))} -> -359.74436 | U53: =U52+T53 -> 9196.5083 | V53: {=SUM(_xlfn._xlws.FILTER(I:I,A:A=S53,0))} -> 1475 | W53: {=COUNT(_xlfn._xlws.FILTER(I:I,A:A=S53,""))} -> 12 | X53: {=SUM(_xlfn._xlws.FILTER(K:K,A:A=S53,0))} -> 72.939727 | Y53: =Y52+X53 -> 5208.3348 | AD53: 0.62962963 | AE53: 1 | AF53: =COUNTIFS($G$2:$G$4000,AD53,$M$2:$M$4000,"=Y")/AE53 -> 1 | AG53: =AD53-AF53 -> -0.37037037 | AO53: =IF(D53<0,I53/(D53/-100),I53*D53/100) -> 20.265734 | AP53: =IF(ISERROR(SEARCH("(Bonus Bet)",B53)),IF(M53="Y",AO53,IF(M53="N",-I53,0)),IF(M53="N",0,IF(M53="Y",AO53,0))) -> 20.265734 | AQ53: =N53 -> 37.636364 | AR53: =AQ53-AP53+AR52 -> 1177.0875
A54: 45266 | B54: Jason Robertson Under 0.5 PowerPlay Points | C54: BetRivers/NorthStar | D54: -500 | E54: 285 | F54: -275 | G54: =IF(AND(D54<0,E54<0),(D54*E54-100*D54)/(2*D54*E54-100*D54-100*E54),IF(OR(AND(D54<0,E54>0),AND(D54>0,E54<0)),IF(D54<=E54,(100*D54+D54*E54)/(200*D54+D54*E54-10000),(100*E54-10000)/(200*E54+D54*E54-10000)),0)) -> 0.76237624 | H54: =IF(F54<0,G54+(1-G54)*(F54/100),IF(F54>0,G54-(1-G54)*(100/F54),0))*$O$2/2 -> 272.27723 | I54: 122.34 | J54: =IF(F54<0,I54/(F54/-100),I54*F54/100) -> 44.487273 | K54: =G54*J54-(1-G54)*I54 -> 4.8451485 | L54: =IF(F54>0,(G54*F54/100-(1-G54)),IF(F54<0,(G54*100/-F54-(1-G54)),0)) -> 0.03960396 | M54: Y | N54: =IF(ISERROR(SEARCH("(Bonus Bet)",B54)),IF(M54="Y",J54,IF(M54="N",-I54,0)),IF(M54="N",0,IF(M54="Y",J54,0))) -> 44.487273 | R54: =SUM(T53:T59) -> 3667.7107 | S54: 45306 | T54: {=SUM(_xlfn._xlws.FILTER(N:N,A:A=S54,0))} -> 920.6453 | U54: =U53+T54 -> 10117.154 | V54: {=SUM(_xlfn._xlws.FILTER(I:I,A:A=S54,0))} -> 4717.04 | W54: {=COUNT(_xlfn._xlws.FILTER(I:I,A:A=S54,""))} -> 57 | X54: {=SUM(_xlfn._xlws.FILTER(K:K,A:A=S54,0))} -> 171.99221 | Y54: =Y53+X54 -> 5380.3271 | AD54: 0.58459743 | AE54: 4 | AF54: =COUNTIFS($G$2:$G$4000,AD54,$M$2:$M$4000,"=Y")/AE54 -> 0.75 | AG54: =AD54-AF54 -> -0.16540257 | AO54: =IF(D54<0,I54/(D54/-100),I54*D54/100) -> 24.468 | AP54: =IF(ISERROR(SEARCH("(Bonus Bet)",B54)),IF(M54="Y",AO54,IF(M54="N",-I54,0)),IF(M54="N",0,IF(M54="Y",AO54,0))) -> 24.468 | AQ54: =N54 -> 44.487273 | AR54: =AQ54-AP54+AR53 -> 1197.1068
A55: 45266 | B55: Jabari Smith Jr. Under 9.5 Rebounds | C55: Betano | D55: -177 | E55: 132 | F55: -114 | G55: =IF(AND(D55<0,E55<0),(D55*E55-100*D55)/(2*D55*E55-100*D55-100*E55),IF(OR(AND(D55<0,E55>0),AND(D55>0,E55<0)),IF(D55<=E55,(100*D55+D55*E55)/(200*D55+D55*E55-10000),(100*E55-10000)/(200*E55+D55*E55-10000)),0)) -> 0.59717294 | H55: =IF(F55<0,G55+(1-G55)*(F55/100),IF(F55>0,G55-(1-G55)*(100/F55),0))*$O$2/2 -> 344.87523 | I55: 65.5 | J55: =IF(F55<0,I55/(F55/-100),I55*F55/100) -> 57.45614 | K55: =G55*J55-(1-G55)*I55 -> 7.9260797 | L55: =IF(F55>0,(G55*F55/100-(1-G55)),IF(F55<0,(G55*100/-F55-(1-G55)),0)) -> 0.12100885 | M55: N | N55: =IF(ISERROR(SEARCH("(Bonus Bet)",B55)),IF(M55="Y",J55,IF(M55="N",-I55,0)),IF(M55="N",0,IF(M55="Y",J55,0))) -> -65.5 | S55: 45307 | T55: {=SUM(_xlfn._xlws.FILTER(N:N,A:A=S55,0))} -> -1009.6728 | U55: =U54+T55 -> 9107.4809 | V55: {=SUM(_xlfn._xlws.FILTER(I:I,A:A=S55,0))} -> 2226.11 | W55: {=COUNT(_xlfn._xlws.FILTER(I:I,A:A=S55,""))} -> 25 | X55: {=SUM(_xlfn._xlws.FILTER(K:K,A:A=S55,0))} -> 102.58169 | Y55: =Y54+X55 -> 5482.9087 | AD55: 0.5794621 | AE55: 1 | AF55: =COUNTIFS($G$2:$G$4000,AD55,$M$2:$M$4000,"=Y")/AE55 -> 1 | AG55: =AD55-AF55 -> -0.4205379 | AO55: =IF(D55<0,I55/(D55/-100),I55*D55/100) -> 37.00565 | AP55: =IF(ISERROR(SEARCH("(Bonus Bet)",B55)),IF(M55="Y",AO55,IF(M55="N",-I55,0)),IF(M55="N",0,IF(M55="Y",AO55,0))) -> -65.5 | AQ55: =N55 -> -65.5 | AR55: =AQ55-AP55+AR54 -> 1197.1068
A56: 45266 | B56: Desmond Bane Under 4.5 Rebounds | C56: Bet888 | D56: -128 | E56: 104 | F56: 100 | G56: =IF(AND(D56<0,E56<0),(D56*E56-100*D56)/(2*D56*E56-100*D56-100*E56),IF(OR(AND(D56<0,E56>0),AND(D56>0,E56<0)),IF(D56<=E56,(100*D56+D56*E56)/(200*D56+D56*E56-10000),(100*E56-10000)/(200*E56+D56*E56-10000)),0)) -> 0.53385672 | H56: =IF(F56<0,G56+(1-G56)*(F56/100),IF(F56>0,G56-(1-G56)*(100/F56),0))*$O$2/2 -> 169.28361 | I56: 42.55 | J56: =IF(F56<0,I56/(F56/-100),I56*F56/100) -> 42.55 | K56: =G56*J56-(1-G56)*I56 -> 2.8812071 | L56: =IF(F56>0,(G56*F56/100-(1-G56)),IF(F56<0,(G56*100/-F56-(1-G56)),0)) -> 0.067713445 | M56: N | N56: =IF(ISERROR(SEARCH("(Bonus Bet)",B56)),IF(M56="Y",J56,IF(M56="N",-I56,0)),IF(M56="N",0,IF(M56="Y",J56,0))) -> -42.55 | S56: 45308 | T56: {=SUM(_xlfn._xlws.FILTER(N:N,A:A=S56,0))} -> 1669.5719 | U56: =U55+T56 -> 10777.053 | V56: {=SUM(_xlfn._xlws.FILTER(I:I,A:A=S56,0))} -> 4781.49 | W56: {=COUNT(_xlfn._xlws.FILTER(I:I,A:A=S56,""))} -> 48 | X56: {=SUM(_xlfn._xlws.FILTER(K:K,A:A=S56,0))} -> 239.24317 | Y56: =Y55+X56 -> 5722.1519 | AD56: 0.63855422 | AE56: 3 | AF56: =COUNTIFS($G$2:$G$4000,AD56,$M$2:$M$4000,"=Y")/AE56 -> 1 | AG56: =AD56-AF56 -> -0.36144578 | AO56: =IF(D56<0,I56/(D56/-100),I56*D56/100) -> 33.242188 | AP56: =IF(ISERROR(SEARCH("(Bonus Bet)",B56)),IF(M56="Y",AO56,IF(M56="N",-I56,0)),IF(M56="N",0,IF(M56="Y",AO56,0))) -> -42.55 | AQ56: =N56 -> -42.55 | AR56: =AQ56-AP56+AR55 -> 1197.1068
A57: 45269 | B57: Luana Santos Moneyline | C57: NorthStar | D57: -200 | E57: 155 | F57: -148 | G57: =IF(AND(D57<0,E57<0),(D57*E57-100*D57)/(2*D57*E57-100*D57-100*E57),IF(OR(AND(D57<0,E57>0),AND(D57>0,E57<0)),IF(D57<=E57,(100*D57+D57*E57)/(200*D57+D57*E57-10000),(100*E57-10000)/(200*E57+D57*E57-10000)),0)) -> 0.62962963 | H57: =IF(F57<0,G57+(1-G57)*(F57/100),IF(F57>0,G57-(1-G57)*(100/F57),0))*$O$2/2 -> 203.7037 | I57: 200 | J57: =IF(F57<0,I57/(F57/-100),I57*F57/100) -> 135.13514 | K57: =G57*J57-(1-G57)*I57 -> 11.011011 | L57: =IF(F57>0,(G57*F57/100-(1-G57)),IF(F57<0,(G57*100/-F57-(1-G57)),0)) -> 0.055055055 | M57: Y | N57: =IF(ISERROR(SEARCH("(Bonus Bet)",B57)),IF(M57="Y",J57,IF(M57="N",-I57,0)),IF(M57="N",0,IF(M57="Y",J57,0))) -> 135.13514 | S57: 45309 | T57: {=SUM(_xlfn._xlws.FILTER(N:N,A:A=S57,0))} -> 734.64405 | U57: =U56+T57 -> 11511.697 | V57: {=SUM(_xlfn._xlws.FILTER(I:I,A:A=S57,0))} -> 3536.96 | W57: {=COUNT(_xlfn._xlws.FILTER(I:I,A:A=S57,""))} -> 34 | X57: {=SUM(_xlfn._xlws.FILTER(K:K,A:A=S57,0))} -> 193.41326 | Y57: =Y56+X57 -> 5915.5652 | AD57: 0.67557252 | AE57: 1 | AF57: =COUNTIFS($G$2:$G$4000,AD57,$M$2:$M$4000,"=Y")/AE57 -> 1 | AG57: =AD57-AF57 -> -0.32442748 | AO57: =IF(D57<0,I57/(D57/-100),I57*D57/100) -> 100 | AP57: =IF(ISERROR(SEARCH("(Bonus Bet)",B57)),IF(M57="Y",AO57,IF(M57="N",-I57,0)),IF(M57="N",0,IF(M57="Y",AO57,0))) -> 100 | AQ57: =N57 -> 135.13514 | AR57: =AQ57-AP57+AR56 -> 1232.2419
A58: 45266 | B58: Jabari Smith Jr. Under 9.5 Rebounds | C58: Betano | D58: -167 | E58: 125 | F58: -118 | G58: =IF(AND(D58<0,E58<0),(D58*E58-100*D58)/(2*D58*E58-100*D58-100*E58),IF(OR(AND(D58<0,E58>0),AND(D58>0,E58<0)),IF(D58<=E58,(100*D58+D58*E58)/(200*D58+D58*E58-10000),(100*E58-10000)/(200*E58+D58*E58-10000)),0)) -> 0.58459743 | H58: =IF(F58<0,G58+(1-G58)*(F58/100),IF(F58>0,G58-(1-G58)*(100/F58),0))*$O$2/2 -> 236.05601 | I58: 127.24 | J58: =IF(F58<0,I58/(F58/-100),I58*F58/100) -> 107.83051 | K58: =G58*J58-(1-G58)*I58 -> 10.181616 | L58: =IF(F58>0,(G58*F58/100-(1-G58)),IF(F58<0,(G58*100/-F58-(1-G58)),0)) -> 0.080018986 | M58: N | N58: =IF(ISERROR(SEARCH("(Bonus Bet)",B58)),IF(M58="Y",J58,IF(M58="N",-I58,0)),IF(M58="N",0,IF(M58="Y",J58,0))) -> -127.24 | S58: 45310 | T58: {=SUM(_xlfn._xlws.FILTER(N:N,A:A=S58,0))} -> 776.46317 | U58: =U57+T58 -> 12288.16 | V58: {=SUM(_xlfn._xlws.FILTER(I:I,A:A=S58,0))} -> 2799.27 | W58: {=COUNT(_xlfn._xlws.FILTER(I:I,A:A=S58,""))} -> 36 | X58: {=SUM(_xlfn._xlws.FILTER(K:K,A:A=S58,0))} -> 112.51019 | Y58: =Y57+X58 -> 6028.0754 | AD58: 0.5992714 | AE58: 2 | AF58: =COUNTIFS($G$2:$G$4000,AD58,$M$2:$M$4000,"=Y")/AE58 -> 0 | AG58: =AD58-AF58 -> 0.5992714 | AO58: =IF(D58<0,I58/(D58/-100),I58*D58/100) -> 76.191617 | AP58: =IF(ISERROR(SEARCH("(Bonus Bet)",B58)),IF(M58="Y",AO58,IF(M58="N",-I58,0)),IF(M58="N",0,IF(M58="Y",AO58,0))) -> -127.24 | AQ58: =N58 -> -127.24 | AR58: =AQ58-AP58+AR57 -> 1232.2419
A59: 45266 | B59: Chet Holmgren Under 1.5 Threes Made | C59: Bet365 | D59: -158 | E59: 125 | F59: -110 | G59: =IF(AND(D59<0,E59<0),(D59*E59-100*D59)/(2*D59*E59-100*D59-100*E59),IF(OR(AND(D59<0,E59>0),AND(D59>0,E59<0)),IF(D59<=E59,(100*D59+D59*E59)/(200*D59+D59*E59-10000),(100*E59-10000)/(200*E59+D59*E59-10000)),0)) -> 0.5794621 | H59: =IF(F59<0,G59+(1-G59)*(F59/100),IF(F59>0,G59-(1-G59)*(100/F59),0))*$O$2/2 -> 292.17604 | I59: 200 | J59: =IF(F59<0,I59/(F59/-100),I59*F59/100) -> 181.81818 | K59: =G59*J59-(1-G59)*I59 -> 21.249166 | L59: =IF(F59>0,(G59*F59/100-(1-G59)),IF(F59<0,(G59*100/-F59-(1-G59)),0)) -> 0.10624583 | M59: Y | N59: =IF(ISERROR(SEARCH("(Bonus Bet)",B59)),IF(M59="Y",J59,IF(M59="N",-I59,0)),IF(M59="N",0,IF(M59="Y",J59,0))) -> 181.81818 | S59: 45311 | T59: {=SUM(_xlfn._xlws.FILTER(N:N,A:A=S59,0))} -> 935.80345 | U59: =U58+T59 -> 13223.963 | V59: {=SUM(_xlfn._xlws.FILTER(I:I,A:A=S59,0))} -> 6227.58 | W59: {=COUNT(_xlfn._xlws.FILTER(I:I,A:A=S59,""))} -> 59 | X59: {=SUM(_xlfn._xlws.FILTER(K:K,A:A=S59,0))} -> 293.54078 | Y59: =Y58+X59 -> 6321.6161 | AD59: 0.76806423 | AE59: 1 | AF59: =COUNTIFS($G$2:$G$4000,AD59,$M$2:$M$4000,"=Y")/AE59 -> 0 | AG59: =AD59-AF59 -> 0.76806423 | AO59: =IF(D59<0,I59/(D59/-100),I59*D59/100) -> 126.58228 | AP59: =IF(ISERROR(SEARCH("(Bonus Bet)",B59)),IF(M59="Y",AO59,IF(M59="N",-I59,0)),IF(M59="N",0,IF(M59="Y",AO59,0))) -> 126.58228 | AQ59: =N59 -> 181.81818 | AR59: =AQ59-AP59+AR58 -> 1287.4778
A60: 45266 | B60: Derrick Jones Jr. Over 0.5 Steals | C60: Fanduel | D60: -200 | E60: 165 | F60: -135 | G60: =IF(AND(D60<0,E60<0),(D60*E60-100*D60)/(2*D60*E60-100*D60-100*E60),IF(OR(AND(D60<0,E60>0),AND(D60>0,E60<0)),IF(D60<=E60,(100*D60+D60*E60)/(200*D60+D60*E60-10000),(100*E60-10000)/(200*E60+D60*E60-10000)),0)) -> 0.63855422 | H60: =IF(F60<0,G60+(1-G60)*(F60/100),IF(F60>0,G60-(1-G60)*(100/F60),0))*$O$2/2 -> 376.50602 | I60: 44 | J60: =IF(F60<0,I60/(F60/-100),I60*F60/100) -> 32.592593 | K60: =G60*J60-(1-G60)*I60 -> 4.908523 | L60: =IF(F60>0,(G60*F60/100-(1-G60)),IF(F60<0,(G60*100/-F60-(1-G60)),0)) -> 0.11155734 | M60: Y | N60: =IF(ISERROR(SEARCH("(Bonus Bet)",B60)),IF(M60="Y",J60,IF(M60="N",-I60,0)),IF(M60="N",0,IF(M60="Y",J60,0))) -> 32.592593 | R60: WEEK 9 | S60: 45312 | T60: {=SUM(_xlfn._xlws.FILTER(N:N,A:A=S60,0))} -> 370.20204 | U60: =U59+T60 -> 13594.165 | V60: {=SUM(_xlfn._xlws.FILTER(I:I,A:A=S60,0))} -> 5005.27 | W60: {=COUNT(_xlfn._xlws.FILTER(I:I,A:A=S60,""))} -> 50 | X60: {=SUM(_xlfn._xlws.FILTER(K:K,A:A=S60,0))} -> 232.8171 | Y60: =Y59+X60 -> 6554.4332 | AD60: 0.68539326 | AE60: 2 | AF60: =COUNTIFS($G$2:$G$4000,AD60,$M$2:$M$4000,"=Y")/AE60 -> 0.5 | AG60: =AD60-AF60 -> 0.18539326 | AO60: =IF(D60<0,I60/(D60/-100),I60*D60/100) -> 22 | AP60: =IF(ISERROR(SEARCH("(Bonus Bet)",B60)),IF(M60="Y",AO60,IF(M60="N",-I60,0)),IF(M60="N",0,IF(M60="Y",AO60,0))) -> 22 | AQ60: =N60 -> 32.592593 | AR60: =AQ60-AP60+AR59 -> 1298.0704
A61: 45266 | B61: Shai Gilgeous-Alexander Under 1.5 Threes | C61: BetRivers | D61: -240 | E61: 195 | F61: -182 | G61: =IF(AND(D61<0,E61<0),(D61*E61-100*D61)/(2*D61*E61-100*D61-100*E61),IF(OR(AND(D61<0,E61>0),AND(D61>0,E61<0)),IF(D61<=E61,(100*D61+D61*E61)/(200*D61+D61*E61-10000),(100*E61-10000)/(200*E61+D61*E61-10000)),0)) -> 0.67557252 | H61: =IF(F61<0,G61+(1-G61)*(F61/100),IF(F61>0,G61-(1-G61)*(100/F61),0))*$O$2/2 -> 212.78626 | I61: 60.13 | J61: =IF(F61<0,I61/(F61/-100),I61*F61/100) -> 33.038462 | K61: =G61*J61-(1-G61)*I61 -> 2.8120523 | L61: =IF(F61>0,(G61*F61/100-(1-G61)),IF(F61<0,(G61*100/-F61-(1-G61)),0)) -> 0.046766211 | M61: Y | N61: =IF(ISERROR(SEARCH("(Bonus Bet)",B61)),IF(M61="Y",J61,IF(M61="N",-I61,0)),IF(M61="N",0,IF(M61="Y",J61,0))) -> 33.038462 | R61: =SUM(T60:T66) -> 4177.425 | S61: 45313 | T61: {=SUM(_xlfn._xlws.FILTER(N:N,A:A=S61,0))} -> 580.46304 | U61: =U60+T61 -> 14174.628 | V61: {=SUM(_xlfn._xlws.FILTER(I:I,A:A=S61,0))} -> 5200.1 | W61: {=COUNT(_xlfn._xlws.FILTER(I:I,A:A=S61,""))} -> 51 | X61: {=SUM(_xlfn._xlws.FILTER(K:K,A:A=S61,0))} -> 292.06463 | Y61: =Y60+X61 -> 6846.4979 | AD61: 0.57983193 | AE61: 1 | AF61: =COUNTIFS($G$2:$G$4000,AD61,$M$2:$M$4000,"=Y")/AE61 -> 0 | AG61: =AD61-AF61 -> 0.57983193 | AO61: =IF(D61<0,I61/(D61/-100),I61*D61/100) -> 25.054167 | AP61: =IF(ISERROR(SEARCH("(Bonus Bet)",B61)),IF(M61="Y",AO61,IF(M61="N",-I61,0)),IF(M61="N",0,IF(M61="Y",AO61,0))) -> 25.054167 | AQ61: =N61 -> 33.038462 | AR61: =AQ61-AP61+AR60 -> 1306.0547
A62: 45266 | B62: Ochai Agbaji Under 9.5 Points | C62: BetMGM | D62: -175 | E62: 135 | F62: -105 | G62: =IF(AND(D62<0,E62<0),(D62*E62-100*D62)/(2*D62*E62-100*D62-100*E62),IF(OR(AND(D62<0,E62>0),AND(D62>0,E62<0)),IF(D62<=E62,(100*D62+D62*E62)/(200*D62+D62*E62-10000),(100*E62-10000)/(200*E62+D62*E62-10000)),0)) -> 0.5992714 | H62: =IF(F62<0,G62+(1-G62)*(F62/100),IF(F62>0,G62-(1-G62)*(100/F62),0))*$O$2/2 -> 446.26594 | I62: 37.03 | J62: =IF(F62<0,I62/(F62/-100),I62*F62/100) -> 35.266667 | K62: =G62*J62-(1-G62)*I62 -> 6.2953248 | L62: =IF(F62>0,(G62*F62/100-(1-G62)),IF(F62<0,(G62*100/-F62-(1-G62)),0)) -> 0.17000607 | M62: N | N62: =IF(ISERROR(SEARCH("(Bonus Bet)",B62)),IF(M62="Y",J62,IF(M62="N",-I62,0)),IF(M62="N",0,IF(M62="Y",J62,0))) -> -37.03 | S62: 45314 | T62: {=SUM(_xlfn._xlws.FILTER(N:N,A:A=S62,0))} -> 1705.7045 | U62: =U61+T62 -> 15880.333 | V62: {=SUM(_xlfn._xlws.FILTER(I:I,A:A=S62,0))} -> 5000.39 | W62: {=COUNT(_xlfn._xlws.FILTER(I:I,A:A=S62,""))} -> 57 | X62: {=SUM(_xlfn._xlws.FILTER(K:K,A:A=S62,0))} -> 208.25121 | Y62: =Y61+X62 -> 7054.7491 | AD62: 0.65968586 | AE62: 1 | AF62: =COUNTIFS($G$2:$G$4000,AD62,$M$2:$M$4000,"=Y")/AE62 -> 1 | AG62: =AD62-AF62 -> -0.34031414 | AO62: =IF(D62<0,I62/(D62/-100),I62*D62/100) -> 21.16 | AP62: =IF(ISERROR(SEARCH("(Bonus Bet)",B62)),IF(M62="Y",AO62,IF(M62="N",-I62,0)),IF(M62="N",0,IF(M62="Y",AO62,0))) -> -37.03 | AQ62: =N62 -> -37.03 | AR62: =AQ62-AP62+AR61 -> 1306.0547
A63: 45276 | B63: Ian Machado Garry Moneyline (v Vicente Luque) | C63: Bet365 | D63: -420 | E63: 310 | F63: -275 | G63: =IF(AND(D63<0,E63<0),(D63*E63-100*D63)/(2*D63*E63-100*D63-100*E63),IF(OR(AND(D63<0,E63>0),AND(D63>0,E63<0)),IF(D63<=E63,(100*D63+D63*E63)/(200*D63+D63*E63-10000),(100*E63-10000)/(200*E63+D63*E63-10000)),0)) -> 0.76806423 | H63: =IF(F63<0,G63+(1-G63)*(F63/100),IF(F63>0,G63-(1-G63)*(100/F63),0))*$O$2/2 -> 325.60214 | I63: 2.54 | J63: =IF(F63<0,I63/(F63/-100),I63*F63/100) -> 0.92363636 | K63: =G63*J63-(1-G63)*I63 -> 0.12029519 | L63: =IF(F63>0,(G63*F63/100-(1-G63)),IF(F63<0,(G63*100/-F63-(1-G63)),0)) -> 0.047360311 | M63: VOID | N63: =IF(ISERROR(SEARCH("(Bonus Bet)",B63)),IF(M63="Y",J63,IF(M63="N",-I63,0)),IF(M63="N",0,IF(M63="Y",J63,0))) -> 0 | S63: 45315 | T63: {=SUM(_xlfn._xlws.FILTER(N:N,A:A=S63,0))} -> -946.13077 | U63: =U62+T63 -> 14934.202 | V63: {=SUM(_xlfn._xlws.FILTER(I:I,A:A=S63,0))} -> 4626.11 | W63: {=COUNT(_xlfn._xlws.FILTER(I:I,A:A=S63,""))} -> 48 | X63: {=SUM(_xlfn._xlws.FILTER(K:K,A:A=S63,0))} -> 231.4023 | Y63: =Y62+X63 -> 7286.1514 | AD63: 0.8219093 | AE63: 1 | AF63: =COUNTIFS($G$2:$G$4000,AD63,$M$2:$M$4000,"=Y")/AE63 -> 1 | AG63: =AD63-AF63 -> -0.1780907 | AO63: =IF(D63<0,I63/(D63/-100),I63*D63/100) -> 0.6047619 | AP63: =IF(ISERROR(SEARCH("(Bonus Bet)",B63)),IF(M63="Y",AO63,IF(M63="N",-I63,0)),IF(M63="N",0,IF(M63="Y",AO63,0))) -> 0 | AQ63: =N63 -> 0 | AR63: =AQ63-AP63+AR62 -> 1306.0547
A64: 45268 | B64: Baskonia Moneyline (v Crvena Zvezda) | C64: BetRivers/NorthStar/Unibet | D64: -250 | E64: 205 | F64: -182 | G64: =IF(AND(D64<0,E64<0),(D64*E64-100*D64)/(2*D64*E64-100*D64-100*E64),IF(OR(AND(D64<0,E64>0),AND(D64>0,E64<0)),IF(D64<=E64,(100*D64+D64*E64)/(200*D64+D64*E64-10000),(100*E64-10000)/(200*E64+D64*E64-10000)),0)) -> 0.68539326 | H64: =IF(F64<0,G64+(1-G64)*(F64/100),IF(F64>0,G64-(1-G64)*(100/F64),0))*$O$2/2 -> 282.02247 | I64: 111.17 | J64: =IF(F64<0,I64/(F64/-100),I64*F64/100) -> 61.082418 | K64: =G64*J64-(1-G64)*I64 -> 6.8906458 | L64: =IF(F64>0,(G64*F64/100-(1-G64)),IF(F64<0,(G64*100/-F64-(1-G64)),0)) -> 0.061982961 | M64: Y | N64: =IF(ISERROR(SEARCH("(Bonus Bet)",B64)),IF(M64="Y",J64,IF(M64="N",-I64,0)),IF(M64="N",0,IF(M64="Y",J64,0))) -> 61.082418 | S64: 45316 | T64: {=SUM(_xlfn._xlws.FILTER(N:N,A:A=S64,0))} -> 1738.0826 | U64: =U63+T64 -> 16672.285 | V64: {=SUM(_xlfn._xlws.FILTER(I:I,A:A=S64,0))} -> 4716.37 | W64: {=COUNT(_xlfn._xlws.FILTER(I:I,A:A=S64,""))} -> 49 | X64: {=SUM(_xlfn._xlws.FILTER(K:K,A:A=S64,0))} -> 219.81036 | Y64: =Y63+X64 -> 7505.9617 | AD64: 0.6187291 | AE64: 1 | AF64: =COUNTIFS($G$2:$G$4000,AD64,$M$2:$M$4000,"=Y")/AE64 -> 1 | AG64: =AD64-AF64 -> -0.3812709 | AO64: =IF(D64<0,I64/(D64/-100),I64*D64/100) -> 44.468 | AP64: =IF(ISERROR(SEARCH("(Bonus Bet)",B64)),IF(M64="Y",AO64,IF(M64="N",-I64,0)),IF(M64="N",0,IF(M64="Y",AO64,0))) -> 44.468 | AQ64: =N64 -> 61.082418 | AR64: =AQ64-AP64+AR63 -> 1322.6691
A65: 45267 | B65: George Pickens Over 38.5 Receiving Yards | C65: BetMGM | D65: -150 | E65: 130 | F65: -120 | G65: =IF(AND(D65<0,E65<0),(D65*E65-100*D65)/(2*D65*E65-100*D65-100*E65),IF(OR(AND(D65<0,E65>0),AND(D65>0,E65<0)),IF(D65<=E65,(100*D65+D65*E65)/(200*D65+D65*E65-10000),(100*E65-10000)/(200*E65+D65*E65-10000)),0)) -> 0.57983193 | H65: =IF(F65<0,G65+(1-G65)*(F65/100),IF(F65>0,G65-(1-G65)*(100/F65),0))*$O$2/2 -> 189.07563 | I65: 118.16 | J65: =IF(F65<0,I65/(F65/-100),I65*F65/100) -> 98.466667 | K65: =G65*J65-(1-G65)*I65 -> 7.4470588 | L65: =IF(F65>0,(G65*F65/100-(1-G65)),IF(F65<0,(G65*100/-F65-(1-G65)),0)) -> 0.06302521 | M65: N | N65: =IF(ISERROR(SEARCH("(Bonus Bet)",B65)),IF(M65="Y",J65,IF(M65="N",-I65,0)),IF(M65="N",0,IF(M65="Y",J65,0))) -> -118.16 | S65: 45317 | T65: {=SUM(_xlfn._xlws.FILTER(N:N,A:A=S65,0))} -> -49.652468 | U65: =U64+T65 -> 16622.632 | V65: {=SUM(_xlfn._xlws.FILTER(I:I,A:A=S65,0))} -> 3578.04 | W65: {=COUNT(_xlfn._xlws.FILTER(I:I,A:A=S65,""))} -> 39 | X65: {=SUM(_xlfn._xlws.FILTER(K:K,A:A=S65,0))} -> 140.82835 | Y65: =Y64+X65 -> 7646.7901 | AD65: 0.57446809 | AE65: 1 | AF65: =COUNTIFS($G$2:$G$4000,AD65,$M$2:$M$4000,"=Y")/AE65 -> 0 | AG65: =AD65-AF65 -> 0.57446809 | AO65: =IF(D65<0,I65/(D65/-100),I65*D65/100) -> 78.773333 | AP65: =IF(ISERROR(SEARCH("(Bonus Bet)",B65)),IF(M65="Y",AO65,IF(M65="N",-I65,0)),IF(M65="N",0,IF(M65="Y",AO65,0))) -> -118.16 | AQ65: =N65 -> -118.16 | AR65: =AQ65-AP65+AR64 -> 1322.6691
